Workbook

Sheet DISPO Att (2)
A1: Republic of the Philippines
A2: PHILIPPINE NATIONAL POLICE | J2: =259-240 -> 19
A3: INFORMATION TECHNOLOGY MANAGEMENT SERVICE | J3: =134-63 -> 71
A4: Camp Bgen Rafael T Crame, Quezon City
A6: Disposition of Personnel (Crame-Based Only)
A7: (As of January 22, 2026)
A9: NO. | B9: OFFICE/DIVISION | C9: GENDER | D9: RANK | E9: LASTNAME | F9: FIRSTNAME | G9: MIDDLE NAME | H9: QUAL | I9: SIGNATURE | J9: ADDRESS | K9: CONTACT # | P9: NAME | Q9: ADDRESS
A10: 1 | B10: OD | C10: Male | D10: PCOL | E10: PALGUE | F10: ROMY | G10: INWAY
A11: 2 | B11: OD | C11: Male | D11: PCpl | E11: CERIL | F11: PAUL KELVIN | G11: LAROZA
A12: 3 | B12: OD | C12: Male | D12: Pat | E12: BEJARIN | F12: GERALD | G12: DADIRO | J12: Riang, Peñarrubia, Abra | K12: 09368167960 | P12: =CONCATENATE(E12," ",F12," ",G12) -> BEJARIN GERALD DADIRO | Q12: =IFERROR(VLOOKUP(P12,[1]Disposition!$AB$9:$AC$495,2,0),"NO RECORD YET") -> NO RECORD YET
A13: 4 | B13: OD | C13: Male | D13: Pat | E13: MORI | F13: LYNDON | G13: ACOSTA | J13: Caimito, Brgy. Buencag, Gerona, Tarlac | K13: 09091819560 | P13: =CONCATENATE(E13," ",F13," ",G13) -> MORI LYNDON ACOSTA | Q13: =IFERROR(VLOOKUP(P13,[1]Disposition!$AB$9:$AC$495,2,0),"NO RECORD YET") -> NO RECORD YET
A14: 5 | B14: OD | C14: Female | D14: NUP | E14: AVENDAÑO | F14: MA. FRELIE JOY | G14: (no middle name) | J14: #92 F Estrella St., San Juan, Malolos City, Bulacan | K14: 09554289264 | P14: =CONCATENATE(E14," ",F14," ",G14) -> AVENDAÑO MA. FRELIE JOY (no middle name) | Q14: =IFERROR(VLOOKUP(P14,[1]Disposition!$AB$9:$AC$495,2,0),"NO RECORD YET") -> #92 F Estrella St., San Juan, Malolos City, Bulacan
A15: 6 | B15: OD | C15: Female | D15: NUP | E15: LUZARA | F15: JEAN | G15: GRATUITO | J15: Blk 5 Lot 1 Orchid Extension, Capitol Park Homes Ii, Brgy 179 Zone 16, Caloocan City. | K15: 09177037934 | M15: 25 | P15: =CONCATENATE(E15," ",F15," ",G15) -> LUZARA JEAN GRATUITO | Q15: =IFERROR(VLOOKUP(P15,[1]Disposition!$AB$9:$AC$495,2,0),"NO RECORD YET") -> Blk 5 Lot 1 Orchid Extension, Capitol Park Homes II, Brgy 179 Zone 16, Caloocan City.
A16: 7 | B16: ODDA/DI | C16: Male | D16: PCOL | E16: TANGO | F16: FROILAN GENN | G16: GELACIO | H16: II | M16: 259 | P16: =CONCATENATE(E16," ",F16," ",G16) -> TANGO FROILAN GENN GELACIO
A17: 8 | B17: ODDA | C17: Male | D17: PMSg | E17: RESPICIO | F17: VIC BASKAR | G17: MADDARA | J17: Calamagui 2Nd, Isabela | K17: 09268096361 | M17: 134 | P17: =CONCATENATE(E17," ",F17," ",G17) -> RESPICIO VIC BASKAR MADDARA | Q17: =IFERROR(VLOOKUP(P17,[1]Disposition!$AB$9:$AC$495,2,0),"NO RECORD YET") -> Calamagui 2nd, Isabela
A18: 9 | B18: ODDA | C18: Female | D18: NUP | E18: ERIBAL | F18: JOZEL JOY | G18: FALAGNE | J18: 5A Diamond St., Jra Subd., Rosario, Pasug City | K18: 09617215961 | M18: 41 | P18: =CONCATENATE(E18," ",F18," ",G18) -> ERIBAL JOZEL JOY FALAGNE | Q18: =IFERROR(VLOOKUP(P18,[1]Disposition!$AB$9:$AC$495,2,0),"NO RECORD YET") -> 5A Diamond St., JRA Subd., Rosario, Pasug City
A19: 10 | B19: ODDA | C19: Female | D19: NUP | E19: SEMILLA | F19: FLORITES | G19: SARIO | J19: 18 C Dungo St., Brgy, Isabelita, San Juan City | K19: 09274390528 | M19: 40 | P19: =CONCATENATE(E19," ",F19," ",G19) -> SEMILLA FLORITES SARIO
A20: 11 | B20: DD for IT Matters | C20: Female | D20: NUP | E20: MATILLANO | F20: MINA HAYDEE | G20: BECERA | J20: B2 L17 Rose St., Venice Homes Subd., Cainta, Rizal | K20: 09266411836 | M20: 20 | P20: =CONCATENATE(E20," ",F20," ",G20) -> MATILLANO MINA HAYDEE BECERA | Q20: =IFERROR(VLOOKUP(P20,[1]Disposition!$AB$9:$AC$495,2,0),"NO RECORD YET") -> B2 L17 Rose St., Venice Homes Subd., Cainta, Rizal
A21: 12 | B21: ODDIT | C21: Female | D21: Pat | E21: PAPA | F21: MARIZ NICOLE | G21: ENGALAN | J21: 8H Road 6, 1st West Crame, San Juan City | K21: 09563393345 | M21: 30 | P21: =CONCATENATE(E21," ",F21," ",G21) -> PAPA MARIZ NICOLE ENGALAN | Q21: =IFERROR(VLOOKUP(P21,[1]Disposition!$AB$9:$AC$495,2,0),"NO RECORD YET") -> NO RECORD YET
A22: 13 | B22: ODDIT | C22: Female | D22: NUP | E22: BAGO | F22: REBECCA | G22: LLANEZA | J22: 196 Guyam Malaki, Indang, Cavite | K22: 09278398862 | M22: 17 | P22: =CONCATENATE(E22," ",F22," ",G22) -> BAGO REBECCA LLANEZA | Q22: =IFERROR(VLOOKUP(P22,[1]Disposition!$AB$9:$AC$495,2,0),"NO RECORD YET") -> 196 Guyam Malaki, Indang, Cavite
A23: 14 | B23: OCS | C23: Male | D23: PCOL | E23: PATIÑO | F23: RANDI | G23: MANZANO | J23: Mddle Nivel Hills, Brgy Apas, Cebu City | K23: 09057369133 | P23: =CONCATENATE(E23," ",F23," ",G23) -> PATIÑO RANDI MANZANO | Q23: =IFERROR(VLOOKUP(P23,[1]Disposition!$AB$9:$AC$495,2,0),"NO RECORD YET") -> Mddle Nivel Hills, Brgy Apas, Cebu City
A24: 15 | B24: OCS | C24: Male | D24: PCPT | E24: KARIM | F24: BENSAR ALI | G24: ABDULGANI | J24: 21-B Maguindanao St, Culiat, Quezon City | K24: 09267388655 | P24: =CONCATENATE(E24," ",F24," ",G24) -> KARIM BENSAR ALI ABDULGANI | Q24: =IFERROR(VLOOKUP(P24,[1]Disposition!$AB$9:$AC$495,2,0),"NO RECORD YET") -> 21-B Maguindanao St, Culiat, Quezon City
A25: 16 | B25: OCS | C25: Male | D25: PCpl | E25: AGGARAO | F25: ALBERTO | G25: CALLANGAN | J25: 215 D Guiho St., Cembo, Makati City | K25: 09434383476 | M25: =SUM(M15:M24) -> 566 | P25: =CONCATENATE(E25," ",F25," ",G25) -> AGGARAO ALBERTO CALLANGAN | Q25: =IFERROR(VLOOKUP(P25,[1]Disposition!$AB$9:$AC$495,2,0),"NO RECORD YET") -> 215 D Guiho St., Cembo, Makati City
A26: 17 | B26: OCS | C26: Female | D26: PCpl | E26: SANG-AN | F26: CATHERINE | G26: VALDESTAMON | J26: Zone 1 Purok Maligaya, Tagburos, Puerto Princesa City, Palawan | K26: 09279979400 | P26: =CONCATENATE(E26," ",F26," ",G26) -> SANG-AN CATHERINE VALDESTAMON | Q26: =IFERROR(VLOOKUP(P26,[1]Disposition!$AB$9:$AC$495,2,0),"NO RECORD YET") -> NO RECORD YET
A27: 18 | B27: OCS | C27: Female | D27: NUP | E27: ESTEVES | F27: MARICEL | G27: FRESNOZA | J27: 3310 Bataan St., Bacood, Sta.Mesa, Manila | K27: 09293473925 | M27: =205-146 -> 59 | P27: =CONCATENATE(E27," ",F27," ",G27) -> ESTEVES MARICEL FRESNOZA | Q27: =IFERROR(VLOOKUP(P27,[1]Disposition!$AB$9:$AC$495,2,0),"NO RECORD YET") -> 3310 Bataan St., Bacood, Sta.Mesa, Manila
A28: 19 | B28: OCS | C28: Male | D28: NUP | E28: NADORA | F28: ADRIAN JOSE | G28: POSADAS | J28: 16 Maligaya St., Rosario 6 Subd, Sta Lucia, Pasig City 1608 | K28: 09179713272 | P28: =CONCATENATE(E28," ",F28," ",G28) -> NADORA ADRIAN JOSE POSADAS | Q28: =IFERROR(VLOOKUP(P28,[1]Disposition!$AB$9:$AC$495,2,0),"NO RECORD YET") -> 16 Maligaya St., Rosario 6 Subd, Sta Lucia, Pasig City 1608
A29: 20 | B29: PIO | C29: Male | D29: Pat | E29: PEÑON | F29: JAYSON | G29: CABRAL | J29: 1901 Interior, Zamora Street, Manila, NCR | K29: 09608411365 | P29: =CONCATENATE(E29," ",F29," ",G29) -> PEÑON JAYSON CABRAL | Q29: =IFERROR(VLOOKUP(P29,[1]Disposition!$AB$9:$AC$495,2,0),"NO RECORD YET") -> NO RECORD YET
A30: 21 | B30: PIO | C30: Female | D30: NUP | E30: ALVAREZ | F30: PAMELA | G30: CEREZO | J30: Pao, Manaoag, Pangasinan | K30: 09615765167 | P30: =CONCATENATE(E30," ",F30," ",G30) -> ALVAREZ PAMELA CEREZO | Q30: =IFERROR(VLOOKUP(P30,[1]Disposition!$AB$9:$AC$495,2,0),"NO RECORD YET") -> Pao, Manaoag, Pangasinan
A31: 22 | B31: PIO | C31: Male | D31: NUP | E31: RUIVIVAR | F31: JOSE SALVADOR | G31: DEL ROSARIO | J31: 13 St. Joseph St., Milton Hills Subd, Diliman, Quezon City | K31: 09770330570 | P31: =CONCATENATE(E31," ",F31," ",G31) -> RUIVIVAR JOSE SALVADOR DEL ROSARIO | Q31: =IFERROR(VLOOKUP(P31,[1]Disposition!$AB$9:$AC$495,2,0),"NO RECORD YET") -> 13 St. Joseph St., Milton Hills Subd, Diliman, Quezon City
A32: 23 | B32: SLO/OCI | C32: Female | D32: PCpl | E32: CUASAY | F32: ZAYRA JANE | G32: CEDENO | J32: 29 P Dizon Circle, Hen. T. De Leon, Valenzuela City | K32: 09953744137 | P32: =CONCATENATE(E32," ",F32," ",G32) -> CUASAY ZAYRA JANE CEDENO | Q32: =IFERROR(VLOOKUP(P32,[1]Disposition!$AB$9:$AC$495,2,0),"NO RECORD YET") -> NO RECORD YET
A33: 24 | B33: SLO/OCI | C33: Female | D33: NUP | E33: COSTALES | F33: MARY GRACE | G33: RODRIGUEZ | J33: 7C 2Nd Ave., Bagong Lipunan Ng Crame, Quezon City | K33: 09275492985 | P33: =CONCATENATE(E33," ",F33," ",G33) -> COSTALES MARY GRACE RODRIGUEZ | Q33: =IFERROR(VLOOKUP(P33,[1]Disposition!$AB$9:$AC$495,2,0),"NO RECORD YET") -> NO RECORD YET
A34: 25 | B34: SLO/OCI | C34: Female | D34: NUP | E34: VER | F34: MARIE LOUISE ROVIAN | G34: RAMOS | J34: Blk 43 Lot 16, Phase 7, Eastwood Residences, Brgy San Isidro, Montalban, Rizal | K34: 09158167417 | M34: =177-226 -> -49 | P34: =CONCATENATE(E34," ",F34," ",G34) -> VER MARIE LOUISE ROVIAN RAMOS | Q34: =IFERROR(VLOOKUP(P34,[1]Disposition!$AB$9:$AC$495,2,0),"NO RECORD YET") -> Blk 43 Lot 16, Phase 7, Eastwood Residences, Brgy San Isidro, Montalban, Rizal
A35: 26 | B35: ITPMD | C35: Male | D35: PCOL | E35: BORRES | F35: RUBEN | G35: BROSAS | J35: 163-W 20Th Avenue, Rembo, Makati City | K35: 09367450777 | P35: =CONCATENATE(E35," ",F35," ",G35) -> BORRES RUBEN BROSAS | Q35: =IFERROR(VLOOKUP(P35,[1]Disposition!$AB$9:$AC$495,2,0),"NO RECORD YET") -> NO RECORD YET
A36: 27 | B36: ITPMD | C36: Female | D36: PLTCOL | E36: FABRO | F36: JHOANA GRACIA | G36: MANLAPAZ
A37: 28 | B37: ITPMD | C37: Female | D37: NUP | E37: GONZALES | F37: NECILDA | G37: JAVINIAR | J37: 641 Blk 22 Kabisig Floodway, San Andres, Cainta, Rizal | K37: 09187708759 | P37: =CONCATENATE(E200," ",F200," ",G200) -> BATICADOS IVY ELEGARLE | Q37: =IFERROR(VLOOKUP(P37,[1]Disposition!$AB$9:$AC$495,2,0),"NO RECORD YET") -> EL Dorado Dulo, Brgy. Don Bosco, Better Living Subd., Parañaque City
A38: 29 | B38: ITPMIS, ITPMD | C38: Female | D38: PCPT | E38: QUINTOS | F38: ANGELICA | G38: AGOR | J38: B1 L128 Phase 1F, Sub Urban Village, San Jose, Montalban, Rizal | K38: 09458154169 | P38: =CONCATENATE(E38," ",F38," ",G38) -> QUINTOS ANGELICA AGOR | Q38: =IFERROR(VLOOKUP(P38,[1]Disposition!$AB$9:$AC$495,2,0),"NO RECORD YET") -> B1 L128 Phase 1F, Sub Urban Village, San Jose, Montalban, Rizal
A39: 30 | B39: ITPMIS, ITPMD | C39: Female | D39: Pat | E39: CELARIO | F39: RUBY ROSE | G39: BUEZA | J39: 37 Tagumpay St. Marawi, Camiling, Tarlac | K39: 09514992446 | N39: =566-554 -> 12 | P39: =CONCATENATE(E39," ",F39," ",G39) -> CELARIO RUBY ROSE BUEZA | Q39: =IFERROR(VLOOKUP(P39,[1]Disposition!$AB$9:$AC$495,2,0),"NO RECORD YET") -> NO RECORD YET
A40: 31 | B40: ITPMIS, ITPMD | C40: Male | D40: Pat | E40: MANAOG | F40: RODNIE | G40: CASTILLO | J40: Sitio Pongol., Brgy. Burabod, San Antonio, Northern Samar | K40: 09452066435 | N40: 3 | P40: =CONCATENATE(E40," ",F40," ",G40) -> MANAOG RODNIE CASTILLO | Q40: =IFERROR(VLOOKUP(P40,[1]Disposition!$AB$9:$AC$495,2,0),"NO RECORD YET") -> NO RECORD YET
A41: 32 | B41: ITPMIS, ITPMD | C41: Male | D41: NUP | E41: DAGTA | F41: MARY ANN | G41: YAP | J41: Blk 3, Lot 20, Amber St., Summit Viwe Subd., Brgy. San Rafael, Rodriguez, Rizal | K41: 09568629227 | P41: =CONCATENATE(E41," ",F41," ",G41) -> DAGTA MARY ANN YAP | Q41: =IFERROR(VLOOKUP(P41,[1]Disposition!$AB$9:$AC$495,2,0),"NO RECORD YET") -> Blk 3, Lot 20, Amber St., Summit Viwe Subd., Brgy. San Rafael, Rodriguez, Rizal
A42: 33 | B42: EMS, ITPMD | C42: Male | D42: PMSg | E42: PEÑAVERDE | F42: PHILIP JAMES | G42: RODRIGUEZ | J42: Blk 1 Lot 128 P1-F Sub-Urban Village, Saan Jose, Rodriguez, Rizal | K42: 09266167584 | P42: =CONCATENATE(E42," ",F42," ",G42) -> PEÑAVERDE PHILIP JAMES RODRIGUEZ | Q42: =IFERROR(VLOOKUP(P42,[1]Disposition!$AB$9:$AC$495,2,0),"NO RECORD YET") -> Blk 1 Lot 128 P1-F Sub-Urban Village, Saan Jose, Rodriguez, Rizal
A43: 34 | B43: EMS, ITPMD | C43: Male | D43: Pat | E43: MORTEL | F43: ALWYN | G43: ALBUFERA | J43: 330 Ilaya, Butong, Taal, Batangas | K43: 09652107608 | N43: 4 | P43: =CONCATENATE(E43," ",F43," ",G43) -> MORTEL ALWYN ALBUFERA | Q43: =IFERROR(VLOOKUP(P43,[1]Disposition!$AB$9:$AC$495,2,0),"NO RECORD YET") -> NO RECORD YET
A44: 35 | B44: EMS, ITPMD | C44: Female | D44: NUP | E44: BERENGUEL | F44: LUCHIE | G44: RELOYA | J44: #2 Alley 15, P. Rosales St., Sta. Ana Kaliwa, Pateros | K44: 09662553586 | P44: =CONCATENATE(E414," ",F414," ",G414) -> RAMOS WENCESLAO AGUILAR | Q44: =IFERROR(VLOOKUP(P44,[1]Disposition!$AB$9:$AC$495,2,0),"NO RECORD YET") -> 5-A St.Paul St., Remerville Subd. Baesa, Quezon City
A45: 36 | B45: ITPMD (OCPNP) | C45: Male | D45: PCPT | E45: SOSA | F45: GIBSON JOHN | G45: ARAOS | J45: #10 Singapore, Bastulde, Fil-Inves, Cainta, Rizal | K45: 09176229285 | P45: =CONCATENATE(E45," ",F45," ",G45) -> SOSA GIBSON JOHN ARAOS | Q45: =IFERROR(VLOOKUP(P45,[1]Disposition!$AB$9:$AC$495,2,0),"NO RECORD YET") -> #10 Singapore, Bastulde, Fil-Inves, Cainta, Rizal
A46: 37 | B46: ITPMD (OCPNP) | C46: Male | D46: PCPT | E46: TAN | F46: ACHILES | G46: YABUT | J46: Blk 1 Lot 33, Maunlad Homes Subd., Caingin, Malolos, Bulacan | K46: 09985974254 | P46: =CONCATENATE(E46," ",F46," ",G46) -> TAN ACHILES YABUT | Q46: =IFERROR(VLOOKUP(P46,[1]Disposition!$AB$9:$AC$495,2,0),"NO RECORD YET") -> Blk 1 Lot 33, Maunlad Homes Subd., Caingin, Malolos, Bulacan
A47: 38 | B47: ITPMD (OCPNP) | C47: Female | D47: PCpl | E47: CLAOR | F47: MICHELLE | G47: DUGAM | J47: Toon, La Paz, Abra | K47: 09556384560 | P47: =CONCATENATE(E47," ",F47," ",G47) -> CLAOR MICHELLE DUGAM | Q47: =IFERROR(VLOOKUP(P47,[1]Disposition!$AB$9:$AC$495,2,0),"NO RECORD YET") -> Toon, La Paz, Abra
A48: 39 | B48: ITPMD (PIO) | C48: Male | D48: PCPT | E48: ALIMAMBO | F48: JICK | G48: BONUAN | J48: 72 Pucay Village, Purok I, Bakakeng Norte, Baguio City | K48: 09774274007 | P48: =CONCATENATE(E48," ",F48," ",G48) -> ALIMAMBO JICK BONUAN | Q48: =IFERROR(VLOOKUP(P48,[1]Disposition!$AB$9:$AC$495,2,0),"NO RECORD YET") -> 72 Pucay Village, Purok I, Bakakeng Norte, Baguio City
A49: 40 | B49: ITPMD (CPSM) | C49: Male | D49: Pat | E49: TUBELLEZA | F49: JOHN CARLO | G49: VILLARINO | J49: 33 Family Ville Subdivision, Bucal, Tanza, Cavite | K49: 09957230126 | P49: =CONCATENATE(E49," ",F49," ",G49) -> TUBELLEZA JOHN CARLO VILLARINO | Q49: =IFERROR(VLOOKUP(P49,[1]Disposition!$AB$9:$AC$495,2,0),"NO RECORD YET") -> NO RECORD YET
A50: 41 | B50: ITPMD (CPSM/IAS) | C50: Male | D50: PCpl | E50: LUALHATI | F50: PAULO ANDREW | G50: PUNZALAN | J50: 33 Jw Diokno St., Poblacion 13, Taal, Batangas | K50: 09568569677 | P50: =CONCATENATE(E50," ",F50," ",G50) -> LUALHATI PAULO ANDREW PUNZALAN | Q50: =IFERROR(VLOOKUP(P50,[1]Disposition!$AB$9:$AC$495,2,0),"NO RECORD YET") -> 33 JW Diokno St., Poblacion 13, Taal, Batangas
A51: 42 | B51: ITPMD (HRAO) | C51: Female | D51: PCPT | E51: SALAS | F51: EUNILAINE | G51: SALVADOR | J51: 131 Wwest Drive St., Narikina Heights, Marikina City | K51: 09175518988 | P51: =CONCATENATE(E51," ",F51," ",G51) -> SALAS EUNILAINE SALVADOR | Q51: =IFERROR(VLOOKUP(P51,[1]Disposition!$AB$9:$AC$495,2,0),"NO RECORD YET") -> 131 Wwest Drive St., Narikina Heights, Marikina City
A52: 43 | B52: ITPMD (IAS) | C52: Male | D52: PLT | E52: ECHANO | F52: KERWIN | G52: RUFON | J52: Lot 37-38 Blk.5 Catanauan St., Vanessa Homes, Bucal, Calamba, Laguna | K52: 09760708892 | P52: =CONCATENATE(E52," ",F52," ",G52) -> ECHANO KERWIN RUFON | Q52: =IFERROR(VLOOKUP(P52,[1]Disposition!$AB$9:$AC$495,2,0),"NO RECORD YET") -> Lot 37-38 BLK.5 Catanauan ST., Vanessa Homes, Bucal, Calamba, Laguna
A53: 44 | B53: ITPMD (EOD/K9) | C53: Male | D53: PMAJ | E53: LAXAMANA | F53: JOSE | G53: DELA CRUZ | H53: II | J53: 191 Gen. Mascardo St., Bagong Barrio, Caloocan City | K53: 09983998333 | P53: =CONCATENATE(E53," ",F53," ",G53) -> LAXAMANA JOSE DELA CRUZ | Q53: =IFERROR(VLOOKUP(P53,[1]Disposition!$AB$9:$AC$495,2,0),"NO RECORD YET") -> 191 Gen. Mascardo St., Bagong Barrio, Caloocan City
A54: 45 | B54: ITPMD (EOD/K9) | C54: Male | D54: Pat | E54: AGUILANDO | F54: ADAMSON | G54: BANDONG | J54: 189, Sitio Palsic, Naguilayan, San Carlos City, Pangasinan | K54: 09275465069 | P54: =CONCATENATE(E54," ",F54," ",G54) -> AGUILANDO ADAMSON BANDONG | Q54: =IFERROR(VLOOKUP(P54,[1]Disposition!$AB$9:$AC$495,2,0),"NO RECORD YET") -> NO RECORD YET
A55: 46 | B55: ITPMD (OTDCA) | C55: Male | D55: Pat | E55: BACATAN | F55: FERDINAND | G55: JALOVA | H55: JR | J55: Blk 55b Lot 1 Sitio Panghulo, Floodway, San Juan, Taytay, Rizal | K55: 09465348401 | P55: =CONCATENATE(E55," ",F55," ",G55) -> BACATAN FERDINAND JALOVA | Q55: =IFERROR(VLOOKUP(P55,[1]Disposition!$AB$9:$AC$495,2,0),"NO RECORD YET") -> NO RECORD YET
A56: 47 | B56: ITPMD (OTDCO) | C56: Male | D56: PCPT | E56: MUÑOZ | F56: RANZ NIKKO | G56: BIEN | J56: Blk. 15 Lot 22, Viola St., Camella Sorrento, P.F. Espiritu Iv, Bacoor, Cavite | K56: 09959045925 | P56: =CONCATENATE(E56," ",F56," ",G56) -> MUÑOZ RANZ NIKKO BIEN | Q56: =IFERROR(VLOOKUP(P56,[1]Disposition!$AB$9:$AC$495,2,0),"NO RECORD YET") -> Blk. 15 Lot 22, Viola St., Camella Sorrento, P.F. Espiritu IV, Bacoor, Cavite
A57: 48 | B57: ITPMD (OTDCO) | C57: Male | D57: PCMS | E57: MARAÑON | F57: CHRIS JOHN | G57: CATALOGO | J57: B18 L1 P-J Francisco Homes, Sjdm, Bulacan | K57: 09217221646 | P57: =CONCATENATE(E57," ",F57," ",G57) -> MARAÑON CHRIS JOHN CATALOGO | Q57: =IFERROR(VLOOKUP(P57,[1]Disposition!$AB$9:$AC$495,2,0),"NO RECORD YET") -> B18 L1 P-J Francisco Homes, SJDM, Bulacan
A58: 49 | B58: ITPMD (OTCDS) | C58: Male | D58: PMAJ | E58: AMIT | F58: ARIEL | G58: DE GUZMAN | J58: Manila, Metro Manila | K58: 09205682939 | P58: =CONCATENATE(E58," ",F58," ",G58) -> AMIT ARIEL DE GUZMAN | Q58: =IFERROR(VLOOKUP(P58,[1]Disposition!$AB$9:$AC$495,2,0),"NO RECORD YET") -> Manila, Metro Manila
A59: 50 | B59: ITPMD (OTCDS) | C59: Male | D59: PLT | E59: ILACAD | F59: DIONELL | G59: TUGADE | P59: =CONCATENATE(E59," ",F59," ",G59) -> ILACAD DIONELL TUGADE
A60: 51 | B60: ITPMD (OTCDS) | C60: Male | D60: PMSg | E60: DULIN | F60: JOEY | G60: BINARAO | J60: 155 19Th Avenue, East Pembo, Makati City | K60: 09175073304 | P60: =CONCATENATE(E60," ",F60," ",G60) -> DULIN JOEY BINARAO | Q60: =IFERROR(VLOOKUP(P60,[1]Disposition!$AB$9:$AC$495,2,0),"NO RECORD YET") -> 155 19th Avenue, East Pembo, Makati City
A61: 52 | B61: ITPMD (OTCDS) | C61: Male | D61: PCpl | E61: DOCTOLERO | F61: JOHN NICK | G61: DE GUZMAN | J61: B25 L5 Ph. J, Brgy. Guijo, Francisco Homes, Sjdm, Bulacan | K61: 09063610614 | P61: =CONCATENATE(E61," ",F61," ",G61) -> DOCTOLERO JOHN NICK DE GUZMAN | Q61: =IFERROR(VLOOKUP(P61,[1]Disposition!$AB$9:$AC$495,2,0),"NO RECORD YET") -> B25 L5 PH. J, Brgy. Guijo, Francisco Homes, SJDM, Bulacan
A62: 53 | B62: ITPMD (DPRM) | C62: Male | D62: PMAJ | E62: DELA CRUZ | F62: ALVIN | G62: ORUA | J62: #6087 Sto. Rosario St., Mapulang Lupa, Valenzuela City | K62: 09178710735 | P62: =CONCATENATE(E62," ",F62," ",G62) -> DELA CRUZ ALVIN ORUA | Q62: =IFERROR(VLOOKUP(P62,[1]Disposition!$AB$9:$AC$495,2,0),"NO RECORD YET") -> #6087 Sto. Rosario St., Mapulang Lupa, Valenzuela City
A63: 54 | B63: ITPMD (DPRM) | C63: Male | D63: PMAJ | E63: DESEO | F63: REYNANTE | G63: NUYDA | J63: Blk 4 L17 Arty In Subdivision, Karuhatan, Valenzueal City | K63: 09974766710 | P63: =CONCATENATE(E63," ",F63," ",G63) -> DESEO REYNANTE NUYDA | Q63: =IFERROR(VLOOKUP(P63,[1]Disposition!$AB$9:$AC$495,2,0),"NO RECORD YET") -> Blk 4 L17 Arty in Subdivision, Karuhatan, Valenzueal City
A64: 55 | B64: ITPMD (DPRM) | C64: Female | D64: PCpl | E64: CASTRO | F64: MARYJANE | G64: DIZON | J64: Phase 1, Purok 5, Taugtog, Botolan, Zambales | K64: 09501115804 | P64: =CONCATENATE(E64," ",F64," ",G64) -> CASTRO MARYJANE DIZON | Q64: =IFERROR(VLOOKUP(P64,[1]Disposition!$AB$9:$AC$495,2,0),"NO RECORD YET") -> Phase 1, Purok 5, Taugtog, Botolan, Zambales
A65: 56 | B65: ITPMD (DPRM) | C65: Male | D65: Pat | E65: CORTEZ | F65: JERWIN | G65: AQUINO | J65: Purok Happy Valley 2, San Vicente, Santa Ignacia, Tarlac | K65: 09101247667 | P65: =CONCATENATE(E65," ",F65," ",G65) -> CORTEZ JERWIN AQUINO | Q65: =IFERROR(VLOOKUP(P65,[1]Disposition!$AB$9:$AC$495,2,0),"NO RECORD YET") -> NO RECORD YET
A66: 57 | B66: ITPMD (DPRM) | C66: Male | D66: Pat | E66: MANIQUIZ | F66: JEREMY | G66: BINUYA | J66: Quezon, Entablado, Cabiao, Nueva Ecija | K66: 09096575574 | P66: =CONCATENATE(E66," ",F66," ",G66) -> MANIQUIZ JEREMY BINUYA | Q66: =IFERROR(VLOOKUP(P66,[1]Disposition!$AB$9:$AC$495,2,0),"NO RECORD YET") -> NO RECORD YET
A67: 58 | B67: ITPMD (DPRM) | C67: Female | D67: NUP | E67: LUMABI | F67: GINA | G67: TINGALA | J67: Mb 15 Rm 109, Diego Silang Village, Brgy Ususan, Taguig City | K67: 09471754148 | P67: =CONCATENATE(E67," ",F67," ",G67) -> LUMABI GINA TINGALA | Q67: =IFERROR(VLOOKUP(P67,[1]Disposition!$AB$9:$AC$495,2,0),"NO RECORD YET") -> MB 15 RM 109, Diego Silang Village, Brgy Ususan, Taguig City
A68: 59 | B68: ITPMD (DPRM) | C68: Female | D68: NUP | E68: UBANDO | F68: MARY ANN | G68: OBENA | J68: Blk 13 Lot 14 Phase M, Francisco Homes, Brgy. Guijo, Sjdm, Bulacan | K68: 09197265632 | P68: =CONCATENATE(E68," ",F68," ",G68) -> UBANDO MARY ANN OBENA | Q68: =IFERROR(VLOOKUP(P68,[1]Disposition!$AB$9:$AC$495,2,0),"NO RECORD YET") -> Blk 13 Lot 14 Phase M, Francisco Homes, Brgy. Guijo, SJDM, Bulacan
A69: 60 | B69: ITPMD (DPRM-DLOD) | C69: Male | D69: Pat | E69: CAGUITE | F69: JOHN REX | G69: ALIDO | J69: Diversion Road, Sitio Guinting, Lalig, Tiaong, Quezon | K69: 09773618665 | P69: =CONCATENATE(E69," ",F69," ",G69) -> CAGUITE JOHN REX ALIDO | Q69: =IFERROR(VLOOKUP(P69,[1]Disposition!$AB$9:$AC$495,2,0),"NO RECORD YET") -> NO RECORD YET
A70: 61 | B70: ITPMD (DPRM-DLOD) | C70: Male | D70: Pat | E70: TAGPAO | F70: RAFAEL | G70: ALUNDAY | J70: Purok 7, Sitio, Dat-Ayan, Minagbag, Quezon, Isabela | K70: 09263606410 | P70: =CONCATENATE(E70," ",F70," ",G70) -> TAGPAO RAFAEL ALUNDAY | Q70: =IFERROR(VLOOKUP(P70,[1]Disposition!$AB$9:$AC$495,2,0),"NO RECORD YET") -> NO RECORD YET
A71: 62 | B71: ITPMD (DRD) | C71: Male | D71: Pat | E71: VILLEGAS | F71: NAIF | G71: STA ANA | J71: #280 Gomez, Santa Rosa, Nueva Ecija | K71: 09267230880 | P71: =CONCATENATE(E71," ",F71," ",G71) -> VILLEGAS NAIF STA ANA | Q71: =IFERROR(VLOOKUP(P71,[1]Disposition!$AB$9:$AC$495,2,0),"NO RECORD YET") -> NO RECORD YET
... A73: 64 | B73: ITPMD (DIDM) | C73: Male | D73: PLT | E73: ABO | F73: MARK JESSIE | G73: MELITANTE | J73: Unit 909, Amaia Skies Cuibao, P. Tuazon Ave., Socorro, Quezon City | K73: 09566570420 | P73: =CONCATENATE(E73," ",F73," ",G73) -> ABO MARK JESSIE MELITANTE | Q73: =IFERROR(VLOOKUP(P73,[1]Disposition!$AB$9:$AC$495,2,0),"NO RECORD YET") -> Unit 909, Amaia Skies Cuibao, P. Tuazon Ave., Socorro, Quezon City
A74: 65 | B74: ITPMD (DIDM) | C74: Male | D74: PLT | E74: GALAMGAM | F74: RAMON | G74: DIAZ | H74: JR | P74: =CONCATENATE(E74," ",F74," ",G74) -> GALAMGAM RAMON DIAZ
A75: 66 | B75: ITPMD (DIDM) | C75: Male | D75: PSMS | E75: TACTAY | F75: HENRY | G75: GOLINO | J75: 41 Quimmarayan, Sto. Domingo, Ilocos Sur | K75: 09950271798 | P75: =CONCATENATE(E75," ",F75," ",G75) -> TACTAY HENRY GOLINO | Q75: =IFERROR(VLOOKUP(P75,[1]Disposition!$AB$9:$AC$495,2,0),"NO RECORD YET") -> 41 Quimmarayan, Sto. Domingo, Ilocos Sur
A76: 67 | B76: ITPMD (DIDM) | C76: Female | D76: Pat | E76: ABRIAM | F76: ANNETH VALERIE | G76: MALNAT | J76: 13 P1 Villa Jose Ylanan, Maddela, Quirino | K76: 09686456470 | P76: =CONCATENATE(E76," ",F76," ",G76) -> ABRIAM ANNETH VALERIE MALNAT | Q76: =IFERROR(VLOOKUP(P76,[1]Disposition!$AB$9:$AC$495,2,0),"NO RECORD YET") -> NO RECORD YET
A77: 68 | B77: ITPMD (DIDM) | C77: Female | D77: Pat | E77: SAET | F77: MITZI ANNE | G77: BESA | J77: Lambingan, Sunrise Viu Village, San Guillermo, Morong, Rizal | K77: 09311126415 | P77: =CONCATENATE(E77," ",F77," ",G77) -> SAET MITZI ANNE BESA | Q77: =IFERROR(VLOOKUP(P77,[1]Disposition!$AB$9:$AC$495,2,0),"NO RECORD YET") -> NO RECORD YET
A78: 69 | B78: ITPMD (DIDM) | C78: Male | D78: Pat | E78: SALES | F78: JAFET | G78: ANINAO | J78: 164 J.P Rizal St., J.Rizal, Santa Maria, Laguna | K78: 09167919991 | P78: =CONCATENATE(E78," ",F78," ",G78) -> SALES JAFET ANINAO | Q78: =IFERROR(VLOOKUP(P78,[1]Disposition!$AB$9:$AC$495,2,0),"NO RECORD YET") -> NO RECORD YET
A79: 70 | B79: ITPMD (DIDM) | C79: Male | D79: NUP | E79: TACORDA | F79: JASON ABRAHAM | G79: ABION | J79: 2315 T2 Amaia Skies, Cubao, 5The Ave. Cor P Tuazon Ave., Brgy. Socorro, Quezon City | K79: 09150334133 | P79: =CONCATENATE(E79," ",F79," ",G79) -> TACORDA JASON ABRAHAM ABION | Q79: =IFERROR(VLOOKUP(P79,[1]Disposition!$AB$9:$AC$495,2,0),"NO RECORD YET") -> 2315 T2 Amaia Skies, Cubao, 5the Ave. cor P Tuazon Ave., Brgy. Socorro, Quezon City
A80: 71 | B80: ITPMD (DIDM-WCPC) | C80: Male | D80: PMAJ | E80: NICOLAS | F80: JAY-R | G80: TADEO | J80: #143 Asin West., Malasigue, Pangasinan | K80: 09770935729 | P80: =CONCATENATE(E80," ",F80," ",G80) -> NICOLAS JAY-R TADEO | Q80: =IFERROR(VLOOKUP(P80,[1]Disposition!$AB$9:$AC$495,2,0),"NO RECORD YET") -> #143 Asin West., Malasigue, Pangasinan
A81: 72 | B81: ITPMD (DPL) | C81: Male | D81: PMAJ | E81: SY | F81: CHRISTIAN | G81: ONG | J81: 4 | K81: 09176548452 | P81: =CONCATENATE(E81," ",F81," ",G81) -> SY CHRISTIAN ONG | Q81: =IFERROR(VLOOKUP(P81,[1]Disposition!$AB$9:$AC$495,2,0),"NO RECORD YET") -> B3 L4 Ephesians St., Sta. Monica Heights, Suqui, Calapan City, Oriental Mindoro
A82: 73 | B82: ITPMD (DPL) | C82: Male | D82: Pat | E82: OBOG | F82: JOHN MARLO | G82: MAGRAMO | J82: 0550 Sanggumay, Looc, Calamba, Laguna | K82: 09161978384 | P82: =CONCATENATE(E82," ",F82," ",G82) -> OBOG JOHN MARLO MAGRAMO | Q82: =IFERROR(VLOOKUP(P82,[1]Disposition!$AB$9:$AC$495,2,0),"NO RECORD YET") -> NO RECORD YET
A83: 74 | B83: ITPMD (DPL) | C83: Male | D83: NUP | E83: BUENSUCESO | F83: NEIL PAUL | G83: BAUTISTA | P83: =CONCATENATE(E83," ",F83," ",G83) -> BUENSUCESO NEIL PAUL BAUTISTA
A84: 75 | B84: ITPMD (DL) | C84: Male | D84: PMAJ | E84: DULA | F84: JOEL | G84: MANALANSAN | J84: 407 Purok 7, New San Juan, Dinalupihan, Bataan | K84: 09667058328 | P84: =CONCATENATE(E84," ",F84," ",G84) -> DULA JOEL MANALANSAN | Q84: =IFERROR(VLOOKUP(P84,[1]Disposition!$AB$9:$AC$495,2,0),"NO RECORD YET") -> 407 Purok 7, New San Juan, Dinalupihan, Bataan
A85: 76 | B85: ITPMD (DL) | C85: Female | D85: PCPT | E85: DIMASANGKAY | F85: SORAIYA | G85: MUSAID | J85: Silver Homes Subdivision, Sadaan, Midsayap, Cotabato | P85: =CONCATENATE(E85," ",F85," ",G85) -> DIMASANGKAY SORAIYA MUSAID | Q85: =IFERROR(VLOOKUP(P85,[1]Disposition!$AB$9:$AC$495,2,0),"NO RECORD YET") -> NO RECORD YET
A86: 77 | B86: ITPMD (DL) | C86: Female | D86: NUP | E86: JEPOLLO | F86: JOCELYN | G86: TAMONDONG | J86: #7 4Th Avenue, Bagong Lipunan, Crame, Quezon City | K86: 09977830520 | P86: =CONCATENATE(E86," ",F86," ",G86) -> JEPOLLO JOCELYN TAMONDONG | Q86: =IFERROR(VLOOKUP(P86,[1]Disposition!$AB$9:$AC$495,2,0),"NO RECORD YET") -> #7 4TH Avenue, Bagong Lipunan, Crame, Quezon City
A87: 78 | B87: ITPMD (DL) | C87: Female | D87: NUP | E87: TODA | F87: MA CRISTINA | G87: TAMONDONG | J87: 19 A J Ocampo St., Project 4, Quezon City | K87: 09175065455 | P87: =CONCATENATE(E87," ",F87," ",G87) -> TODA MA CRISTINA TAMONDONG | Q87: =IFERROR(VLOOKUP(P87,[1]Disposition!$AB$9:$AC$495,2,0),"NO RECORD YET") -> 19 A J Ocampo St., Project 4, Quezon City
A88: 79 | B88: ITPMD (DC) | C88: Male | D88: PCPT | E88: BALLENAS | F88: ROBERTO | G88: ALPAS | H88: JR | J88: Purok Masipag, Buayan, M'Lang, Cotabato, North Cotabato | K88: 09664625855 | P88: =CONCATENATE(E88," ",F88," ",G88) -> BALLENAS ROBERTO ALPAS | Q88: =IFERROR(VLOOKUP(P88,[1]Disposition!$AB$9:$AC$495,2,0),"NO RECORD YET") -> Purok Masipag, Buayan, M'lang, Cotabato, North Cotabato
A89: 80 | B89: ITPMD (DC) | C89: Female | D89: Pat | E89: GUAVINO | F89: CHE-YENNE | G89: LAZARITO | J89: Apartment 23, Emq Camp Crame, Bagong Lipunan Ng Crame, Qauezon City | K89: 09179975888 | P89: =CONCATENATE(E89," ",F89," ",G89) -> GUAVINO CHE-YENNE LAZARITO | Q89: =IFERROR(VLOOKUP(P89,[1]Disposition!$AB$9:$AC$495,2,0),"NO RECORD YET") -> Apartment 23, EMQ Camp Crame, Bagong Lipunan ng Crame, Qauezon City
A90: 81 | B90: ITPMD (DC) | C90: Male | D90: Pat | E90: INALVEZ | F90: NEIL ADRIAN | G90: NUCOM | J90: 676 Purok Kb3, Maugat, San Antonio, Nueva Ecija, | K90: 09531143703 | P90: =CONCATENATE(E90," ",F90," ",G90) -> INALVEZ NEIL ADRIAN NUCOM | Q90: =IFERROR(VLOOKUP(P90,[1]Disposition!$AB$9:$AC$495,2,0),"NO RECORD YET") -> 676 Purok KB3, Maugat, San Antonio, Nueva Ecija,
A91: 82 | B91: ITPMD (DPCR) | C91: Female | D91: PCPT | E91: BUHAIN | F91: DOROTHY | G91: VILLALOBOS | J91: 301 Masagana Subd., Gumamela St., San Francisco, Bulacan | K91: 09567595065 | P91: =CONCATENATE(E91," ",F91," ",G91) -> BUHAIN DOROTHY VILLALOBOS | Q91: =IFERROR(VLOOKUP(P91,[1]Disposition!$AB$9:$AC$495,2,0),"NO RECORD YET") -> 301 Masagana Subd., Gumamela St., San Francisco, Bulacan
A92: 83 | B92: ITPMD (DPCR) | C92: Male | D92: PSMS | E92: SIBAYAN | F92: REYGIE | G92: PIAGAN | J92: Giron St., Brgy No. 2, Santa Joaquina, Laoag City, Ilocos Norte | K92: 09082302544 | P92: =CONCATENATE(E92," ",F92," ",G92) -> SIBAYAN REYGIE PIAGAN | Q92: =IFERROR(VLOOKUP(P92,[1]Disposition!$AB$9:$AC$495,2,0),"NO RECORD YET") -> Giron St., BRGY NO. 2, Santa Joaquina, Laoag City, Ilocos Norte
A93: 84 | B93: ITPMD (DPCR) | C93: Male | D93: Pat | E93: CORDERO | F93: EARLBON | G93: JIMENEZ | J93: 1362 R.A Reyes Street, Tondo, Manila | K93: 09066901087 | P93: =CONCATENATE(E93," ",F93," ",G93) -> CORDERO EARLBON JIMENEZ | Q93: =IFERROR(VLOOKUP(P93,[1]Disposition!$AB$9:$AC$495,2,0),"NO RECORD YET") -> NO RECORD YET
A94: 85 | B94: ITPMD (DPCR) | C94: Male | D94: Pat | E94: ORLANDA | F94: BERNABE | G94: MACADANGDANG | H94: JR | J94: Sitio Malubec Curva, Pamplona, Cagayan | K94: 09975442501 | P94: =CONCATENATE(E94," ",F94," ",G94) -> ORLANDA BERNABE MACADANGDANG | Q94: =IFERROR(VLOOKUP(P94,[1]Disposition!$AB$9:$AC$495,2,0),"NO RECORD YET") -> NO RECORD YET
A95: 86 | B95: ITPMD (DHRDD/PRO1) | C95: Male | D95: PLTCOL | E95: SEVILLA | F95: JERALD | G95: MANUZON | J95: B-38 L-20 Violeta St., Pembo, Makati City | K95: 09176055075 | P95: =CONCATENATE(E95," ",F95," ",G95) -> SEVILLA JERALD MANUZON | Q95: =IFERROR(VLOOKUP(P95,[1]Disposition!$AB$9:$AC$495,2,0),"NO RECORD YET") -> B-38 L-20 Violeta St., Pembo, Makati City
A96: 87 | B96: ITPMD (DHRDD) | C96: Female | D96: PCPT | E96: SUAYA | F96: RAFFY JANE | G96: ALIDAO | J96: #25 C Purok 1, Lower Liwanag, Liwanag-Loakan, Baguio City, Benguet | K96: 09126980797 | P96: =CONCATENATE(E96," ",F96," ",G96) -> SUAYA RAFFY JANE ALIDAO | Q96: =IFERROR(VLOOKUP(P96,[1]Disposition!$AB$9:$AC$495,2,0),"NO RECORD YET") -> #25 C Purok 1, Lower Liwanag, Liwanag-Loakan, Baguio City, Benguet
A97: 88 | B97: ITPMD (DI) | C97: Female | D97: PCPT | E97: REVALE | F97: EDELLENE | G97: BABAGAY | J97: P3 Brgy. Ems Barrio, Legaspi City, Albay | K97: 09994275134 | P97: =CONCATENATE(E97," ",F97," ",G97) -> REVALE EDELLENE BABAGAY | Q97: =IFERROR(VLOOKUP(P97,[1]Disposition!$AB$9:$AC$495,2,0),"NO RECORD YET") -> P3 Brgy. Ems Barrio, Legaspi City, Albay
A98: 89 | B98: ITPMD (DI) | C98: Male | D98: PCPT | E98: SOBREVILLA | F98: RAYMUND CHRISTOPHER | G98: DECIPULO | J98: 15 F Int. Del Pilar St., Purok Bougambilla, Brgy. Bagja Mother, Cotabato City | K98: 09262417598 | P98: =CONCATENATE(E98," ",F98," ",G98) -> SOBREVILLA RAYMUND CHRISTOPHER DECIPULO | Q98: =IFERROR(VLOOKUP(P98,[1]Disposition!$AB$9:$AC$495,2,0),"NO RECORD YET") -> 15 F Int. Del Pilar ST., Purok Bougambilla, Brgy. Bagja Mother, Cotabato City
A99: 90 | B99: ITPMD (DI) | C99: Female | D99: PCPT | E99: ESTRADA | F99: MICAELLA ALLYSSA | G99: MONTES | J99: 15 Jonathan St., Brgy. 55, Tondo, Manila | K99: 09156803437 | P99: =CONCATENATE(E99," ",F99," ",G99) -> ESTRADA MICAELLA ALLYSSA MONTES | Q99: =IFERROR(VLOOKUP(P99,[1]Disposition!$AB$9:$AC$495,2,0),"NO RECORD YET") -> 15 Jonathan St., Brgy. 55, Tondo, Manila
A100: 91 | B100: ITPMD (DI) | C100: Male | D100: Pat | E100: CODIMO | F100: SOLOMON | G100: MADLAENG | J100: Old Poblacion, Burgos, La Union | K100: 09052120646 | P100: =CONCATENATE(E100," ",F100," ",G100) -> CODIMO SOLOMON MADLAENG | Q100: =IFERROR(VLOOKUP(P100,[1]Disposition!$AB$9:$AC$495,2,0),"NO RECORD YET") -> NO RECORD YET
A101: 92 | B101: ITPMD (DI) | C101: Male | D101: Pat | E101: MANGOBA | F101: ROMMEL | G101: JAZMIN | J101: Sitio Mangga, Pogon Lomboy, Mangatarem, Pangasinan | K101: 09208467671 | P101: =CONCATENATE(E101," ",F101," ",G101) -> MANGOBA ROMMEL JAZMIN | Q101: =IFERROR(VLOOKUP(P101,[1]Disposition!$AB$9:$AC$495,2,0),"NO RECORD YET") -> NO RECORD YET
A102: 93 | B102: ITPMD (DI)ODDA | C102: Female | D102: Pat | E102: MARASIGAN | F102: MIA ANGELA | G102: CORNEJO | J102: 121G 14Th Ave., Socorro, Quezon City | K102: 09568570005 | P102: =CONCATENATE(E102," ",F102," ",G102) -> MARASIGAN MIA ANGELA CORNEJO | Q102: =IFERROR(VLOOKUP(P102,[1]Disposition!$AB$9:$AC$495,2,0),"NO RECORD YET") -> 121G 14TH Ave., Socorro, Quezon City
A103: 94 | B103: ITPMD (DI) | C103: Female | D103: Pat | E103: RADA | F103: KRIZTELA FEY | G103: LIM | J103: Pili, San Fernando, Romblon | K103: 09562658528 | P103: =CONCATENATE(E103," ",F103," ",G103) -> RADA KRIZTELA FEY LIM | Q103: =IFERROR(VLOOKUP(P103,[1]Disposition!$AB$9:$AC$495,2,0),"NO RECORD YET") -> Pili, San Fernando, Romblon
...

Sheet DISPO Att
A1: Republic of the Philippines
A2: PHILIPPINE NATIONAL POLICE | J2: =259-240 -> 19
A3: INFORMATION TECHNOLOGY MANAGEMENT SERVICE | J3: =134-63 -> 71
A4: Camp Bgen Rafael T Crame, Quezon City
A6: Disposition of Personnel
A7: (As of January 22, 2026)
A9: NO. | B9: OFFICE/DIVISION | C9: GENDER | D9: RANK | E9: LASTNAME | F9: FIRSTNAME | G9: MIDDLE NAME | H9: QUAL | I9: SIGNATURE | J9: ADDRESS | K9: CONTACT # | P9: NAME | Q9: ADDRESS
A10: 1 | B10: OD | C10: Male | D10: PCOL | E10: PALGUE | F10: ROMY | G10: INWAY
A11: 2 | B11: OD | C11: Male | D11: PCpl | E11: CERIL | F11: PAUL KELVIN | G11: LAROZA
A12: 3 | B12: OD | C12: Male | D12: Pat | E12: BEJARIN | F12: GERALD | G12: DADIRO | J12: Riang, Peñarrubia, Abra | K12: 09368167960 | P12: =CONCATENATE(E12," ",F12," ",G12) -> BEJARIN GERALD DADIRO | Q12: =IFERROR(VLOOKUP(P12,[1]Disposition!$AB$9:$AC$495,2,0),"NO RECORD YET") -> NO RECORD YET
A13: 4 | B13: OD | C13: Male | D13: Pat | E13: MORI | F13: LYNDON | G13: ACOSTA | J13: Caimito, Brgy. Buencag, Gerona, Tarlac | K13: 09091819560 | P13: =CONCATENATE(E13," ",F13," ",G13) -> MORI LYNDON ACOSTA | Q13: =IFERROR(VLOOKUP(P13,[1]Disposition!$AB$9:$AC$495,2,0),"NO RECORD YET") -> NO RECORD YET
A14: 5 | B14: OD | C14: Female | D14: NUP | E14: AVENDAÑO | F14: MA. FRELIE JOY | G14: (no middle name) | J14: #92 F Estrella St., San Juan, Malolos City, Bulacan | K14: 09554289264 | P14: =CONCATENATE(E14," ",F14," ",G14) -> AVENDAÑO MA. FRELIE JOY (no middle name) | Q14: =IFERROR(VLOOKUP(P14,[1]Disposition!$AB$9:$AC$495,2,0),"NO RECORD YET") -> #92 F Estrella St., San Juan, Malolos City, Bulacan
A15: 7 | B15: OD | C15: Female | D15: NUP | E15: LUZARA | F15: JEAN | G15: GRATUITO | J15: Blk 5 Lot 1 Orchid Extension, Capitol Park Homes Ii, Brgy 179 Zone 16, Caloocan City. | K15: 09177037934 | M15: 25 | P15: =CONCATENATE(E15," ",F15," ",G15) -> LUZARA JEAN GRATUITO | Q15: =IFERROR(VLOOKUP(P15,[1]Disposition!$AB$9:$AC$495,2,0),"NO RECORD YET") -> Blk 5 Lot 1 Orchid Extension, Capitol Park Homes II, Brgy 179 Zone 16, Caloocan City.
A16: 8 | B16: ODDA/DI | C16: Male | D16: PCOL | E16: TANGO | F16: FROILAN GENN | G16: GELACIO | H16: II | M16: 259 | P16: =CONCATENATE(E16," ",F16," ",G16) -> TANGO FROILAN GENN GELACIO
A17: 9 | B17: ODDA | C17: Male | D17: PMSg | E17: RESPICIO | F17: VIC BASKAR | G17: MADDARA | J17: Calamagui 2Nd, Isabela | K17: 09268096361 | M17: 134 | P17: =CONCATENATE(E17," ",F17," ",G17) -> RESPICIO VIC BASKAR MADDARA | Q17: =IFERROR(VLOOKUP(P17,[1]Disposition!$AB$9:$AC$495,2,0),"NO RECORD YET") -> Calamagui 2nd, Isabela
A18: 10 | B18: ODDA | C18: Female | D18: NUP | E18: ERIBAL | F18: JOZEL JOY | G18: FALAGNE | J18: 5A Diamond St., Jra Subd., Rosario, Pasug City | K18: 09617215961 | M18: 41 | P18: =CONCATENATE(E18," ",F18," ",G18) -> ERIBAL JOZEL JOY FALAGNE | Q18: =IFERROR(VLOOKUP(P18,[1]Disposition!$AB$9:$AC$495,2,0),"NO RECORD YET") -> 5A Diamond St., JRA Subd., Rosario, Pasug City
A19: 11 | B19: ODDA | C19: Female | D19: NUP | E19: SEMILLA | F19: FLORITES | G19: SARIO | J19: 18 C Dungo St., Brgy, Isabelita, San Juan City | K19: 09274390528 | M19: 40 | P19: =CONCATENATE(E19," ",F19," ",G19) -> SEMILLA FLORITES SARIO
A20: 12 | B20: DD for IT Matters | C20: Female | D20: NUP | E20: MATILLANO | F20: MINA HAYDEE | G20: BECERA | J20: B2 L17 Rose St., Venice Homes Subd., Cainta, Rizal | K20: 09266411836 | M20: 20 | P20: =CONCATENATE(E20," ",F20," ",G20) -> MATILLANO MINA HAYDEE BECERA | Q20: =IFERROR(VLOOKUP(P20,[1]Disposition!$AB$9:$AC$495,2,0),"NO RECORD YET") -> B2 L17 Rose St., Venice Homes Subd., Cainta, Rizal
A21: 13 | B21: ODDIT | C21: Female | D21: Pat | E21: PAPA | F21: MARIZ NICOLE | G21: ENGALAN | J21: 8H Road 6, 1st West Crame, San Juan City | K21: 09563393345 | M21: 30 | P21: =CONCATENATE(E21," ",F21," ",G21) -> PAPA MARIZ NICOLE ENGALAN | Q21: =IFERROR(VLOOKUP(P21,[1]Disposition!$AB$9:$AC$495,2,0),"NO RECORD YET") -> NO RECORD YET
A22: 14 | B22: ODDIT | C22: Female | D22: NUP | E22: BAGO | F22: REBECCA | G22: LLANEZA | J22: 196 Guyam Malaki, Indang, Cavite | K22: 09278398862 | M22: 17 | P22: =CONCATENATE(E22," ",F22," ",G22) -> BAGO REBECCA LLANEZA | Q22: =IFERROR(VLOOKUP(P22,[1]Disposition!$AB$9:$AC$495,2,0),"NO RECORD YET") -> 196 Guyam Malaki, Indang, Cavite
A23: 15 | B23: OCS | C23: Male | D23: PCOL | E23: PATIÑO | F23: RANDI | G23: MANZANO | J23: Mddle Nivel Hills, Brgy Apas, Cebu City | K23: 09057369133 | P23: =CONCATENATE(E23," ",F23," ",G23) -> PATIÑO RANDI MANZANO | Q23: =IFERROR(VLOOKUP(P23,[1]Disposition!$AB$9:$AC$495,2,0),"NO RECORD YET") -> Mddle Nivel Hills, Brgy Apas, Cebu City
A24: 16 | B24: OCS | C24: Male | D24: PCPT | E24: KARIM | F24: BENSAR ALI | G24: ABDULGANI | J24: 21-B Maguindanao St, Culiat, Quezon City | K24: 09267388655 | P24: =CONCATENATE(E24," ",F24," ",G24) -> KARIM BENSAR ALI ABDULGANI | Q24: =IFERROR(VLOOKUP(P24,[1]Disposition!$AB$9:$AC$495,2,0),"NO RECORD YET") -> 21-B Maguindanao St, Culiat, Quezon City
A25: 17 | B25: OCS | C25: Male | D25: PCpl | E25: AGGARAO | F25: ALBERTO | G25: CALLANGAN | J25: 215 D Guiho St., Cembo, Makati City | K25: 09434383476 | M25: =SUM(M15:M24) -> 566 | P25: =CONCATENATE(E25," ",F25," ",G25) -> AGGARAO ALBERTO CALLANGAN | Q25: =IFERROR(VLOOKUP(P25,[1]Disposition!$AB$9:$AC$495,2,0),"NO RECORD YET") -> 215 D Guiho St., Cembo, Makati City
A26: 18 | B26: OCS | C26: Female | D26: PCpl | E26: SANG-AN | F26: CATHERINE | G26: VALDESTAMON | J26: Zone 1 Purok Maligaya, Tagburos, Puerto Princesa City, Palawan | K26: 09279979400 | P26: =CONCATENATE(E26," ",F26," ",G26) -> SANG-AN CATHERINE VALDESTAMON | Q26: =IFERROR(VLOOKUP(P26,[1]Disposition!$AB$9:$AC$495,2,0),"NO RECORD YET") -> NO RECORD YET
A27: 19 | B27: OCS | C27: Female | D27: NUP | E27: ESTEVES | F27: MARICEL | G27: FRESNOZA | J27: 3310 Bataan St., Bacood, Sta.Mesa, Manila | K27: 09293473925 | M27: =205-146 -> 59 | P27: =CONCATENATE(E27," ",F27," ",G27) -> ESTEVES MARICEL FRESNOZA | Q27: =IFERROR(VLOOKUP(P27,[1]Disposition!$AB$9:$AC$495,2,0),"NO RECORD YET") -> 3310 Bataan St., Bacood, Sta.Mesa, Manila
A28: 20 | B28: OCS | C28: Male | D28: NUP | E28: NADORA | F28: ADRIAN JOSE | G28: POSADAS | J28: 16 Maligaya St., Rosario 6 Subd, Sta Lucia, Pasig City 1608 | K28: 09179713272 | P28: =CONCATENATE(E28," ",F28," ",G28) -> NADORA ADRIAN JOSE POSADAS | Q28: =IFERROR(VLOOKUP(P28,[1]Disposition!$AB$9:$AC$495,2,0),"NO RECORD YET") -> 16 Maligaya St., Rosario 6 Subd, Sta Lucia, Pasig City 1608
A29: 21 | B29: PIO | C29: Male | D29: Pat | E29: PEÑON | F29: JAYSON | G29: CABRAL | J29: 1901 Interior, Zamora Street, Manila, NCR | K29: 09608411365 | P29: =CONCATENATE(E29," ",F29," ",G29) -> PEÑON JAYSON CABRAL | Q29: =IFERROR(VLOOKUP(P29,[1]Disposition!$AB$9:$AC$495,2,0),"NO RECORD YET") -> NO RECORD YET
A30: 22 | B30: PIO | C30: Female | D30: NUP | E30: ALVAREZ | F30: PAMELA | G30: CEREZO | J30: Pao, Manaoag, Pangasinan | K30: 09615765167 | P30: =CONCATENATE(E30," ",F30," ",G30) -> ALVAREZ PAMELA CEREZO | Q30: =IFERROR(VLOOKUP(P30,[1]Disposition!$AB$9:$AC$495,2,0),"NO RECORD YET") -> Pao, Manaoag, Pangasinan
A31: 23 | B31: PIO | C31: Male | D31: NUP | E31: RUIVIVAR | F31: JOSE SALVADOR | G31: DEL ROSARIO | J31: 13 St. Joseph St., Milton Hills Subd, Diliman, Quezon City | K31: 09770330570 | P31: =CONCATENATE(E31," ",F31," ",G31) -> RUIVIVAR JOSE SALVADOR DEL ROSARIO | Q31: =IFERROR(VLOOKUP(P31,[1]Disposition!$AB$9:$AC$495,2,0),"NO RECORD YET") -> 13 St. Joseph St., Milton Hills Subd, Diliman, Quezon City
A32: 25 | B32: SLO/OCI | C32: Female | D32: PCpl | E32: CUASAY | F32: ZAYRA JANE | G32: CEDENO | J32: 29 P Dizon Circle, Hen. T. De Leon, Valenzuela City | K32: 09953744137 | P32: =CONCATENATE(E32," ",F32," ",G32) -> CUASAY ZAYRA JANE CEDENO | Q32: =IFERROR(VLOOKUP(P32,[1]Disposition!$AB$9:$AC$495,2,0),"NO RECORD YET") -> NO RECORD YET
A33: 26 | B33: SLO/OCI | C33: Female | D33: NUP | E33: COSTALES | F33: MARY GRACE | G33: RODRIGUEZ | J33: 7C 2Nd Ave., Bagong Lipunan Ng Crame, Quezon City | K33: 09275492985 | P33: =CONCATENATE(E33," ",F33," ",G33) -> COSTALES MARY GRACE RODRIGUEZ | Q33: =IFERROR(VLOOKUP(P33,[1]Disposition!$AB$9:$AC$495,2,0),"NO RECORD YET") -> NO RECORD YET
A34: 27 | B34: SLO/OCI | C34: Female | D34: NUP | E34: VER | F34: MARIE LOUISE ROVIAN | G34: RAMOS | J34: Blk 43 Lot 16, Phase 7, Eastwood Residences, Brgy San Isidro, Montalban, Rizal | K34: 09158167417 | M34: =177-226 -> -49 | P34: =CONCATENATE(E34," ",F34," ",G34) -> VER MARIE LOUISE ROVIAN RAMOS | Q34: =IFERROR(VLOOKUP(P34,[1]Disposition!$AB$9:$AC$495,2,0),"NO RECORD YET") -> Blk 43 Lot 16, Phase 7, Eastwood Residences, Brgy San Isidro, Montalban, Rizal
A35: 28 | B35: ITPMD | C35: Male | D35: PCOL | E35: BORRES | F35: RUBEN | G35: BROSAS | J35: 163-W 20Th Avenue, Rembo, Makati City | K35: 09367450777 | P35: =CONCATENATE(E35," ",F35," ",G35) -> BORRES RUBEN BROSAS | Q35: =IFERROR(VLOOKUP(P35,[1]Disposition!$AB$9:$AC$495,2,0),"NO RECORD YET") -> NO RECORD YET
A36: 29 | B36: ITPMD | C36: Female | D36: PLTCOL | E36: FABRO | F36: JHOANA GRACIA | G36: MANLAPAZ
A37: 30 | B37: ITPMD | C37: Female | D37: NUP | E37: GONZALES | F37: NECILDA | G37: JAVINIAR | J37: 641 Blk 22 Kabisig Floodway, San Andres, Cainta, Rizal | K37: 09187708759 | P37: =CONCATENATE(E354," ",F354," ",G354) -> BATICADOS IVY ELEGARLE | Q37: =IFERROR(VLOOKUP(P37,[1]Disposition!$AB$9:$AC$495,2,0),"NO RECORD YET") -> EL Dorado Dulo, Brgy. Don Bosco, Better Living Subd., Parañaque City
A38: 31 | B38: ITPMIS, ITPMD | C38: Female | D38: PCPT | E38: QUINTOS | F38: ANGELICA | G38: AGOR | J38: B1 L128 Phase 1F, Sub Urban Village, San Jose, Montalban, Rizal | K38: 09458154169 | P38: =CONCATENATE(E38," ",F38," ",G38) -> QUINTOS ANGELICA AGOR | Q38: =IFERROR(VLOOKUP(P38,[1]Disposition!$AB$9:$AC$495,2,0),"NO RECORD YET") -> B1 L128 Phase 1F, Sub Urban Village, San Jose, Montalban, Rizal
A39: 32 | B39: ITPMIS, ITPMD | C39: Female | D39: Pat | E39: CELARIO | F39: RUBY ROSE | G39: BUEZA | J39: 37 Tagumpay St. Marawi, Camiling, Tarlac | K39: 09514992446 | N39: =566-554 -> 12 | P39: =CONCATENATE(E39," ",F39," ",G39) -> CELARIO RUBY ROSE BUEZA | Q39: =IFERROR(VLOOKUP(P39,[1]Disposition!$AB$9:$AC$495,2,0),"NO RECORD YET") -> NO RECORD YET
A40: 33 | B40: ITPMIS, ITPMD | C40: Male | D40: Pat | E40: MANAOG | F40: RODNIE | G40: CASTILLO | J40: Sitio Pongol., Brgy. Burabod, San Antonio, Northern Samar | K40: 09452066435 | N40: 3 | P40: =CONCATENATE(E40," ",F40," ",G40) -> MANAOG RODNIE CASTILLO | Q40: =IFERROR(VLOOKUP(P40,[1]Disposition!$AB$9:$AC$495,2,0),"NO RECORD YET") -> NO RECORD YET
A41: 34 | B41: ITPMIS, ITPMD | C41: Male | D41: NUP | E41: DAGTA | F41: MARY ANN | G41: YAP | J41: Blk 3, Lot 20, Amber St., Summit Viwe Subd., Brgy. San Rafael, Rodriguez, Rizal | K41: 09568629227 | P41: =CONCATENATE(E41," ",F41," ",G41) -> DAGTA MARY ANN YAP | Q41: =IFERROR(VLOOKUP(P41,[1]Disposition!$AB$9:$AC$495,2,0),"NO RECORD YET") -> Blk 3, Lot 20, Amber St., Summit Viwe Subd., Brgy. San Rafael, Rodriguez, Rizal
A42: 35 | B42: EMS, ITPMD | C42: Male | D42: PMSg | E42: PEÑAVERDE | F42: PHILIP JAMES | G42: RODRIGUEZ | J42: Blk 1 Lot 128 P1-F Sub-Urban Village, Saan Jose, Rodriguez, Rizal | K42: 09266167584 | P42: =CONCATENATE(E42," ",F42," ",G42) -> PEÑAVERDE PHILIP JAMES RODRIGUEZ | Q42: =IFERROR(VLOOKUP(P42,[1]Disposition!$AB$9:$AC$495,2,0),"NO RECORD YET") -> Blk 1 Lot 128 P1-F Sub-Urban Village, Saan Jose, Rodriguez, Rizal
A43: 36 | B43: EMS, ITPMD | C43: Male | D43: Pat | E43: MORTEL | F43: ALWYN | G43: ALBUFERA | J43: 330 Ilaya, Butong, Taal, Batangas | K43: 09652107608 | N43: 4 | P43: =CONCATENATE(E43," ",F43," ",G43) -> MORTEL ALWYN ALBUFERA | Q43: =IFERROR(VLOOKUP(P43,[1]Disposition!$AB$9:$AC$495,2,0),"NO RECORD YET") -> NO RECORD YET
A44: 37 | B44: EMS, ITPMD | C44: Female | D44: NUP | E44: BERENGUEL | F44: LUCHIE | G44: RELOYA | J44: #2 Alley 15, P. Rosales St., Sta. Ana Kaliwa, Pateros | K44: 09662553586 | P44: =CONCATENATE(E568," ",F568," ",G568) -> RAMOS WENCESLAO AGUILAR | Q44: =IFERROR(VLOOKUP(P44,[1]Disposition!$AB$9:$AC$495,2,0),"NO RECORD YET") -> 5-A St.Paul St., Remerville Subd. Baesa, Quezon City
A45: 38 | B45: ITPMD (OCPNP) | C45: Male | D45: PCPT | E45: SOSA | F45: GIBSON JOHN | G45: ARAOS | J45: #10 Singapore, Bastulde, Fil-Inves, Cainta, Rizal | K45: 09176229285 | P45: =CONCATENATE(E45," ",F45," ",G45) -> SOSA GIBSON JOHN ARAOS | Q45: =IFERROR(VLOOKUP(P45,[1]Disposition!$AB$9:$AC$495,2,0),"NO RECORD YET") -> #10 Singapore, Bastulde, Fil-Inves, Cainta, Rizal
A46: 39 | B46: ITPMD (OCPNP) | C46: Male | D46: PCPT | E46: TAN | F46: ACHILES | G46: YABUT | J46: Blk 1 Lot 33, Maunlad Homes Subd., Caingin, Malolos, Bulacan | K46: 09985974254 | P46: =CONCATENATE(E46," ",F46," ",G46) -> TAN ACHILES YABUT | Q46: =IFERROR(VLOOKUP(P46,[1]Disposition!$AB$9:$AC$495,2,0),"NO RECORD YET") -> Blk 1 Lot 33, Maunlad Homes Subd., Caingin, Malolos, Bulacan
A47: 40 | B47: ITPMD (OCPNP) | C47: Female | D47: PCpl | E47: CLAOR | F47: MICHELLE | G47: DUGAM | J47: Toon, La Paz, Abra | K47: 09556384560 | P47: =CONCATENATE(E47," ",F47," ",G47) -> CLAOR MICHELLE DUGAM | Q47: =IFERROR(VLOOKUP(P47,[1]Disposition!$AB$9:$AC$495,2,0),"NO RECORD YET") -> Toon, La Paz, Abra
A48: 41 | B48: ITPMD (PIO) | C48: Male | D48: PCPT | E48: ALIMAMBO | F48: JICK | G48: BONUAN | J48: 72 Pucay Village, Purok I, Bakakeng Norte, Baguio City | K48: 09774274007 | P48: =CONCATENATE(E48," ",F48," ",G48) -> ALIMAMBO JICK BONUAN | Q48: =IFERROR(VLOOKUP(P48,[1]Disposition!$AB$9:$AC$495,2,0),"NO RECORD YET") -> 72 Pucay Village, Purok I, Bakakeng Norte, Baguio City
A49: 42 | B49: ITPMD (CPSM) | C49: Male | D49: Pat | E49: TUBELLEZA | F49: JOHN CARLO | G49: VILLARINO | J49: 33 Family Ville Subdivision, Bucal, Tanza, Cavite | K49: 09957230126 | P49: =CONCATENATE(E49," ",F49," ",G49) -> TUBELLEZA JOHN CARLO VILLARINO | Q49: =IFERROR(VLOOKUP(P49,[1]Disposition!$AB$9:$AC$495,2,0),"NO RECORD YET") -> NO RECORD YET
A50: 43 | B50: ITPMD (CPSM/IAS) | C50: Male | D50: PCpl | E50: LUALHATI | F50: PAULO ANDREW | G50: PUNZALAN | J50: 33 Jw Diokno St., Poblacion 13, Taal, Batangas | K50: 09568569677 | P50: =CONCATENATE(E50," ",F50," ",G50) -> LUALHATI PAULO ANDREW PUNZALAN | Q50: =IFERROR(VLOOKUP(P50,[1]Disposition!$AB$9:$AC$495,2,0),"NO RECORD YET") -> 33 JW Diokno St., Poblacion 13, Taal, Batangas
A51: 44 | B51: ITPMD (HRAO) | C51: Female | D51: PCPT | E51: SALAS | F51: EUNILAINE | G51: SALVADOR | J51: 131 Wwest Drive St., Narikina Heights, Marikina City | K51: 09175518988 | P51: =CONCATENATE(E51," ",F51," ",G51) -> SALAS EUNILAINE SALVADOR | Q51: =IFERROR(VLOOKUP(P51,[1]Disposition!$AB$9:$AC$495,2,0),"NO RECORD YET") -> 131 Wwest Drive St., Narikina Heights, Marikina City
A52: 45 | B52: ITPMD (IAS) | C52: Male | D52: PLT | E52: ECHANO | F52: KERWIN | G52: RUFON | J52: Lot 37-38 Blk.5 Catanauan St., Vanessa Homes, Bucal, Calamba, Laguna | K52: 09760708892 | P52: =CONCATENATE(E52," ",F52," ",G52) -> ECHANO KERWIN RUFON | Q52: =IFERROR(VLOOKUP(P52,[1]Disposition!$AB$9:$AC$495,2,0),"NO RECORD YET") -> Lot 37-38 BLK.5 Catanauan ST., Vanessa Homes, Bucal, Calamba, Laguna
A53: 46 | B53: ITPMD (EOD/K9) | C53: Male | D53: PMAJ | E53: LAXAMANA | F53: JOSE | G53: DELA CRUZ | H53: II | J53: 191 Gen. Mascardo St., Bagong Barrio, Caloocan City | K53: 09983998333 | P53: =CONCATENATE(E53," ",F53," ",G53) -> LAXAMANA JOSE DELA CRUZ | Q53: =IFERROR(VLOOKUP(P53,[1]Disposition!$AB$9:$AC$495,2,0),"NO RECORD YET") -> 191 Gen. Mascardo St., Bagong Barrio, Caloocan City
A54: 47 | B54: ITPMD (EOD/K9) | C54: Male | D54: Pat | E54: AGUILANDO | F54: ADAMSON | G54: BANDONG | J54: 189, Sitio Palsic, Naguilayan, San Carlos City, Pangasinan | K54: 09275465069 | P54: =CONCATENATE(E54," ",F54," ",G54) -> AGUILANDO ADAMSON BANDONG | Q54: =IFERROR(VLOOKUP(P54,[1]Disposition!$AB$9:$AC$495,2,0),"NO RECORD YET") -> NO RECORD YET
A55: 48 | B55: ITPMD (OTDCA) | C55: Male | D55: Pat | E55: BACATAN | F55: FERDINAND | G55: JALOVA | H55: JR | J55: Blk 55b Lot 1 Sitio Panghulo, Floodway, San Juan, Taytay, Rizal | K55: 09465348401 | P55: =CONCATENATE(E55," ",F55," ",G55) -> BACATAN FERDINAND JALOVA | Q55: =IFERROR(VLOOKUP(P55,[1]Disposition!$AB$9:$AC$495,2,0),"NO RECORD YET") -> NO RECORD YET
A56: 49 | B56: ITPMD (OTDCO) | C56: Male | D56: PCPT | E56: MUÑOZ | F56: RANZ NIKKO | G56: BIEN | J56: Blk. 15 Lot 22, Viola St., Camella Sorrento, P.F. Espiritu Iv, Bacoor, Cavite | K56: 09959045925 | P56: =CONCATENATE(E56," ",F56," ",G56) -> MUÑOZ RANZ NIKKO BIEN | Q56: =IFERROR(VLOOKUP(P56,[1]Disposition!$AB$9:$AC$495,2,0),"NO RECORD YET") -> Blk. 15 Lot 22, Viola St., Camella Sorrento, P.F. Espiritu IV, Bacoor, Cavite
A57: 50 | B57: ITPMD (OTDCO) | C57: Male | D57: PCMS | E57: MARAÑON | F57: CHRIS JOHN | G57: CATALOGO | J57: B18 L1 P-J Francisco Homes, Sjdm, Bulacan | K57: 09217221646 | P57: =CONCATENATE(E57," ",F57," ",G57) -> MARAÑON CHRIS JOHN CATALOGO | Q57: =IFERROR(VLOOKUP(P57,[1]Disposition!$AB$9:$AC$495,2,0),"NO RECORD YET") -> B18 L1 P-J Francisco Homes, SJDM, Bulacan
A58: 51 | B58: ITPMD (OTCDS) | C58: Male | D58: PMAJ | E58: AMIT | F58: ARIEL | G58: DE GUZMAN | J58: Manila, Metro Manila | K58: 09205682939 | P58: =CONCATENATE(E58," ",F58," ",G58) -> AMIT ARIEL DE GUZMAN | Q58: =IFERROR(VLOOKUP(P58,[1]Disposition!$AB$9:$AC$495,2,0),"NO RECORD YET") -> Manila, Metro Manila
A59: 52 | B59: ITPMD (OTCDS) | C59: Male | D59: PLT | E59: ILACAD | F59: DIONELL | G59: TUGADE | P59: =CONCATENATE(E59," ",F59," ",G59) -> ILACAD DIONELL TUGADE
A60: 53 | B60: ITPMD (OTCDS) | C60: Male | D60: PMSg | E60: DULIN | F60: JOEY | G60: BINARAO | J60: 155 19Th Avenue, East Pembo, Makati City | K60: 09175073304 | P60: =CONCATENATE(E60," ",F60," ",G60) -> DULIN JOEY BINARAO | Q60: =IFERROR(VLOOKUP(P60,[1]Disposition!$AB$9:$AC$495,2,0),"NO RECORD YET") -> 155 19th Avenue, East Pembo, Makati City
A61: 54 | B61: ITPMD (OTCDS) | C61: Male | D61: PCpl | E61: DOCTOLERO | F61: JOHN NICK | G61: DE GUZMAN | J61: B25 L5 Ph. J, Brgy. Guijo, Francisco Homes, Sjdm, Bulacan | K61: 09063610614 | P61: =CONCATENATE(E61," ",F61," ",G61) -> DOCTOLERO JOHN NICK DE GUZMAN | Q61: =IFERROR(VLOOKUP(P61,[1]Disposition!$AB$9:$AC$495,2,0),"NO RECORD YET") -> B25 L5 PH. J, Brgy. Guijo, Francisco Homes, SJDM, Bulacan
A62: 55 | B62: ITPMD (DPRM) | C62: Male | D62: PMAJ | E62: DELA CRUZ | F62: ALVIN | G62: ORUA | J62: #6087 Sto. Rosario St., Mapulang Lupa, Valenzuela City | K62: 09178710735 | P62: =CONCATENATE(E62," ",F62," ",G62) -> DELA CRUZ ALVIN ORUA | Q62: =IFERROR(VLOOKUP(P62,[1]Disposition!$AB$9:$AC$495,2,0),"NO RECORD YET") -> #6087 Sto. Rosario St., Mapulang Lupa, Valenzuela City
A63: 56 | B63: ITPMD (DPRM) | C63: Male | D63: PMAJ | E63: DESEO | F63: REYNANTE | G63: NUYDA | J63: Blk 4 L17 Arty In Subdivision, Karuhatan, Valenzueal City | K63: 09974766710 | P63: =CONCATENATE(E63," ",F63," ",G63) -> DESEO REYNANTE NUYDA | Q63: =IFERROR(VLOOKUP(P63,[1]Disposition!$AB$9:$AC$495,2,0),"NO RECORD YET") -> Blk 4 L17 Arty in Subdivision, Karuhatan, Valenzueal City
A64: 57 | B64: ITPMD (DPRM) | C64: Female | D64: PCpl | E64: CASTRO | F64: MARYJANE | G64: DIZON | J64: Phase 1, Purok 5, Taugtog, Botolan, Zambales | K64: 09501115804 | P64: =CONCATENATE(E64," ",F64," ",G64) -> CASTRO MARYJANE DIZON | Q64: =IFERROR(VLOOKUP(P64,[1]Disposition!$AB$9:$AC$495,2,0),"NO RECORD YET") -> Phase 1, Purok 5, Taugtog, Botolan, Zambales
A65: 58 | B65: ITPMD (DPRM) | C65: Male | D65: Pat | E65: CORTEZ | F65: JERWIN | G65: AQUINO | J65: Purok Happy Valley 2, San Vicente, Santa Ignacia, Tarlac | K65: 09101247667 | P65: =CONCATENATE(E65," ",F65," ",G65) -> CORTEZ JERWIN AQUINO | Q65: =IFERROR(VLOOKUP(P65,[1]Disposition!$AB$9:$AC$495,2,0),"NO RECORD YET") -> NO RECORD YET
A66: 59 | B66: ITPMD (DPRM) | C66: Male | D66: Pat | E66: MANIQUIZ | F66: JEREMY | G66: BINUYA | J66: Quezon, Entablado, Cabiao, Nueva Ecija | K66: 09096575574 | P66: =CONCATENATE(E66," ",F66," ",G66) -> MANIQUIZ JEREMY BINUYA | Q66: =IFERROR(VLOOKUP(P66,[1]Disposition!$AB$9:$AC$495,2,0),"NO RECORD YET") -> NO RECORD YET
A67: 60 | B67: ITPMD (DPRM) | C67: Female | D67: NUP | E67: LUMABI | F67: GINA | G67: TINGALA | J67: Mb 15 Rm 109, Diego Silang Village, Brgy Ususan, Taguig City | K67: 09471754148 | P67: =CONCATENATE(E67," ",F67," ",G67) -> LUMABI GINA TINGALA | Q67: =IFERROR(VLOOKUP(P67,[1]Disposition!$AB$9:$AC$495,2,0),"NO RECORD YET") -> MB 15 RM 109, Diego Silang Village, Brgy Ususan, Taguig City
A68: 61 | B68: ITPMD (DPRM) | C68: Female | D68: NUP | E68: UBANDO | F68: MARY ANN | G68: OBENA | J68: Blk 13 Lot 14 Phase M, Francisco Homes, Brgy. Guijo, Sjdm, Bulacan | K68: 09197265632 | P68: =CONCATENATE(E68," ",F68," ",G68) -> UBANDO MARY ANN OBENA | Q68: =IFERROR(VLOOKUP(P68,[1]Disposition!$AB$9:$AC$495,2,0),"NO RECORD YET") -> Blk 13 Lot 14 Phase M, Francisco Homes, Brgy. Guijo, SJDM, Bulacan
A69: 62 | B69: ITPMD (DPRM-DLOD) | C69: Male | D69: Pat | E69: CAGUITE | F69: JOHN REX | G69: ALIDO | J69: Diversion Road, Sitio Guinting, Lalig, Tiaong, Quezon | K69: 09773618665 | P69: =CONCATENATE(E69," ",F69," ",G69) -> CAGUITE JOHN REX ALIDO | Q69: =IFERROR(VLOOKUP(P69,[1]Disposition!$AB$9:$AC$495,2,0),"NO RECORD YET") -> NO RECORD YET
A70: 63 | B70: ITPMD (DPRM-DLOD) | C70: Male | D70: Pat | E70: TAGPAO | F70: RAFAEL | G70: ALUNDAY | J70: Purok 7, Sitio, Dat-Ayan, Minagbag, Quezon, Isabela | K70: 09263606410 | P70: =CONCATENATE(E70," ",F70," ",G70) -> TAGPAO RAFAEL ALUNDAY | Q70: =IFERROR(VLOOKUP(P70,[1]Disposition!$AB$9:$AC$495,2,0),"NO RECORD YET") -> NO RECORD YET
A71: 64 | B71: ITPMD (DRD) | C71: Male | D71: Pat | E71: VILLEGAS | F71: NAIF | G71: STA ANA | J71: #280 Gomez, Santa Rosa, Nueva Ecija | K71: 09267230880 | P71: =CONCATENATE(E71," ",F71," ",G71) -> VILLEGAS NAIF STA ANA | Q71: =IFERROR(VLOOKUP(P71,[1]Disposition!$AB$9:$AC$495,2,0),"NO RECORD YET") -> NO RECORD YET
... A73: 66 | B73: ITPMD (DIDM) | C73: Male | D73: PLT | E73: ABO | F73: MARK JESSIE | G73: MELITANTE | J73: Unit 909, Amaia Skies Cuibao, P. Tuazon Ave., Socorro, Quezon City | K73: 09566570420 | P73: =CONCATENATE(E73," ",F73," ",G73) -> ABO MARK JESSIE MELITANTE | Q73: =IFERROR(VLOOKUP(P73,[1]Disposition!$AB$9:$AC$495,2,0),"NO RECORD YET") -> Unit 909, Amaia Skies Cuibao, P. Tuazon Ave., Socorro, Quezon City
A74: 67 | B74: ITPMD (DIDM) | C74: Male | D74: PLT | E74: GALAMGAM | F74: RAMON | G74: DIAZ | H74: JR | P74: =CONCATENATE(E74," ",F74," ",G74) -> GALAMGAM RAMON DIAZ
A75: 68 | B75: ITPMD (DIDM) | C75: Male | D75: PSMS | E75: TACTAY | F75: HENRY | G75: GOLINO | J75: 41 Quimmarayan, Sto. Domingo, Ilocos Sur | K75: 09950271798 | P75: =CONCATENATE(E75," ",F75," ",G75) -> TACTAY HENRY GOLINO | Q75: =IFERROR(VLOOKUP(P75,[1]Disposition!$AB$9:$AC$495,2,0),"NO RECORD YET") -> 41 Quimmarayan, Sto. Domingo, Ilocos Sur
A76: 69 | B76: ITPMD (DIDM) | C76: Female | D76: Pat | E76: ABRIAM | F76: ANNETH VALERIE | G76: MALNAT | J76: 13 P1 Villa Jose Ylanan, Maddela, Quirino | K76: 09686456470 | P76: =CONCATENATE(E76," ",F76," ",G76) -> ABRIAM ANNETH VALERIE MALNAT | Q76: =IFERROR(VLOOKUP(P76,[1]Disposition!$AB$9:$AC$495,2,0),"NO RECORD YET") -> NO RECORD YET
A77: 70 | B77: ITPMD (DIDM) | C77: Female | D77: Pat | E77: SAET | F77: MITZI ANNE | G77: BESA | J77: Lambingan, Sunrise Viu Village, San Guillermo, Morong, Rizal | K77: 09311126415 | P77: =CONCATENATE(E77," ",F77," ",G77) -> SAET MITZI ANNE BESA | Q77: =IFERROR(VLOOKUP(P77,[1]Disposition!$AB$9:$AC$495,2,0),"NO RECORD YET") -> NO RECORD YET
A78: 71 | B78: ITPMD (DIDM) | C78: Male | D78: Pat | E78: SALES | F78: JAFET | G78: ANINAO | J78: 164 J.P Rizal St., J.Rizal, Santa Maria, Laguna | K78: 09167919991 | P78: =CONCATENATE(E78," ",F78," ",G78) -> SALES JAFET ANINAO | Q78: =IFERROR(VLOOKUP(P78,[1]Disposition!$AB$9:$AC$495,2,0),"NO RECORD YET") -> NO RECORD YET
A79: 72 | B79: ITPMD (DIDM) | C79: Male | D79: NUP | E79: TACORDA | F79: JASON ABRAHAM | G79: ABION | J79: 2315 T2 Amaia Skies, Cubao, 5The Ave. Cor P Tuazon Ave., Brgy. Socorro, Quezon City | K79: 09150334133 | P79: =CONCATENATE(E79," ",F79," ",G79) -> TACORDA JASON ABRAHAM ABION | Q79: =IFERROR(VLOOKUP(P79,[1]Disposition!$AB$9:$AC$495,2,0),"NO RECORD YET") -> 2315 T2 Amaia Skies, Cubao, 5the Ave. cor P Tuazon Ave., Brgy. Socorro, Quezon City
A80: 73 | B80: ITPMD (DIDM-WCPC) | C80: Male | D80: PMAJ | E80: NICOLAS | F80: JAY-R | G80: TADEO | J80: #143 Asin West., Malasigue, Pangasinan | K80: 09770935729 | P80: =CONCATENATE(E80," ",F80," ",G80) -> NICOLAS JAY-R TADEO | Q80: =IFERROR(VLOOKUP(P80,[1]Disposition!$AB$9:$AC$495,2,0),"NO RECORD YET") -> #143 Asin West., Malasigue, Pangasinan
A81: 74 | B81: ITPMD (DPL) | C81: Male | D81: PMAJ | E81: SY | F81: CHRISTIAN | G81: ONG | J81: 4 | K81: 09176548452 | P81: =CONCATENATE(E81," ",F81," ",G81) -> SY CHRISTIAN ONG | Q81: =IFERROR(VLOOKUP(P81,[1]Disposition!$AB$9:$AC$495,2,0),"NO RECORD YET") -> B3 L4 Ephesians St., Sta. Monica Heights, Suqui, Calapan City, Oriental Mindoro
A82: 75 | B82: ITPMD (DPL) | C82: Male | D82: Pat | E82: OBOG | F82: JOHN MARLO | G82: MAGRAMO | J82: 0550 Sanggumay, Looc, Calamba, Laguna | K82: 09161978384 | P82: =CONCATENATE(E82," ",F82," ",G82) -> OBOG JOHN MARLO MAGRAMO | Q82: =IFERROR(VLOOKUP(P82,[1]Disposition!$AB$9:$AC$495,2,0),"NO RECORD YET") -> NO RECORD YET
A83: 76 | B83: ITPMD (DPL) | C83: Male | D83: NUP | E83: BUENSUCESO | F83: NEIL PAUL | G83: BAUTISTA | P83: =CONCATENATE(E83," ",F83," ",G83) -> BUENSUCESO NEIL PAUL BAUTISTA
A84: 77 | B84: ITPMD (DL) | C84: Male | D84: PMAJ | E84: DULA | F84: JOEL | G84: MANALANSAN | J84: 407 Purok 7, New San Juan, Dinalupihan, Bataan | K84: 09667058328 | P84: =CONCATENATE(E84," ",F84," ",G84) -> DULA JOEL MANALANSAN | Q84: =IFERROR(VLOOKUP(P84,[1]Disposition!$AB$9:$AC$495,2,0),"NO RECORD YET") -> 407 Purok 7, New San Juan, Dinalupihan, Bataan
A85: 78 | B85: ITPMD (DL) | C85: Female | D85: PCPT | E85: DIMASANGKAY | F85: SORAIYA | G85: MUSAID | J85: Silver Homes Subdivision, Sadaan, Midsayap, Cotabato | P85: =CONCATENATE(E85," ",F85," ",G85) -> DIMASANGKAY SORAIYA MUSAID | Q85: =IFERROR(VLOOKUP(P85,[1]Disposition!$AB$9:$AC$495,2,0),"NO RECORD YET") -> NO RECORD YET
A86: 79 | B86: ITPMD (DL) | C86: Female | D86: NUP | E86: JEPOLLO | F86: JOCELYN | G86: TAMONDONG | J86: #7 4Th Avenue, Bagong Lipunan, Crame, Quezon City | K86: 09977830520 | P86: =CONCATENATE(E86," ",F86," ",G86) -> JEPOLLO JOCELYN TAMONDONG | Q86: =IFERROR(VLOOKUP(P86,[1]Disposition!$AB$9:$AC$495,2,0),"NO RECORD YET") -> #7 4TH Avenue, Bagong Lipunan, Crame, Quezon City
A87: 80 | B87: ITPMD (DL) | C87: Female | D87: NUP | E87: TODA | F87: MA CRISTINA | G87: TAMONDONG | J87: 19 A J Ocampo St., Project 4, Quezon City | K87: 09175065455 | P87: =CONCATENATE(E87," ",F87," ",G87) -> TODA MA CRISTINA TAMONDONG | Q87: =IFERROR(VLOOKUP(P87,[1]Disposition!$AB$9:$AC$495,2,0),"NO RECORD YET") -> 19 A J Ocampo St., Project 4, Quezon City
A88: 81 | B88: ITPMD (DC) | C88: Male | D88: PCPT | E88: BALLENAS | F88: ROBERTO | G88: ALPAS | H88: JR | J88: Purok Masipag, Buayan, M'Lang, Cotabato, North Cotabato | K88: 09664625855 | P88: =CONCATENATE(E88," ",F88," ",G88) -> BALLENAS ROBERTO ALPAS | Q88: =IFERROR(VLOOKUP(P88,[1]Disposition!$AB$9:$AC$495,2,0),"NO RECORD YET") -> Purok Masipag, Buayan, M'lang, Cotabato, North Cotabato
A89: 82 | B89: ITPMD (DC) | C89: Female | D89: Pat | E89: GUAVINO | F89: CHE-YENNE | G89: LAZARITO | J89: Apartment 23, Emq Camp Crame, Bagong Lipunan Ng Crame, Qauezon City | K89: 09179975888 | P89: =CONCATENATE(E89," ",F89," ",G89) -> GUAVINO CHE-YENNE LAZARITO | Q89: =IFERROR(VLOOKUP(P89,[1]Disposition!$AB$9:$AC$495,2,0),"NO RECORD YET") -> Apartment 23, EMQ Camp Crame, Bagong Lipunan ng Crame, Qauezon City
A90: 83 | B90: ITPMD (DC) | C90: Male | D90: Pat | E90: INALVEZ | F90: NEIL ADRIAN | G90: NUCOM | J90: 676 Purok Kb3, Maugat, San Antonio, Nueva Ecija, | K90: 09531143703 | P90: =CONCATENATE(E90," ",F90," ",G90) -> INALVEZ NEIL ADRIAN NUCOM | Q90: =IFERROR(VLOOKUP(P90,[1]Disposition!$AB$9:$AC$495,2,0),"NO RECORD YET") -> 676 Purok KB3, Maugat, San Antonio, Nueva Ecija,
A91: 84 | B91: ITPMD (DPCR) | C91: Female | D91: PCPT | E91: BUHAIN | F91: DOROTHY | G91: VILLALOBOS | J91: 301 Masagana Subd., Gumamela St., San Francisco, Bulacan | K91: 09567595065 | P91: =CONCATENATE(E91," ",F91," ",G91) -> BUHAIN DOROTHY VILLALOBOS | Q91: =IFERROR(VLOOKUP(P91,[1]Disposition!$AB$9:$AC$495,2,0),"NO RECORD YET") -> 301 Masagana Subd., Gumamela St., San Francisco, Bulacan
A92: 85 | B92: ITPMD (DPCR) | C92: Male | D92: PSMS | E92: SIBAYAN | F92: REYGIE | G92: PIAGAN | J92: Giron St., Brgy No. 2, Santa Joaquina, Laoag City, Ilocos Norte | K92: 09082302544 | P92: =CONCATENATE(E92," ",F92," ",G92) -> SIBAYAN REYGIE PIAGAN | Q92: =IFERROR(VLOOKUP(P92,[1]Disposition!$AB$9:$AC$495,2,0),"NO RECORD YET") -> Giron St., BRGY NO. 2, Santa Joaquina, Laoag City, Ilocos Norte
A93: 86 | B93: ITPMD (DPCR) | C93: Male | D93: Pat | E93: CORDERO | F93: EARLBON | G93: JIMENEZ | J93: 1362 R.A Reyes Street, Tondo, Manila | K93: 09066901087 | P93: =CONCATENATE(E93," ",F93," ",G93) -> CORDERO EARLBON JIMENEZ | Q93: =IFERROR(VLOOKUP(P93,[1]Disposition!$AB$9:$AC$495,2,0),"NO RECORD YET") -> NO RECORD YET
A94: 87 | B94: ITPMD (DPCR) | C94: Male | D94: Pat | E94: ORLANDA | F94: BERNABE | G94: MACADANGDANG | H94: JR | J94: Sitio Malubec Curva, Pamplona, Cagayan | K94: 09975442501 | P94: =CONCATENATE(E94," ",F94," ",G94) -> ORLANDA BERNABE MACADANGDANG | Q94: =IFERROR(VLOOKUP(P94,[1]Disposition!$AB$9:$AC$495,2,0),"NO RECORD YET") -> NO RECORD YET
A95: 88 | B95: ITPMD (DHRDD/PRO1) | C95: Male | D95: PLTCOL | E95: SEVILLA | F95: JERALD | G95: MANUZON | J95: B-38 L-20 Violeta St., Pembo, Makati City | K95: 09176055075 | P95: =CONCATENATE(E95," ",F95," ",G95) -> SEVILLA JERALD MANUZON | Q95: =IFERROR(VLOOKUP(P95,[1]Disposition!$AB$9:$AC$495,2,0),"NO RECORD YET") -> B-38 L-20 Violeta St., Pembo, Makati City
A96: 89 | B96: ITPMD (DHRDD) | C96: Female | D96: PCPT | E96: SUAYA | F96: RAFFY JANE | G96: ALIDAO | J96: #25 C Purok 1, Lower Liwanag, Liwanag-Loakan, Baguio City, Benguet | K96: 09126980797 | P96: =CONCATENATE(E96," ",F96," ",G96) -> SUAYA RAFFY JANE ALIDAO | Q96: =IFERROR(VLOOKUP(P96,[1]Disposition!$AB$9:$AC$495,2,0),"NO RECORD YET") -> #25 C Purok 1, Lower Liwanag, Liwanag-Loakan, Baguio City, Benguet
A97: 90 | B97: ITPMD (DI) | C97: Female | D97: PCPT | E97: REVALE | F97: EDELLENE | G97: BABAGAY | J97: P3 Brgy. Ems Barrio, Legaspi City, Albay | K97: 09994275134 | P97: =CONCATENATE(E97," ",F97," ",G97) -> REVALE EDELLENE BABAGAY | Q97: =IFERROR(VLOOKUP(P97,[1]Disposition!$AB$9:$AC$495,2,0),"NO RECORD YET") -> P3 Brgy. Ems Barrio, Legaspi City, Albay
A98: 91 | B98: ITPMD (DI) | C98: Male | D98: PCPT | E98: SOBREVILLA | F98: RAYMUND CHRISTOPHER | G98: DECIPULO | J98: 15 F Int. Del Pilar St., Purok Bougambilla, Brgy. Bagja Mother, Cotabato City | K98: 09262417598 | P98: =CONCATENATE(E98," ",F98," ",G98) -> SOBREVILLA RAYMUND CHRISTOPHER DECIPULO | Q98: =IFERROR(VLOOKUP(P98,[1]Disposition!$AB$9:$AC$495,2,0),"NO RECORD YET") -> 15 F Int. Del Pilar ST., Purok Bougambilla, Brgy. Bagja Mother, Cotabato City
A99: 92 | B99: ITPMD (DI) | C99: Female | D99: PCPT | E99: ESTRADA | F99: MICAELLA ALLYSSA | G99: MONTES | J99: 15 Jonathan St., Brgy. 55, Tondo, Manila | K99: 09156803437 | P99: =CONCATENATE(E99," ",F99," ",G99) -> ESTRADA MICAELLA ALLYSSA MONTES | Q99: =IFERROR(VLOOKUP(P99,[1]Disposition!$AB$9:$AC$495,2,0),"NO RECORD YET") -> 15 Jonathan St., Brgy. 55, Tondo, Manila
A100: 93 | B100: ITPMD (DI) | C100: Male | D100: Pat | E100: CODIMO | F100: SOLOMON | G100: MADLAENG | J100: Old Poblacion, Burgos, La Union | K100: 09052120646 | P100: =CONCATENATE(E100," ",F100," ",G100) -> CODIMO SOLOMON MADLAENG | Q100: =IFERROR(VLOOKUP(P100,[1]Disposition!$AB$9:$AC$495,2,0),"NO RECORD YET") -> NO RECORD YET
A101: 94 | B101: ITPMD (DI) | C101: Male | D101: Pat | E101: MANGOBA | F101: ROMMEL | G101: JAZMIN | J101: Sitio Mangga, Pogon Lomboy, Mangatarem, Pangasinan | K101: 09208467671 | P101: =CONCATENATE(E101," ",F101," ",G101) -> MANGOBA ROMMEL JAZMIN | Q101: =IFERROR(VLOOKUP(P101,[1]Disposition!$AB$9:$AC$495,2,0),"NO RECORD YET") -> NO RECORD YET
A102: 95 | B102: ITPMD (DI)ODDA | C102: Female | D102: Pat | E102: MARASIGAN | F102: MIA ANGELA | G102: CORNEJO | J102: 121G 14Th Ave., Socorro, Quezon City | K102: 09568570005 | P102: =CONCATENATE(E102," ",F102," ",G102) -> MARASIGAN MIA ANGELA CORNEJO | Q102: =IFERROR(VLOOKUP(P102,[1]Disposition!$AB$9:$AC$495,2,0),"NO RECORD YET") -> 121G 14TH Ave., Socorro, Quezon City
A103: 96 | B103: ITPMD (DI) | C103: Female | D103: Pat | E103: RADA | F103: KRIZTELA FEY | G103: LIM | J103: Pili, San Fernando, Romblon | K103: 09562658528 | P103: =CONCATENATE(E103," ",F103," ",G103) -> RADA KRIZTELA FEY LIM | Q103: =IFERROR(VLOOKUP(P103,[1]Disposition!$AB$9:$AC$495,2,0),"NO RECORD YET") -> Pili, San Fernando, Romblon
...

Sheet detail Crame based
A1: Republic of the Philippines
A2: PHILIPPINE NATIONAL POLICE | J2: =259-240 -> 19
A3: INFORMATION TECHNOLOGY MANAGEMENT SERVICE | J3: =134-63 -> 71
A4: Camp Bgen Rafael T Crame, Quezon City
A6: Roster of Personnel (Detailed Crame Based)
A7: (As of January 22, 2026)
A9: NO. | B9: OFFICE/DIVISION | C9: GENDER | D9: RANK | E9: LASTNAME | F9: FIRSTNAME | G9: MIDDLE NAME | H9: QUAL | I9: SIGNATURE | J9: ADDRESS | K9: CONTACT # | P9: NAME | Q9: ADDRESS
A10: POLICE COMMISSIONED OFFICERS
A11: 1 | B11: PHAS(DICTM) | C11: Female | D11: PCOL | E11: DAMASO | F11: MARIBEL | G11: MONES | J11: 58 B, 8Th Ave., Brgy.Socorro, Cubao, Quezon City | K11: 09178740745 | P11: =CONCATENATE(E11," ",F11," ",G11) -> DAMASO MARIBEL MONES | Q11: =IFERROR(VLOOKUP(P11,[1]Disposition!$AB$9:$AC$495,2,0),"NO RECORD YET") -> 58 B, 8TH Ave., Brgy.SOcorro, Cubao, Quezon City
A12: 2 | B12: PHAS(DICTM) | C12: Male | D12: PCOL | E12: ESCOBAL | F12: CARLO JOSEPH | G12: TORRES | P12: =CONCATENATE(E12," ",F12," ",G12) -> ESCOBAL CARLO JOSEPH TORRES | Q12: =IFERROR(VLOOKUP(P12,[1]Disposition!$AB$9:$AC$495,2,0),"NO RECORD YET") -> NO RECORD YET
A13: 3 | B13: PHAS(DICTM) | C13: Male | D13: PCOL | E13: GACES | F13: JUANITO | G13: BALLUG | H13: JR | P13: =CONCATENATE(E13," ",F13," ",G13) -> GACES JUANITO BALLUG
A14: 4 | B14: PHAS(DICTM) | C14: Male | D14: PLTCOL | E14: BORJA | F14: BRIAN THEO | G14: PANGANIBAN | J14: 6 Ignacio Diaz St., Brgy. Kaunlaran, Cubao, Quezon City | K14: 09190794772 | P14: =CONCATENATE(E14," ",F14," ",G14) -> BORJA BRIAN THEO PANGANIBAN | Q14: =IFERROR(VLOOKUP(P14,[1]Disposition!$AB$9:$AC$495,2,0),"NO RECORD YET") -> 6 Ignacio Diaz St., Brgy. Kaunlaran, Cubao, Quezon City
A15: 5 | B15: ITPMD (ACG/PRO BAR) | C15: Male | D15: PLTCOL | E15: FERRANCULLO | F15: JOHN PAUL | G15: PAZ | J15: 103 Hernandez St., Old Zaniga, Mandaluyong Cityn | K15: 09987914105 | P15: =CONCATENATE(E15," ",F15," ",G15) -> FERRANCULLO JOHN PAUL PAZ | Q15: =IFERROR(VLOOKUP(P15,[1]Disposition!$AB$9:$AC$495,2,0),"NO RECORD YET") -> 103 Hernandez St., Old Zaniga, Mandaluyong CityN
A16: 6 | B16: PHAS(PRO CAR/DICTM) | C16: Male | D16: PLTCOL | E16: FONCARDAS | F16: MARK | G16: REYES | P16: =CONCATENATE(G31," ",F31," ",#REF!) -> #REF! | Q16: =IFERROR(VLOOKUP(P16,[1]Disposition!$AB$9:$AC$495,2,0),"NO RECORD YET") -> NO RECORD YET
A17: 7 | B17: ITPMD (MG/DO/RICTMD PRO12) | C17: Male | D17: PLTCOL | E17: IGNACIO | F17: MICHAEL | G17: TINTE | J17: 38 Aganan St., Zone 6, Nia Village, Quezon City | K17: 09998842166 | P17: =CONCATENATE(E17," ",F17," ",G17) -> IGNACIO MICHAEL TINTE | Q17: =IFERROR(VLOOKUP(P17,[1]Disposition!$AB$9:$AC$495,2,0),"NO RECORD YET") -> 38 Aganan St., Zone 6, NIA Village, Quezon City
A18: 8 | B18: PHAS(DICTM) | C18: Female | D18: PLTCOL | E18: MARAMAG | F18: MARCIANA | G18: DELA CRUZ | P18: =CONCATENATE(E18," ",F18," ",G18) -> MARAMAG MARCIANA DELA CRUZ | Q18: =IFERROR(VLOOKUP(P18,[1]Disposition!$AB$9:$AC$495,2,0),"NO RECORD YET") -> NO RECORD YET
A19: 9 | B19: PHAS(DICTM) | C19: Male | D19: PLTCOL | E19: REYES | F19: ROBERT | G19: ANDAL | J19: 7 Antipoli Ext., Krus Na Ligas, Quezon City | K19: 09055320909 | P19: =CONCATENATE(E19," ",F19," ",G19) -> REYES ROBERT ANDAL | Q19: =IFERROR(VLOOKUP(P19,[1]Disposition!$AB$9:$AC$495,2,0),"NO RECORD YET") -> 7 Antipoli Ext., Krus na Ligas, Quezon City
A20: 10 | B20: PHAS (RICTMD PRO4B/FS) | C20: Male | D20: PLTCOL | E20: SANTOS | F20: JAY WALTER | G20: SANTIAGO | J20: #109-B Herbosa St., Tondo, Manila | K20: 09166183905 | P20: =CONCATENATE(E20," ",F20," ",G20) -> SANTOS JAY WALTER SANTIAGO | Q20: =IFERROR(VLOOKUP(P20,[1]Disposition!$AB$9:$AC$495,2,0),"NO RECORD YET") -> #109-B Herbosa St., Tondo, Manila
A21: 11 | B21: ITPMD (DHRDD/PRO1) | C21: Male | D21: PLTCOL | E21: SEVILLA | F21: JERALD | G21: MANUZON | J21: B-38 L-20 Violeta St., Pembo, Makati City | K21: 09176055075 | P21: =CONCATENATE(E21," ",F21," ",G21) -> SEVILLA JERALD MANUZON | Q21: =IFERROR(VLOOKUP(P21,[1]Disposition!$AB$9:$AC$495,2,0),"NO RECORD YET") -> B-38 L-20 Violeta St., Pembo, Makati City
A22: 12 | B22: ITPMD (OTCDS) | C22: Male | D22: PMAJ | E22: AMIT | F22: ARIEL | G22: DE GUZMAN | J22: Manila, Metro Manila | K22: 09205682939 | P22: =CONCATENATE(#REF!," ",#REF!," ",#REF!) -> #REF! | Q22: =IFERROR(VLOOKUP(P22,[1]Disposition!$AB$9:$AC$495,2,0),"NO RECORD YET") -> NO RECORD YET
A23: 13 | B23: ITPMD (HS)/SMD | C23: Male | D23: PMAJ | E23: ANDANAR | F23: JON JASON | G23: GORGOLON | J23: B6, L2, Kingstown Subd., Brgy. 171, Caloocan City | K23: 09173197823 | P23: =CONCATENATE(E23," ",F23," ",G23) -> ANDANAR JON JASON GORGOLON | Q23: =IFERROR(VLOOKUP(P23,[1]Disposition!$AB$9:$AC$495,2,0),"NO RECORD YET") -> B6, L2, Kingstown Subd., Brgy. 171, Caloocan City
A24: 14 | B24: PHAS(DICTM) | C24: Female | D24: PMAJ | E24: BELLY | F24: JOCELYN | G24: DEL BARRIO | J24: B6 L2, Hilltop, Abatex, San Jose, Rodriguez, Rizal | K24: 09338637458 | P24: =CONCATENATE(E24," ",F24," ",G24) -> BELLY JOCELYN DEL BARRIO | Q24: =IFERROR(VLOOKUP(P24,[1]Disposition!$AB$9:$AC$495,2,0),"NO RECORD YET") -> B6 L2, Hilltop, Abatex, San Jose, Rodriguez, Rizal
A25: 15 | B25: PHAS(DICTM) | C25: Female | D25: PMAJ | E25: CRUZ | F25: MARICON | G25: TAYAMEN | J25: B6 L2 11Th Ave., Hhsg Extebsion, North Signal Village, Taguig City | K25: 09272162479 | P25: =CONCATENATE(E25," ",F25," ",G25) -> CRUZ MARICON TAYAMEN
A26: 16 | B26: ITPMD (DPRM) | C26: Male | D26: PMAJ | E26: DELA CRUZ | F26: ALVIN | G26: ORUA | J26: #6087 Sto. Rosario St., Mapulang Lupa, Valenzuela City | K26: 09178710735 | P26: =CONCATENATE(E26," ",F26," ",G26) -> DELA CRUZ ALVIN ORUA | Q26: =IFERROR(VLOOKUP(P26,[1]Disposition!$AB$9:$AC$495,2,0),"NO RECORD YET") -> #6087 Sto. Rosario St., Mapulang Lupa, Valenzuela City
A27: 17 | B27: ITPMD (DPRM) | C27: Male | D27: PMAJ | E27: DESEO | F27: REYNANTE | G27: NUYDA | J27: Blk 4 L17 Arty In Subdivision, Karuhatan, Valenzueal City | K27: 09974766710 | P27: =CONCATENATE(E27," ",F27," ",G27) -> DESEO REYNANTE NUYDA | Q27: =IFERROR(VLOOKUP(P27,[1]Disposition!$AB$9:$AC$495,2,0),"NO RECORD YET") -> Blk 4 L17 Arty in Subdivision, Karuhatan, Valenzueal City
A28: 18 | B28: ITPMD (DL) | C28: Male | D28: PMAJ | E28: DULA | F28: JOEL | G28: MANALANSAN | J28: 407 Purok 7, New San Juan, Dinalupihan, Bataan | K28: 09667058328 | P28: =CONCATENATE(E28," ",F28," ",G28) -> DULA JOEL MANALANSAN
A29: 19 | B29: ITPMD (PNP RSS) | C29: Male | D29: PMAJ | E29: ESCABOSA | F29: GEROGIL | G29: SALAZAR | J29: Blk 110 Lot 17 K-57 Kalinisan St., Karangalan V Illage, San Isidro Village, Cainta, Rizal | K29: 09171046735 | P29: =CONCATENATE(E29," ",F29," ",G29) -> ESCABOSA GEROGIL SALAZAR
A30: 20 | B30: ITPMD (EOD/K9) | C30: Male | D30: PMAJ | E30: LAXAMANA | F30: JOSE | G30: DELA CRUZ | H30: II | J30: 191 Gen. Mascardo St., Bagong Barrio, Caloocan City | K30: 09983998333 | P30: =CONCATENATE(E30," ",F30," ",G30) -> LAXAMANA JOSE DELA CRUZ
A31: 21 | B31: ITPMD (DIDM-WCPC) | C31: Male | D31: PMAJ | E31: NICOLAS | F31: JAY-R | G31: TADEO | J31: #143 Asin West., Malasigue, Pangasinan | K31: 09770935729 | P31: =CONCATENATE(#REF!," ",#REF!," ",#REF!) -> #REF!
A32: 22 | B32: ITPMD (DIDM) | C32: Male | D32: PMAJ | E32: NOBRES | F32: ROY | G32: DANGSI | J32: Lot 4-Lot 5 Metro Royale Homes Burgos, Montalban, Rizal | K32: 09178665305
A33: 23 | B33: ITPMD (CSG-SOSIA) | C33: Male | D33: PMAJ | E33: OCAMPO | F33: AMADO | G33: BISCAYDA | H33: JR | J33: 39 Constabulary St., Vet Village, Quezon City | K33: 09154810533 | P33: =CONCATENATE(#REF!," ",#REF!," ",#REF!) -> #REF! | Q33: =IFERROR(VLOOKUP(P33,[1]Disposition!$AB$9:$AC$495,2,0),"NO RECORD YET") -> NO RECORD YET
A34: 24 | B34: ITPMD (DPL) | C34: Male | D34: PMAJ | E34: SY | F34: CHRISTIAN | G34: ONG | J34: 4 | K34: 09176548452 | P34: =CONCATENATE('detail Crame based'!#REF!," ",'detail Crame based'!#REF!," ",'detail Crame based'!#REF!) -> #REF! | Q34: =IFERROR(VLOOKUP(P34,[1]Disposition!$AB$9:$AC$495,2,0),"NO RECORD YET") -> NO RECORD YET
A35: 25 | B35: PHAS(DICTM) | C35: Male | D35: PMAJ | E35: TAN | F35: ROBERT | G35: BACALTOS | J35: 847 Tahimik St., Delpan, Tondo, Manila | K35: 09176860807 | P35: =CONCATENATE(E35," ",F35," ",G35) -> TAN ROBERT BACALTOS | Q35: =IFERROR(VLOOKUP(P35,[1]Disposition!$AB$9:$AC$495,2,0),"NO RECORD YET") -> 847 Tahimik St., Delpan, Tondo, Manila
A36: 26 | B36: ITPMD (PSPG) | C36: Male | D36: PCPT | E36: ABUAN | F36: DICKSON | G36: CLEMENTE | J36: 735 Purok 4B, Lucnab Baguio City | K36: 09481748796 | P36: =CONCATENATE(E36," ",F36," ",G36) -> ABUAN DICKSON CLEMENTE
A37: 27 | B37: ITPMD (PIO) | C37: Male | D37: PCPT | E37: ALIMAMBO | F37: JICK | G37: BONUAN | J37: 72 Pucay Village, Purok I, Bakakeng Norte, Baguio City | K37: 09774274007 | P37: =CONCATENATE(E37," ",F37," ",G37) -> ALIMAMBO JICK BONUAN | Q37: =IFERROR(VLOOKUP(P37,[1]Disposition!$AB$9:$AC$495,2,0),"NO RECORD YET") -> 72 Pucay Village, Purok I, Bakakeng Norte, Baguio City
A38: 28 | B38: PHAS (CICC) | C38: Male | D38: PCPT | E38: ANURAN | F38: ADRIAN | G38: MIRASOL | J38: 57 A Delas Alas St., Zone 13, Taal, Batangas | K38: 09065467212 | P38: =CONCATENATE(E38," ",F38," ",G38) -> ANURAN ADRIAN MIRASOL | Q38: =IFERROR(VLOOKUP(P38,[1]Disposition!$AB$9:$AC$495,2,0),"NO RECORD YET") -> 57 A Delas Alas St., Zone 13, Taal, Batangas
A39: 29 | B39: ITPMD (CSG-FEO) | C39: Male | D39: PCPT | E39: BALICAG | F39: JOSE | G39: DAKETAN | H39: JR | J39: Block 3, D Molintas, Bulanao, Tabuk City Kalinga | K39: 09303641739 | P39: =CONCATENATE(E39," ",F39," ",G39) -> BALICAG JOSE DAKETAN
A40: 30 | B40: ITPMD (DC) | C40: Male | D40: PCPT | E40: BALLENAS | F40: ROBERTO | G40: ALPAS | H40: JR | J40: Purok Masipag, Buayan, M'Lang, Cotabato, North Cotabato | K40: 09664625855 | P40: =CONCATENATE(E40," ",F40," ",G40) -> BALLENAS ROBERTO ALPAS | Q40: =IFERROR(VLOOKUP(P40,[1]Disposition!$AB$9:$AC$495,2,0),"NO RECORD YET") -> Purok Masipag, Buayan, M'lang, Cotabato, North Cotabato
A41: 31 | B41: PHAS(DICTM) | C41: Male | D41: PCPT | E41: BATALLER | F41: SHERWIN SOLOMON | G41: BELLEN | H41: III | J41: J Rizal St., Paciano Rizal, Calamba City, Laguna | K41: 09175121981 | P41: =CONCATENATE(#REF!," ",#REF!," ",#REF!) -> #REF! | Q41: =IFERROR(VLOOKUP(P41,[1]Disposition!$AB$9:$AC$495,2,0),"NO RECORD YET") -> NO RECORD YET
A42: 32 | B42: ITPMD (PNPTS) | C42: Male | D42: PCPT | E42: BAYAUA | F42: ANGELO | G42: ZALUN | J42: B10 L23 P-H Guijo, Francisco Homes , Sjdm, Bulacan | K42: 09171108106 | P42: =CONCATENATE(E42," ",F42," ",G42) -> BAYAUA ANGELO ZALUN | Q42: =IFERROR(VLOOKUP(P42,[1]Disposition!$AB$9:$AC$495,2,0),"NO RECORD YET") -> B10 L23 P-H Guijo, Francisco Homes , SJDM, Bulacan
A43: 33 | B43: ITPMD (DPCR) | C43: Female | D43: PCPT | E43: BUHAIN | F43: DOROTHY | G43: VILLALOBOS | J43: 301 Masagana Subd., Gumamela St., San Francisco, Bulacan | K43: 09567595065 | P43: =CONCATENATE(E90," ",F90," ",G90) -> ECHEGOYEN RYAN MOJICA | Q43: =IFERROR(VLOOKUP(P43,[1]Disposition!$AB$9:$AC$495,2,0),"NO RECORD YET") -> 1061-A Molina Ext. San Antonio, Cavite City
A44: 34 | B44: PHAS(DICTM) | C44: Male | D44: PCPT | E44: CABATIN | F44: ROGEL VERGEL | G44: GUEVARRA | H44: JR | J44: 596 Re Chico St., Santo Cristo, Baliuag, Bulacan | K44: 09322461634 | P44: =CONCATENATE('detail Crame based'!D44," ",'detail Crame based'!E44," ",'detail Crame based'!F44) -> PCPT CABATIN ROGEL VERGEL | Q44: =IFERROR(VLOOKUP(P44,[1]Disposition!$AB$9:$AC$495,2,0),"NO RECORD YET") -> NO RECORD YET
A45: 35 | B45: PHAS(DICTM) | C45: Female | D45: PCPT | E45: CRUZ | F45: CRISTINA JOY | G45: VICENTE | J45: Pilapil Street, Sabang Calabanga, Camarines Sur | K45: 09123299695 | P45: =CONCATENATE('detail Crame based'!D45," ",'detail Crame based'!E45," ",'detail Crame based'!F45) -> PCPT CRUZ CRISTINA JOY | Q45: =IFERROR(VLOOKUP(P45,[1]Disposition!$AB$9:$AC$495,2,0),"NO RECORD YET") -> NO RECORD YET
A46: 36 | B46: ITPMD (DL) | C46: Female | D46: PCPT | E46: DIMASANGKAY | F46: SORAIYA | G46: MUSAID | J46: Silver Homes Subdivision, Sadaan, Midsayap, Cotabato | P46: =CONCATENATE('detail Crame based'!D46," ",'detail Crame based'!E46," ",'detail Crame based'!F46) -> PCPT DIMASANGKAY SORAIYA | Q46: =IFERROR(VLOOKUP(P46,[1]Disposition!$AB$9:$AC$495,2,0),"NO RECORD YET") -> NO RECORD YET
A47: 37 | B47: ITPMD (DI) | C47: Female | D47: PCPT | E47: ESTRADA | F47: MICAELLA ALLYSSA | G47: MONTES | J47: 15 Jonathan St., Brgy. 55, Tondo, Manila | K47: 09156803437 | P47: =CONCATENATE('detail Crame based'!D47," ",'detail Crame based'!E47," ",'detail Crame based'!F47) -> PCPT ESTRADA MICAELLA ALLYSSA | Q47: =IFERROR(VLOOKUP(P47,[1]Disposition!$AB$9:$AC$495,2,0),"NO RECORD YET") -> NO RECORD YET
A48: 38 | B48: ITPMD (IG) | C48: Female | D48: PCPT | E48: EVANGELISTA | F48: RHEA | G48: TADURAN | J48: 39 Col. Bonny Serrano Ave, Bagong Lipunan Ng Crame, Quezon City | K48: 09194833249 | P48: =CONCATENATE('detail Crame based'!D48," ",'detail Crame based'!E48," ",'detail Crame based'!F48) -> PCPT EVANGELISTA RHEA | Q48: =IFERROR(VLOOKUP(P48,[1]Disposition!$AB$9:$AC$495,2,0),"NO RECORD YET") -> NO RECORD YET
A49: 39 | B49: PHAS(DICTM) | C49: Female | D49: PCPT | E49: FERMANTEZ | F49: DINA | G49: SUNIEGA | J49: 445 Purok 5 , Rizal, Diffun, Quirino | K49: 09455295643 | P49: =CONCATENATE('detail Crame based'!D49," ",'detail Crame based'!E49," ",'detail Crame based'!F49) -> PCPT FERMANTEZ DINA | Q49: =IFERROR(VLOOKUP(P49,[1]Disposition!$AB$9:$AC$495,2,0),"NO RECORD YET") -> NO RECORD YET
A50: 40 | B50: ITPMD (DO) | C50: Male | D50: PCPT | E50: GOZE | F50: JONATHAN | G50: SISON | J50: 207 B Purok 1, Luzon Avenue, Culiat, Quezon City | K50: 09278265228 | P50: =CONCATENATE('detail Crame based'!D50," ",'detail Crame based'!E50," ",'detail Crame based'!F50) -> PCPT GOZE JONATHAN | Q50: =IFERROR(VLOOKUP(P50,[1]Disposition!$AB$9:$AC$495,2,0),"NO RECORD YET") -> NO RECORD YET
A51: 41 | B51: ITPMD (ES) | C51: Male | D51: PCPT | E51: GUEVARRA | F51: JAYSON | G51: GALANG | J51: 240 Zone-2, Mangga-Cacutud, Arayat, Pampanga | K51: 09175778327 | P51: =CONCATENATE('detail Crame based'!D51," ",'detail Crame based'!E51," ",'detail Crame based'!F51) -> PCPT GUEVARRA JAYSON | Q51: =IFERROR(VLOOKUP(P51,[1]Disposition!$AB$9:$AC$495,2,0),"NO RECORD YET") -> NO RECORD YET
A52: 42 | B52: PHAS(DICTM) | C52: Female | D52: PCPT | E52: JAVIER | F52: ROGINA | G52: TANGLAO | J52: 19-I 1St Avenue, Bagong Lipunan Ng Crame, Quezon City | K52: 09175352023 | P52: =CONCATENATE('detail Crame based'!D52," ",'detail Crame based'!E52," ",'detail Crame based'!F52) -> PCPT JAVIER ROGINA | Q52: =IFERROR(VLOOKUP(P52,[1]Disposition!$AB$9:$AC$495,2,0),"NO RECORD YET") -> NO RECORD YET
A53: 43 | B53: ITPMD (LS) | C53: Female | D53: PCPT | E53: LACSON | F53: VINEAH | G53: DIMO | J53: 50 Goldrock St., San Roque, Navotas City | K53: 09662061857 | P53: =CONCATENATE('detail Crame based'!D53," ",'detail Crame based'!E53," ",'detail Crame based'!F53) -> PCPT LACSON VINEAH | Q53: =IFERROR(VLOOKUP(P53,[1]Disposition!$AB$9:$AC$495,2,0),"NO RECORD YET") -> NO RECORD YET
A54: 44 | B54: ITPMD (HPG) | C54: Male | D54: PCPT | E54: MAGALONG | F54: DAREN | G54: NATIVIDAD | J54: 696 Brgy Kitakita, San Jose City, Nueva Ecija | K54: 09453621665 | P54: =CONCATENATE('detail Crame based'!D54," ",'detail Crame based'!E54," ",'detail Crame based'!F54) -> PCPT MAGALONG DAREN | Q54: =IFERROR(VLOOKUP(P54,[1]Disposition!$AB$9:$AC$495,2,0),"NO RECORD YET") -> NO RECORD YET
A55: 45 | B55: ITPMD (ITSD/DO) | C55: Male | D55: PCPT | E55: MALAKI | F55: ROFEL GEN | G55: TIMBAL | J55: Calle Nueva, Brgy. Labrador, Hinunangan, Southern Leyte | K55: 09951461125 | P55: =CONCATENATE('detail Crame based'!D55," ",'detail Crame based'!E55," ",'detail Crame based'!F55) -> PCPT MALAKI ROFEL GEN | Q55: =IFERROR(VLOOKUP(P55,[1]Disposition!$AB$9:$AC$495,2,0),"NO RECORD YET") -> NO RECORD YET
A56: 46 | B56: PHAS(DICTM-CSOC) | C56: Female | D56: PCPT | E56: MARTINEZ | F56: ANGELICA | G56: VIRAY | J56: 057, San Francisco, Macabebe, Pampanga | K56: 09674253706 | P56: =CONCATENATE('detail Crame based'!D56," ",'detail Crame based'!E56," ",'detail Crame based'!F56) -> PCPT MARTINEZ ANGELICA
A57: 47 | B57: ITPMD (OTDCO) | C57: Male | D57: PCPT | E57: MUÑOZ | F57: RANZ NIKKO | G57: BIEN | J57: Blk. 15 Lot 22, Viola St., Camella Sorrento, P.F. Espiritu Iv, Bacoor, Cavite | K57: 09959045925 | P57: =CONCATENATE('detail Crame based'!D57," ",'detail Crame based'!E57," ",'detail Crame based'!F57) -> PCPT MUÑOZ RANZ NIKKO | Q57: =IFERROR(VLOOKUP(P57,[1]Disposition!$AB$9:$AC$495,2,0),"NO RECORD YET") -> NO RECORD YET
A58: 48 | B58: ITPMD (PDEG) | C58: Male | D58: PCPT | E58: NAPOD | F58: GILBERT | G58: OLIQUINO | J58: Lot 39 Blk 9 Purok 3, Deano St., Central Bicutan, Taguig City | K58: 09399368006 | P58: =CONCATENATE('detail Crame based'!D58," ",'detail Crame based'!E58," ",'detail Crame based'!F58) -> PCPT NAPOD GILBERT | Q58: =IFERROR(VLOOKUP(P58,[1]Disposition!$AB$9:$AC$495,2,0),"NO RECORD YET") -> NO RECORD YET
A59: 49 | B59: ITPMD (CES) | C59: Male | D59: PCPT | E59: OBORDO | F59: JOEDHEL LLOYD | G59: EYAO | J59: Maninang, Sapi-An, Capiz | K59: 09468887288 | P59: =CONCATENATE('detail Crame based'!D59," ",'detail Crame based'!E59," ",'detail Crame based'!F59) -> PCPT OBORDO JOEDHEL LLOYD | Q59: =IFERROR(VLOOKUP(P59,[1]Disposition!$AB$9:$AC$495,2,0),"NO RECORD YET") -> NO RECORD YET
A60: 50 | B60: PHAS(DICTM-CSOC) | C60: Male | D60: PCPT | E60: PILASPILAS | F60: MARK JAYSON | G60: AMI | J60: Zone 2, Manambong Sur, Bayambang, Pangasinan | K60: 09958604167 | P60: =CONCATENATE('detail Crame based'!D60," ",'detail Crame based'!E60," ",'detail Crame based'!F60) -> PCPT PILASPILAS MARK JAYSON | Q60: =IFERROR(VLOOKUP(P60,[1]Disposition!$AB$9:$AC$495,2,0),"NO RECORD YET") -> NO RECORD YET
A61: 51 | B61: PHAS(DICTM) | C61: Male | D61: PCPT | E61: QUIDEZ | F61: BRYAN MARK | G61: SORIANO | J61: Purok 1, Baldios, Santa Ignacia, Tarlac | K61: 09531144507 | P61: =CONCATENATE('detail Crame based'!D61," ",'detail Crame based'!E61," ",'detail Crame based'!F61) -> PCPT QUIDEZ BRYAN MARK | Q61: =IFERROR(VLOOKUP(P61,[1]Disposition!$AB$9:$AC$495,2,0),"NO RECORD YET") -> NO RECORD YET
A62: 52 | B62: ITPMD (DI) | C62: Female | D62: PCPT | E62: REVALE | F62: EDELLENE | G62: BABAGAY | J62: P3 Brgy. Ems Barrio, Legaspi City, Albay | K62: 09994275134 | P62: =CONCATENATE('detail Crame based'!D62," ",'detail Crame based'!E62," ",'detail Crame based'!F62) -> PCPT REVALE EDELLENE
A63: 53 | B63: ITPMD (HRAO) | C63: Female | D63: PCPT | E63: SALAS | F63: EUNILAINE | G63: SALVADOR | J63: 131 Wwest Drive St., Narikina Heights, Marikina City | K63: 09175518988 | P63: =CONCATENATE(#REF!," ",#REF!," ",#REF!) -> #REF!
A64: 54 | B64: ITPMD (DI) | C64: Male | D64: PCPT | E64: SOBREVILLA | F64: RAYMUND CHRISTOPHER | G64: DECIPULO | J64: 15 F Int. Del Pilar St., Purok Bougambilla, Brgy. Bagja Mother, Cotabato City | K64: 09262417598 | P64: =CONCATENATE('detail Crame based'!D64," ",'detail Crame based'!E64," ",'detail Crame based'!F64) -> PCPT SOBREVILLA RAYMUND CHRISTOPHER | Q64: =IFERROR(VLOOKUP(P64,[1]Disposition!$AB$9:$AC$495,2,0),"NO RECORD YET") -> NO RECORD YET
A65: 55 | B65: ITPMD (OCPNP) | C65: Male | D65: PCPT | E65: SOSA | F65: GIBSON JOHN | G65: ARAOS | J65: #10 Singapore, Bastulde, Fil-Inves, Cainta, Rizal | K65: 09176229285 | P65: =CONCATENATE(E65," ",F65," ",G65) -> SOSA GIBSON JOHN ARAOS | Q65: =IFERROR(VLOOKUP(P65,[1]Disposition!$AB$9:$AC$495,2,0),"NO RECORD YET") -> #10 Singapore, Bastulde, Fil-Inves, Cainta, Rizal
A66: 56 | B66: ITPMD (DHRDD) | C66: Female | D66: PCPT | E66: SUAYA | F66: RAFFY JANE | G66: ALIDAO | J66: #25 C Purok 1, Lower Liwanag, Liwanag-Loakan, Baguio City, Benguet | K66: 09126980797 | P66: =CONCATENATE(E66," ",F66," ",G66) -> SUAYA RAFFY JANE ALIDAO | Q66: =IFERROR(VLOOKUP(P66,[1]Disposition!$AB$9:$AC$495,2,0),"NO RECORD YET") -> #25 C Purok 1, Lower Liwanag, Liwanag-Loakan, Baguio City, Benguet
A67: 57 | B67: ITPMD (PRBS) | C67: Male | D67: PCPT | E67: TAEZA | F67: ERIKSON | G67: TE | J67: 20 Alley 1, Project 6, Quezon City | K67: 09276964813 | P67: =CONCATENATE(E67," ",F67," ",G67) -> TAEZA ERIKSON TE | Q67: =IFERROR(VLOOKUP(P67,[1]Disposition!$AB$9:$AC$495,2,0),"NO RECORD YET") -> 20 Alley 1, Project 6, Quezon City
A68: 58 | B68: PHAS(DICTM)/PSMU | C68: Female | D68: PCPT | E68: TAJON | F68: VERONICA | G68: QUILIZA | J68: Mb 23 Unit 308 Bcda, Taguig City | K68: 09190955171 | P68: =CONCATENATE(E68," ",F68," ",G68) -> TAJON VERONICA QUILIZA | Q68: =IFERROR(VLOOKUP(P68,[1]Disposition!$AB$9:$AC$495,2,0),"NO RECORD YET") -> MB 23 Unit 308 BCDA, Taguig City
A69: 59 | B69: ITPMD (OCPNP) | C69: Male | D69: PCPT | E69: TAN | F69: ACHILES | G69: YABUT | J69: Blk 1 Lot 33, Maunlad Homes Subd., Caingin, Malolos, Bulacan | K69: 09985974254 | P69: =CONCATENATE(E69," ",F69," ",G69) -> TAN ACHILES YABUT | Q69: =IFERROR(VLOOKUP(P69,[1]Disposition!$AB$9:$AC$495,2,0),"NO RECORD YET") -> Blk 1 Lot 33, Maunlad Homes Subd., Caingin, Malolos, Bulacan
A70: 60 | B70: ITPMD (CIDG/AKG/DI) | C70: Male | D70: PCPT | E70: VENTURA | F70: JOSEPH | G70: SAMONTE | J70: 04 Angoluan, Atulayan Norte, Tuguegarao City, Cagayan Valley | K70: 09776767160 | P70: =CONCATENATE(E70," ",F70," ",G70) -> VENTURA JOSEPH SAMONTE
A71: 61 | B71: ITPMD(CHS) | C71: Male | D71: PCPT | E71: VILLAGONZALO | F71: RYAN | G71: VILLARIN | J71: Lot 1042-8-4 Lower Panabang, Apas, Cebu City | K71: 09222948723 | P71: =CONCATENATE(E71," ",F71," ",G71) -> VILLAGONZALO RYAN VILLARIN | Q71: =IFERROR(VLOOKUP(P71,[1]Disposition!$AB$9:$AC$495,2,0),"NO RECORD YET") -> NO RECORD YET
A72: 62 | B72: ITPMD (DIDM) | C72: Male | D72: PLT | E72: ABO | F72: MARK JESSIE | G72: MELITANTE | J72: Unit 909, Amaia Skies Cuibao, P. Tuazon Ave., Socorro, Quezon City | K72: 09566570420 | P72: =CONCATENATE(E72," ",F72," ",G72) -> ABO MARK JESSIE MELITANTE | Q72: =IFERROR(VLOOKUP(P72,[1]Disposition!$AB$9:$AC$495,2,0),"NO RECORD YET") -> Unit 909, Amaia Skies Cuibao, P. Tuazon Ave., Socorro, Quezon City
A73: 63 | B73: ITPMD (IMEG) | C73: Male | D73: PLT | E73: AREVALO | F73: RALPH LYNDON | G73: RESUELLO | J73: 43 Luzon Street Zone 5, Central Signal Village (Signal Village), Taguig City, Metro Manila, Ncr - National Capital Region | P73: =CONCATENATE(E73," ",F73," ",G73) -> AREVALO RALPH LYNDON RESUELLO | Q73: =IFERROR(VLOOKUP(P73,[1]Disposition!$AB$9:$AC$495,2,0),"NO RECORD YET") -> NO RECORD YET
A74: 64 | B74: PHAS(DICTM-CSOC) | C74: Male | D74: PLT | E74: BILLOTE | F74: KYLE BENEDICT | G74: SORIANO | J74: Blk 25 Lot 31 Villa Palao, Banlic, Calamba City, Laguna | K74: 09451855015 | P74: =CONCATENATE(E74," ",F74," ",G74) -> BILLOTE KYLE BENEDICT SORIANO | Q74: =IFERROR(VLOOKUP(P74,[1]Disposition!$AB$9:$AC$495,2,0),"NO RECORD YET") -> Blk 25 Lot 31 Villa Palao, Banlic, Calamba City, Laguna
A75: 65 | B75: ITPMD (HSS) | C75: Male | D75: PLT | E75: DELA CRUZ | F75: ASHTER | G75: TIBURCIO | J75: 227 Sta, Cruz, Zaragisa, Nueva Ecija | K75: 09458823777 | P75: =CONCATENATE(E75," ",F75," ",G75) -> DELA CRUZ ASHTER TIBURCIO | Q75: =IFERROR(VLOOKUP(P75,[1]Disposition!$AB$9:$AC$495,2,0),"NO RECORD YET") -> 227 Sta, Cruz, Zaragisa, Nueva Ecija
A76: 66 | B76: ITPMD (PCADG) | C76: Male | D76: PLT | E76: DULNUAN | F76: RAMON | G76: CUYANGCO | H76: JR | J76: 60, Poblacion West, Lamut, Ifugao, Car - Cordillera Administrative Region | P76: =CONCATENATE(E76," ",F76," ",G76) -> DULNUAN RAMON CUYANGCO | Q76: =IFERROR(VLOOKUP(P76,[1]Disposition!$AB$9:$AC$495,2,0),"NO RECORD YET") -> NO RECORD YET
A77: 67 | B77: ITPMD (IAS) | C77: Male | D77: PLT | E77: ECHANO | F77: KERWIN | G77: RUFON | J77: Lot 37-38 Blk.5 Catanauan St., Vanessa Homes, Bucal, Calamba, Laguna | K77: 09760708892
A78: 68 | B78: ITPMD (FG/DICTM)) | C78: Female | D78: PLT | E78: ESPEDIDO | F78: IBON GAY | G78: DACUMOS | J78: #60 Purok Magsaysay, Lawig, Lamut, Ifugao, Car - Cordillera Administrative Region | P78: =CONCATENATE(E78," ",F78," ",G78) -> ESPEDIDO IBON GAY DACUMOS
A79: 69 | B79: ITPMD (DIDM) | C79: Male | D79: PLT | E79: GALAMGAM | F79: RAMON | G79: DIAZ | H79: JR | P79: =CONCATENATE(E79," ",F79," ",G79) -> GALAMGAM RAMON DIAZ | Q79: =IFERROR(VLOOKUP(P79,[1]Disposition!$AB$9:$AC$495,2,0),"NO RECORD YET") -> 38 Agno, Tayug, Pangasinan
A80: 70 | B80: ITPMD (CSG) | C80: Female | D80: PLT | E80: GUSTILO | F80: THOBORNE THER | G80: SANTOS | J80: Blk 5 Lot 4 Phase-M, Francisco Homes- Guijo, Sjdm, Bulacan | K80: 09451854958 | P80: =CONCATENATE(E80," ",F80," ",G80) -> GUSTILO THOBORNE THER SANTOS | Q80: =IFERROR(VLOOKUP(P80,[1]Disposition!$AB$9:$AC$495,2,0),"NO RECORD YET") -> Blk 5 Lot 4 Phase-M, Francisco Homes- Guijo, SJDM, Bulacan
A81: 71 | B81: ITPMD (OTCDS) | C81: Male | D81: PLT | E81: ILACAD | F81: DIONELL | G81: TUGADE | P81: =CONCATENATE(E81," ",F81," ",G81) -> ILACAD DIONELL TUGADE
A82: 72 | B82: ITPMD (LSS) | C82: Male | D82: PLT | E82: ORTIZ | F82: JULIUS | G82: SEMITARA | J82: B62 L34 Ph1 Sycamore St. Grand Cedar Homes, Bignay, City Of Valenzuela, Metro Manila, Ncr - National Capital Region | P82: =CONCATENATE(E82," ",F82," ",G82) -> ORTIZ JULIUS SEMITARA | Q82: =IFERROR(VLOOKUP(P82,[1]Disposition!$AB$9:$AC$495,2,0),"NO RECORD YET") -> NO RECORD YET
A83: 73 | B83: DMD/ITPMD (PCC-DO) | C83: Male | D83: PLT | E83: RETAZO | F83: RIZALDY | G83: ISIDORO | P83: =CONCATENATE(E83," ",F83," ",G83) -> RETAZO RIZALDY ISIDORO | Q83: =IFERROR(VLOOKUP(P83,[1]Disposition!$AB$9:$AC$495,2,0),"NO RECORD YET") -> Calamagui 2nd, Ilagan, Isabela
A84: 74 | B84: PHAS(DICTM) | C84: Male | D84: PLT | E84: SIA | F84: ENARD | G84: ANDAYA | J84: 10-A Governor Pascual Avenue, Potrero, Malabon City | K84: 09362510010 | P84: =CONCATENATE(E84," ",F84," ",G84) -> SIA ENARD ANDAYA | Q84: =IFERROR(VLOOKUP(P84,[1]Disposition!$AB$9:$AC$495,2,0),"NO RECORD YET") -> 10-A Governor Pascual Avenue, Potrero, Malabon City
A85: 75 | B85: PRS, PTD | C85: Male | D85: PLT | E85: VALLE | F85: MARK LAWRENCE | G85: ABENOJAR | K85: 09391871290 | P85: =CONCATENATE(E85," ",F85," ",G85) -> VALLE MARK LAWRENCE ABENOJAR
A86: POLICE NON-COMMISSIONED OFFICERS
A87: 1 | B87: ITPMD (OTDCO) | C87: Male | D87: PCMS | E87: MARAÑON | F87: CHRIS JOHN | G87: CATALOGO | J87: B18 L1 P-J Francisco Homes, Sjdm, Bulacan | K87: 09217221646 | P87: =CONCATENATE(E87," ",F87," ",G87) -> MARAÑON CHRIS JOHN CATALOGO | Q87: =IFERROR(VLOOKUP(P87,[1]Disposition!$AB$9:$AC$495,2,0),"NO RECORD YET") -> B18 L1 P-J Francisco Homes, SJDM, Bulacan
A88: 2 | B88: PHAS(DICTM) | C88: Male | D88: PCMS | E88: SABIO | F88: SHERWIN | G88: INTONG | J88: 173-P 22Nd Avenue , East Rembo, Makati City | K88: 09167479918 | P88: =CONCATENATE(E88," ",F88," ",G88) -> SABIO SHERWIN INTONG | Q88: =IFERROR(VLOOKUP(P88,[1]Disposition!$AB$9:$AC$495,2,0),"NO RECORD YET") -> 173-P 22nd Avenue , East Rembo, Makati City
A89: 3 | B89: PHAS(DICTM) | C89: Male | D89: PSMS | E89: DIÑA | F89: JEREMY | G89: DOMALAON | J89: Unit 302, Mb9, Bcda, Diego Silang Village, Ususan, Taguig City | K89: 09176414479 | P89: =CONCATENATE(#REF!," ",#REF!," ",#REF!) -> #REF! | Q89: =IFERROR(VLOOKUP(P89,[1]Disposition!$AB$9:$AC$495,2,0),"NO RECORD YET") -> NO RECORD YET
A90: 4 | B90: PHAS(DICTM) | C90: Male | D90: PSMS | E90: ECHEGOYEN | F90: RYAN | G90: MOJICA | J90: 1061-A Molina Ext. San Antonio, Cavite City | K90: 09168490658 | P90: =CONCATENATE(#REF!," ",#REF!," ",#REF!) -> #REF! | Q90: =IFERROR(VLOOKUP(P90,[1]Disposition!$AB$9:$AC$495,2,0),"NO RECORD YET") -> NO RECORD YET
A91: 5 | B91: ITPMD (PCC-DO) | C91: Male | D91: PSMS | E91: FRIAS | F91: KIM ANTHONY | G91: NICOLAS | J91: 1234 Katipunan St., Calumpang, Binangonan, Rizal | K91: 09154956592 | P91: =CONCATENATE(E43," ",F43," ",G43) -> BUHAIN DOROTHY VILLALOBOS | Q91: =IFERROR(VLOOKUP(P91,[1]Disposition!$AB$9:$AC$495,2,0),"NO RECORD YET") -> 301 Masagana Subd., Gumamela St., San Francisco, Bulacan
A92: 6 | B92: ITPMD (DPCR) | C92: Male | D92: PSMS | E92: SIBAYAN | F92: REYGIE | G92: PIAGAN | J92: Giron St., Brgy No. 2, Santa Joaquina, Laoag City, Ilocos Norte | K92: 09082302544 | P92: =CONCATENATE(E92," ",F92," ",G92) -> SIBAYAN REYGIE PIAGAN
A93: 7 | B93: PHAS(DICTM) | C93: Male | D93: PSMS | E93: SIGGAYO | F93: WILLARD | G93: MALABAD | J93: 11 Road 2 Sitio Kumunoy, Bagong Silangan, Quezon City | K93: 09355344158 | P93: =CONCATENATE(E93," ",F93," ",G93) -> SIGGAYO WILLARD MALABAD | Q93: =IFERROR(VLOOKUP(P93,[1]Disposition!$AB$9:$AC$495,2,0),"NO RECORD YET") -> 11 Road 2 Sitio Kumunoy, Bagong Silangan, Quezon City
A94: 8 | B94: PHAS(DICTM) | C94: Female | D94: PSMS | E94: SORIANO | F94: NEPTHALIE | G94: ADONA | J94: #233 7Th St., Ghq Village, Zone 1-C, Taguig City | K94: 09174857735 | P94: =CONCATENATE(#REF!," ",#REF!," ",#REF!) -> #REF!
A95: 9 | B95: ITPMD (DIDM) | C95: Male | D95: PSMS | E95: TACTAY | F95: HENRY | G95: GOLINO | J95: 41 Quimmarayan, Sto. Domingo, Ilocos Sur | K95: 09950271798 | P95: =CONCATENATE(#REF!," ",#REF!," ",#REF!) -> #REF! | Q95: =IFERROR(VLOOKUP(P95,[1]Disposition!$AB$9:$AC$495,2,0),"NO RECORD YET") -> NO RECORD YET
A96: 10 | B96: ITPMD (FS) | C96: Male | D96: PMSg | E96: BALINGIT | F96: JOSE JEFFERSON | G96: LACSAM | H96: II | J96: B153 L9 Amorseco St., Rizal, Makati City | K96: 09175183464 | P96: =CONCATENATE(#REF!," ",#REF!," ",#REF!) -> #REF! | Q96: =IFERROR(VLOOKUP(P96,[1]Disposition!$AB$9:$AC$495,2,0),"NO RECORD YET") -> NO RECORD YET
A97: 11 | B97: ITPMD (OTCDS) | C97: Male | D97: PMSg | E97: DULIN | F97: JOEY | G97: BINARAO | J97: 155 19Th Avenue, East Pembo, Makati City | K97: 09175073304 | P97: =CONCATENATE(E97," ",F97," ",G97) -> DULIN JOEY BINARAO
A98: 12 | B98: ITPMD (DO) | C98: Female | D98: PMSg | E98: INFANTE | F98: BEVERLY | G98: PASAMBA | J98: 333 Verdar St., Sampaloc, Manila | K98: 09395171645 | P98: =CONCATENATE(E98," ",F98," ",G98) -> INFANTE BEVERLY PASAMBA | Q98: =IFERROR(VLOOKUP(P98,[1]Disposition!$AB$9:$AC$495,2,0),"NO RECORD YET") -> 333 Verdar St., Sampaloc, Manila
A99: 13 | B99: PHAS(DICTM) | C99: Male | D99: PSSg | E99: TABUYO | F99: GILBERT | G99: POLA | J99: #21 Panay Norte, Magsingal, Ilocos Sur | K99: 09959387916 | P99: =CONCATENATE(#REF!," ",#REF!," ",#REF!) -> #REF! | Q99: =IFERROR(VLOOKUP(P99,[1]Disposition!$AB$9:$AC$495,2,0),"NO RECORD YET") -> NO RECORD YET
A100: 14 | B100: ITPMD (SOSIA-OSS) | C100: Male | D100: PSSg | E100: ZAMORA | F100: MELVIN | G100: PANGANIBAN | J100: Light Residences, Mandaluyong City | K100: 09455027450
A101: 15 | B101: PHAS(DICTM) | C101: Male | D101: PCpl | E101: ARCANGEL | F101: OLIVER | G101: GARCIA | J101: #8 Binalatongan, San Juan, San Carlos City, Pangasinan | K101: 09156641566 | P101: =CONCATENATE(E101," ",F101," ",G101) -> ARCANGEL OLIVER GARCIA | Q101: =IFERROR(VLOOKUP(P101,[1]Disposition!$AB$9:$AC$495,2,0),"NO RECORD YET") -> #8 Binalatongan, San Juan, San Carlos City, Pangasinan
A102: 16 | B102: ITPMD (CSG-SOSIA) | C102: Male | D102: PCpl | E102: BUENO | F102: CHIER BRYAN | G102: MARCOS | J102: Block 27, Kabisig St.,, San Andres (Pob.), Cainta, Rizal, Region Iv-A (Calabarzon) | P102: =CONCATENATE(E102," ",F102," ",G102) -> BUENO CHIER BRYAN MARCOS | Q102: =IFERROR(VLOOKUP(P102,[1]Disposition!$AB$9:$AC$495,2,0),"NO RECORD YET") -> 0
...

Sheet itmsHQ
A1: Republic of the Philippines
A2: PHILIPPINE NATIONAL POLICE
A3: INFORMATION TECHNOLOGY MANAGEMENT SERVICE
A4: Camp Bgen Rafael T Crame, Quezon City
A6: Roster of Personnel (ITMSHQ Only)
A7: (As of January 22, 2026)
A9: NO. | B9: OFFICE/DIVISION | C9: GENDER | D9: RANK | E9: LASTNAME | F9: FIRSTNAME | G9: MIDDLE NAME | H9: QUAL | I9: SIGNATURE
A10: POLICE COMMISSIONED OFFICERS
A11: 1 | B11: PTD | C11: Female | D11: PCOL | E11: ALI | F11: SHIRLEY MAE | G11: SALVADOR
A12: 2 | B12: ITPMD | C12: Male | D12: PCOL | E12: BORRES | F12: RUBEN | G12: BROSAS
A13: 3 | B13: ARMD | C13: Male | D13: PCOL | E13: DELA PEÑA | F13: VICTORIO | G13: MENDIOLA | H13: JR
A14: 4 | B14: DMD | C14: Male | D14: PCOL | E14: JOAQUIN | F14: ROMEO | G14: LISING
A15: 5 | B15: OD | C15: Male | D15: PCOL | E15: PALGUE | F15: ROMY | G15: INWAY
A16: 6 | B16: OCS | C16: Male | D16: PCOL | E16: PATIÑO | F16: RANDI | G16: MANZANO
A17: 7 | B17: ODDA/DI | C17: Male | D17: PCOL | E17: TANGO | F17: FROILAN GENN | G17: GELACIO | H17: II
A18: 8 | B18: BFS/LS/IHSS/PRO12 | C18: Male | D18: PLTCOL | E18: AQUINO | F18: JOHANNES GOLD | G18: LUCERO
A19: 9 | B19: BFS, ARMD | C19: Male | D19: PLTCOL | E19: BALMACEDA | F19: ROMMEL | G19: BANGUILAN
A20: 10 | B20: ITPMD | C20: Female | D20: PLTCOL | E20: FABRO | F20: JHOANA GRACIA | G20: MANLAPAZ
A21: 11 | B21: SMD/RICTMD PRO 9 | C21: Male | D21: PLTCOL | E21: RIMANDO | F21: JUVENAL | G21: AFOS
A22: 12 | B22: ISSD | C22: Male | D22: PLTCOL | E22: SANTOS | F22: NHARCISO JHOEL | G22: SULIT
A23: 13 | B23: ARMD | C23: Female | D23: PLTCOL | E23: SUCGANG | F23: ROSE ANNE | G23: ROXAS
A24: 14 | B24: DMD/PRO13 | C24: Male | D24: PLTCOL | E24: TARUN | F24: CHRISTIAN | G24: BELTRAN
A25: 15 | B25: PHAS (RICTMD PRO13) | C25: Male | D25: PLTCOL | E25: VIRTUDAZO | F25: MICHAEL | G25: TAREPE
A26: 16 | B26: TSS, PTD | C26: Female | D26: PCPT | E26: AGUSTIN | F26: RIZELLE | G26: INALDO
A27: 17 | B27: ITPMD (PIO) | C27: Male | D27: PCPT | E27: ALIMAMBO | F27: JICK | G27: BONUAN
A28: 18 | B28: SMD | C28: Male | D28: PCPT | E28: ANISCO | F28: ARCHIE | G28: STO.DOMINGO
A29: 19 | B29: IT Help Desk SAS, ITSD | C29: Male | D29: PCPT | E29: CABILES | F29: FIDEL | G29: VALEROS
... A31: 21 | B31: OCS | C31: Male | D31: PCPT | E31: KARIM | F31: BENSAR ALI | G31: ABDULGANI
A32: 22 | B32: PHAS, ARMD | C32: Male | D32: PCPT | E32: LOPEZ | F32: JOEL | G32: MORATALLA | H32: JR
A33: 23 | B33: ISSD | C33: Male | D33: PCPT | E33: ONIL | F33: RELLON | G33: SUAYAN
A34: 24 | B34: SMD | C34: Male | D34: PCPT | E34: PAPIÑA | F34: PATRICK LYNDON | G34: PARCAREY
A35: 25 | B35: PS, ARMD | C35: Male | D35: PCPT | E35: SYTICO | F35: JAMES | G35: ALCERA
A36: 26 | B36: SMD | C36: Male | D36: PCPT | E36: ULPINDO | F36: KRISANTO | G36: TAPIA
A37: 27 | B37: TS, PTD | C37: Male | D37: PLT | E37: ARIAS | F37: AUDEN | G37: GOZUM
A38: 28 | B38: ITSD | C38: Male | D38: PLT | E38: BANTIYAN | F38: JEFTER | G38: PAKID
A39: 29 | B39: ISSD | C39: Male | D39: PLT | E39: CORPUZ | F39: ALEX ACE | G39: CABAUATAN
A40: 30 | B40: DWBIS, DMD | C40: Male | D40: PLT | E40: DAVID | F40: EDUARDO | G40: BALATIAN | H40: JR
A41: 31 | B41: ITSD | C41: Male | D41: PLT | E41: GUIFAYA | F41: GILBERT | G41: ULIDAN | H41: JR
A42: 32 | B42: ICRMS, ARMD | C42: Female | D42: PLT | E42: PAMITTAN | F42: JOCELYN | G42: LATTAO
A43: 33 | B43: SMD | C43: Male | D43: PLT | E43: PARRE | F43: WINSTON | G43: SAFLOR
A44: 34 | B44: IHSS/LS, ARMD | C44: Female | D44: PLT | E44: RAMOS | F44: CHRISHELLE | G44: SAGUN
A45: 35 | B45: PRS, PTD | C45: Male | D45: PLT | E45: VALLE | F45: MARK LAWRENCE | G45: ABENOJAR
A46: POLICE NON-COMMISSIONED OFFICERS
A47: 1 | B47: ARMD | C47: Male | D47: PCMS | E47: MELCHOR | F47: JUNVI | G47: PASCUAL | J47: PRS, PTD | K47: Male | L47: PMSg | M47: OLOJAN | N47: CHRISTOPHER BRIAN | O47: ASTUDILLO
A48: 2 | B48: LS, ARMD | C48: Male | D48: PCMS | E48: MINA | F48: EDGAR | G48: LABIAO | J48: ITPMD (PRO5) | K48: Male | L48: PMSg | M48: ORANTE | N48: JOHN MICHEAL | O48: CEPRIA
A49: 3 | B49: PTD | C49: Male | D49: PSMS | E49: GOYENA | F49: MARLON | G49: ARGENIO | J49: EMS, ITPMD | K49: Male | L49: PMSg | M49: PEÑAVERDE | N49: PHILIP JAMES | O49: RODRIGUEZ
A50: 4 | B50: BFS, ARMD | C50: Male | D50: PSMS | E50: PALISOC | F50: PREMIER HAROLD | G50: TABUÑAR | J50: ODDA | K50: Male | L50: PMSg | M50: RESPICIO | N50: VIC BASKAR | O50: MADDARA
A51: 5 | B51: ITSD | C51: Male | D51: PSMS | E51: PLAZA | F51: ERVIN | G51: TELAPER | J51: ITPMD (PRO1) | K51: Male | L51: PMSg | M51: RIVERA | N51: RONALD | O51: BATIS
A52: 6 | B52: SLO/OCI/ARMD | C52: Male | D52: PMSg | E52: CANJA | F52: ROBERTO | G52: GINETA | H52: JR | J52: ITPMD (PRO8) | K52: Male | L52: PMSg | M52: SEPTIMO | N52: LEO | O52: CACA | P52: JR
A53: 7 | B53: PRS, PTD | C53: Male | D53: PMSg | E53: OLOJAN | F53: CHRISTOPHER BRIAN | G53: ASTUDILLO | J53: ITPMD (PRO3) | K53: Male | L53: PMSg | M53: VELASCO | N53: ACE | O53: PAGADUAN
A54: 8 | B54: EMS, ITPMD | C54: Male | D54: PMSg | E54: PEÑAVERDE | F54: PHILIP JAMES | G54: RODRIGUEZ | J54: LS, ARMD | K54: Male | L54: PSSg | M54: AGUILAR | N54: JAMES BENEDICT | O54: GALVEZ
A55: 9 | B55: ODDA | C55: Male | D55: PMSg | E55: RESPICIO | F55: VIC BASKAR | G55: MADDARA | J55: SAS, ITSD | K55: Male | L55: PSSg | M55: CALAPANO | N55: MELVIN | O55: AVILA
A56: 10 | B56: LS, ARMD | C56: Male | D56: PSSg | E56: AGUILAR | F56: JAMES BENEDICT | G56: GALVEZ | J56: ASCS, SMD | K56: Male | L56: PSSg | M56: CHAN | N56: HAROLD JAY | O56: AMAZONA
A57: 11 | B57: SAS, ITSD | C57: Male | D57: PSSg | E57: CALAPANO | F57: MELVIN | G57: AVILA | J57: ITPMD (PRO13) | K57: Male | L57: PSSg | M57: COMON | N57: RAQUIL | O57: MANATAD
A58: 12 | B58: ASCS, SMD | C58: Male | D58: PSSg | E58: CHAN | F58: HAROLD JAY | G58: AMAZONA | J58: ITPMD (MPD) | K58: Male | L58: PSSg | M58: ELECCION | N58: CHRISTOFFERSON | O58: CURAMING
A59: 13 | B59: IHSS, ARMD | C59: Male | D59: PSSg | E59: FRONDA | F59: JIMMSON | G59: CILOCILO | J59: IHSS, ARMD | K59: Male | L59: PSSg | M59: FRONDA | N59: JIMMSON | O59: CILOCILO
A60: 14 | B60: ARMD | D60: PSSg | E60: MANUEL | F60: MARK | G60: ALMONTE | J60: ARMD | L60: PSSg | M60: MANUEL | N60: MARK | O60: ALMONTE
A61: 15 | B61: OCS | C61: Male | D61: PCpl | E61: AGGARAO | F61: ALBERTO | G61: CALLANGAN | J61: ITPMD (NCRPO) | K61: Male | L61: PSSg | M61: RANCE | N61: LEONARDO | O61: ESPINOSA
A62: 16 | B62: OD | C62: Male | D62: PCpl | E62: CERIL | F62: PAUL KELVIN | G62: LAROZA | J62: ARMD | K62: Female | L62: PCpl | M62: MERQUE | N62: JUDE ANN | O62: GRIEGO
A63: 17 | B63: ARMD | C63: Female | D63: PCpl | E63: CRUZAT | F63: MARIEL | G63: ARELLANO | J63: ITPMD (PRO3) | K63: Female | L63: Pat | M63: JARANILLA | N63: MA ANNIE | O63: CAABAS
A64: 18 | B64: SLO/OCI | C64: Female | D64: PCpl | E64: CUASAY | F64: ZAYRA JANE | G64: CEDENO | J64: ISSD | L64: Pat | M64: JUANATA | N64: MICAELA | O64: SIAO
A65: 19 | B65: ARMD | C65: Female | D65: PCpl | E65: MERQUE | F65: JUDE ANN | G65: GRIEGO | J65: ITPMD (PRO1) | K65: Female | L65: Pat | M65: LAMES | N65: MAYJEAN | O65: GAGET
A66: 20 | B66: OCS | C66: Female | D66: PCpl | E66: SANG-AN | F66: CATHERINE | G66: VALDESTAMON | J66: PHAS(DICTM-CSOC) | K66: Male | L66: Pat | M66: LLANEZA | N66: MARC | O66: LEE
A67: 21 | B67: LS, ARMD | C67: Male | D67: PCpl | E67: TAMANIO | F67: ANTHONY ELKING | G67: SALVADOR | J67: ITPMD (PRO6) | K67: Male | L67: Pat | M67: LOCOP | N67: HERRAEL KARL | O67: GIDOR
A68: 22 | B68: OISS, SMD | C68: Male | D68: PCpl | E68: TOLENTINO | F68: NATHANIEL | G68: MELEGRITO | J68: ITPMD (PRO11) | K68: Male | L68: Pat | M68: LOPEZ | N68: JAYVEE | O68: POCDOL
A69: 23 | B69: PS, ARMD | C69: Male | D69: Pat | E69: APALLA | F69: RUEL | G69: AMPIS | J69: ITPMD (PRO10) | K69: Female | L69: Pat | M69: MACAPILIT | N69: MARYLAND | O69: SEPLON
A70: 24 | B70: DMD | C70: Male | D70: Pat | E70: AYUPAN | F70: LAURENCE | G70: NOBLEZA | J70: PHAS (PNPA) | K70: Male | L70: Pat | M70: MACAPUNO | N70: JAMES RYAN | O70: DE SAGUN
A71: 25 | B71: LS, ARMD | C71: Male | D71: Pat | E71: BARQUIN | F71: CHRISTIAN PAUL | G71: SAN VICENTE | J71: ITPMD (DO) | K71: Male | L71: Pat | M71: MACAWILE | N71: ROMY | O71: INCISO | P71: JR
A72: 26 | B72: OD | C72: Male | D72: Pat | E72: BEJARIN | F72: GERALD | G72: DADIRO | J72: PHAS, ARMD | K72: Male | L72: Pat | M72: MAMENTA | N72: CRISTOPHER | O72: ALLAS
A73: 27 | B73: ISSD | C73: Male | D73: Pat | E73: BILLOSO | F73: AL ANTHONY | G73: CONSOLACION | J73: ITPMIS, ITPMD | K73: Male | L73: Pat | M73: MANAOG | N73: RODNIE | O73: CASTILLO
A74: 28 | B74: AISS, SMD | C74: Male | D74: Pat | E74: BRONZAL | F74: BRUCE KELLY | G74: LOZANO | J74: ITPMD (NCRPO) | K74: Male | L74: Pat | M74: MANCERA | N74: JOSHUA | O74: ARMENTA
A75: 29 | B75: ITPMIS, ITPMD | C75: Female | D75: Pat | E75: CELARIO | F75: RUBY ROSE | G75: BUEZA | J75: ITPMD (DI) | K75: Male | L75: Pat | M75: MANGOBA | N75: ROMMEL | O75: JAZMIN
A76: 30 | B76: ITSD | D76: Pat | E76: COPRADA | F76: ROMUALDO JULES | G76: OSMOND | J76: ITSD | K76: Male | L76: Pat | M76: PARANE | N76: DETANIL | O76: COROCOTO
A77: 31 | B77: PS, ARMD | C77: Male | D77: Pat | E77: DICO | F77: JOEMAR | G77: RODRIGUEZ | J77: ITPMD (DPRM) | K77: Male | L77: Pat | M77: MANIQUIZ | N77: JEREMY | O77: BINUYA
A78: 32 | B78: NMS, ITSD | C78: Male | D78: Pat | E78: DIONEDA | F78: KARL JOHN | G78: QUIRANTE | J78: ITPMD (DI)ODDA | K78: Female | L78: Pat | M78: MARASIGAN | N78: MIA ANGELA | O78: CORNEJO
A79: 33 | B79: ITSD | D79: Pat | E79: ESTACIO | F79: NEIL BRYAN | G79: ALARIN | J79: ITPMD (PRO CAR) | K79: Male | L79: Pat | M79: PATERNO | N79: JEFFREY | O79: PAUS
A80: 34 | B80: IT Help Desk, ITSD | C80: Male | D80: Pat | E80: FERNANDEZ | F80: ERIC | G80: MOLINA | J80: PHAS(DICTM) | K80: Female | L80: Pat | M80: MELGAR | N80: CATHERINE | O80: MANUEL
A81: 35 | B81: PS, ARMD | C81: Male | D81: Pat | E81: FRANK | F81: JEFF BRIAN | G81: RUIZ | J81: ITPMD (STF-DPAGS-SL) | K81: Male | L81: Pat | M81: MENDOZA | N81: FLOMARIE JOHN | O81: GAVERIA
A82: 36 | B82: AISS, SMD | C82: Male | D82: Pat | E82: GALVEZ | F82: MARK RHOMMEL | G82: MDRIAGA | J82: BFS, ARMD | K82: Male | L82: Pat | M82: MOLINA | N82: DOMINICK EZRA | O82: GACES
A83: 37 | B83: LS, ARMD | C83: Male | D83: Pat | E83: GUINAOWA | F83: JAYMAR | G83: GUDAREN | J83: PHAS(DICTM-CSOC) | K83: Male | L83: Pat | M83: MONTIGO | N83: MARKIN | O83: GUTIERREZ
A84: 38 | B84: PRS, PTD | C84: Female | D84: Pat | E84: GUNNACAO | F84: LOVELYN KATE | G84: LEGMAN | J84: OD | K84: Male | L84: Pat | M84: MORI | N84: LYNDON | O84: ACOSTA
A85: 39 | B85: ISSD | D85: Pat | E85: JUANATA | F85: MICAELA | G85: SIAO | J85: EMS, ITPMD | K85: Male | L85: Pat | M85: MORTEL | N85: ALWYN | O85: ALBUFERA
A86: 40 | B86: ITPMIS, ITPMD | C86: Male | D86: Pat | E86: MANAOG | F86: RODNIE | G86: CASTILLO
A87: 41 | B87: BFS, ARMD | C87: Male | D87: Pat | E87: MOLINA | F87: DOMINICK EZRA | G87: GACES | J87: QAS, SMD | K87: Male | L87: Pat | M87: MOSLARES | N87: CHARLES BRYAN | O87: MOLINA | P87: JR
A88: 42 | B88: OD | C88: Male | D88: Pat | E88: MORI | F88: LYNDON | G88: ACOSTA | J88: ITPMD (PRO4B) | K88: Female | L88: Pat | M88: NALING | N88: ANN JENETH | O88: SALAZAR
A89: 43 | B89: EMS, ITPMD | C89: Male | D89: Pat | E89: MORTEL | F89: ALWYN | G89: ALBUFERA | J89: ITPMD (PRO9) | K89: Male | L89: Pat | M89: NERI | N89: FREDIMAR | O89: SIMON
A90: 44 | B90: QAS, SMD | C90: Male | D90: Pat | E90: MOSLARES | F90: CHARLES BRYAN | G90: MOLINA | J90: ITPMD (Palawan PPO) | K90: Male | L90: Pat | M90: NIEZ | N90: JORDAN | O90: ESTRELLA | P90: JR
A91: 45 | B91: ISSD | C91: Male | D91: Pat | E91: PANSOY | F91: LEX LEVIN | G91: JUEGOS | J91: ITPMD (DPL) | K91: Male | L91: Pat | M91: OBOG | N91: JOHN MARLO | O91: MAGRAMO
A92: 46 | B92: ODDIT | C92: Female | D92: Pat | E92: PAPA | F92: MARIZ NICOLE | G92: ENGALAN | J92: ITPMD (DPCR) | K92: Male | L92: Pat | M92: ORLANDA | N92: BERNABE | O92: MACADANGDANG
A93: 47 | B93: OISS, SMD | C93: Male | D93: Pat | E93: PAQUIZ | F93: JOHN ANTHONY | G93: BATO | J93: ITPMD (PRO8) | K93: Female | L93: Pat | M93: PACIENCIA | N93: METALLICA LYH | O93: OCTAVIANO
A94: 48 | B94: ITSD | C94: Male | D94: Pat | E94: PARANE | F94: DETANIL | G94: COROCOTO | J94: ITPMD (PRO10) | K94: Male | L94: Pat | M94: PADAYOGDOG | N94: FRANCISCO | O94: EMPINADO
A95: 49 | B95: PIO | C95: Male | D95: Pat | E95: PEÑON | F95: JAYSON | G95: CABRAL | J95: ITPMD (PCC-DO) | K95: Male | L95: Pat | M95: PADILLA | N95: KEM EDNYLL | O95: MACARINE
A96: 50 | B96: NMS, ITSD | C96: Male | D96: Pat | E96: REYES | F96: AVELINO | G96: MORO | J96: ITPMD (DO) | K96: Male | L96: Pat | M96: PAISTE | N96: MARL JAYSON | O96: JOVES | P96: JR
A97: 51 | B97: ITSD | C97: Male | D97: Pat | E97: ROVIRA | F97: CRISMUNDO | G97: PADULLO | J97: ISSD | K97: Male | L97: Pat | M97: PANSOY | N97: LEX LEVIN | O97: JUEGOS
A98: 52 | B98: PS, ARMD | C98: Male | D98: Pat | E98: TAGUINOD | F98: DANNY BOY | G98: ONG | J98: ODDIT | K98: Female | L98: Pat | M98: PAPA | N98: MARIZ NICOLE | O98: ENGALAN
A99: 53 | B99: ICRMS, ARMD | C99: Male | D99: Pat | E99: VALLEJOS | F99: DRANREB | G99: GAPAL | J99: OISS, SMD | K99: Male | L99: Pat | M99: PAQUIZ | N99: JOHN ANTHONY | O99: BATO
A100: 54 | B100: TSS, PTD | C100: Female | D100: Pat | E100: YAGO | F100: SHARMEN | G100: BALLEBAR | J100: ITPMD (DO) | K100: Male | L100: Pat | M100: PARALLAG | N100: MAX CASSANDER | O100: SINIGUIAN
A101: NON-UNIFORMED PERSONNEL
A102: 1 | B102: ICRMS, ARMD | C102: Male | D102: NUP | E102: ACORDA | F102: ELPIDIO | G102: PALARCA | J102: ICRMS, ARMD | K102: Male | L102: NUP | M102: ACORDA | N102: ELPIDIO | O102: PALARCA | Q102: Liaison Officer (SG7)
A103: 2 | B103: SPIS, SMD | C103: Female | D103: NUP | E103: ACUESTA | F103: ANA JUNE | G103: FORRO | J103: SPIS, SMD | K103: Female | L103: NUP | M103: ACUESTA | N103: ANA JUNE | O103: FORRO | Q103: Info Systems Researcher (SG17)
...

Sheet Disposition
A1: NATIONAL POLICE COMMISSION
A2: PHILIPPINE NATIONAL POLICE
A3: INFORMATION TECHNOLOGY MANAGEMENT SERVICE
A4: Camp Bgen Rafael T Crame, Quezon City
A6: Disposition of Personnel
A7: (As of September 7, 2026) | J7: =SUM(9+0+1) -> 10
A9: NO. | B9: OFFICE/DIVISION | C9: GENDER | D9: RANK | E9: LASTNAME | F9: FIRSTNAME | G9: MIDDLE NAME | H9: QUAL | I9: DESIGNATION | J9: ADDRESS | K9: CONTACT # | P9: NAME | Q9: ADDRESS
A10: 1 | B10: OD | C10: Male | D10: PBGEN | E10: PALGUE | F10: ROMY | G10: INWAY | I10: Director | J10: Imugan, Sta. Fe, Nueva Vizcaya | K10: 09175304121
A11: 2 | B11: OD | C11: Male | D11: PCpl | E11: CERIL | F11: PAUL KELVIN | G11: LAROZA | I11: Duty PNCO | J11: Purok Saranay, Palabotan, Dupax Del Sur, Nueva Vizcaya | K11: 09165565299
A12: 3 | B12: OD | C12: Male | D12: Pat | E12: BEJARIN | F12: GERALD | G12: DADIRO | I12: Duty PNCO | J12: Riang, Peñarrubia, Abra | K12: 09368167960 | P12: =CONCATENATE(E12," ",F12," ",G12) -> BEJARIN GERALD DADIRO | Q12: =IFERROR(VLOOKUP(P12,[1]Disposition!$AB$9:$AC$495,2,0),"NO RECORD YET") -> NO RECORD YET
A13: 4 | B13: OD | C13: Male | D13: Pat | E13: MORI | F13: LYNDON | G13: ACOSTA | I13: Duty PNCO | J13: Caimito, Brgy. Buencag, Gerona, Tarlac | K13: 09091819560 | P13: =CONCATENATE(E13," ",F13," ",G13) -> MORI LYNDON ACOSTA | Q13: =IFERROR(VLOOKUP(P13,[1]Disposition!$AB$9:$AC$495,2,0),"NO RECORD YET") -> NO RECORD YET
A14: 5 | B14: OD | C14: Female | D14: NUP | E14: AVENDAÑO | F14: MA. FRELIE JOY | G14: (no middle name) | I14: ISR II (SG14) | J14: #92 F Estrella St., San Juan, Malolos City, Bulacan | K14: 09554289264 | P14: =CONCATENATE(E14," ",F14," ",G14) -> AVENDAÑO MA. FRELIE JOY (no middle name) | Q14: =IFERROR(VLOOKUP(P14,[1]Disposition!$AB$9:$AC$495,2,0),"NO RECORD YET") -> #92 F Estrella St., San Juan, Malolos City, Bulacan
A15: 6 | B15: OD | C15: Female | D15: NUP | E15: DALLEGO | F15: RHIZA | G15: ARROYO | I15: Supply Accountable Officer | J15: Mb26 U109 Pamayanang Diego Silang, Brgy. Ususan, Taguig City | K15: 09950858301 | P15: =CONCATENATE(E15," ",F15," ",G15) -> DALLEGO RHIZA ARROYO | Q15: =IFERROR(VLOOKUP(P15,[1]Disposition!$AB$9:$AC$495,2,0),"NO RECORD YET") -> MB26 U109 Pamayanang Diego Silang, Brgy. Ususan, Taguig City
A16: 7 | B16: OD | C16: Female | D16: NUP | E16: LUZARA | F16: JEAN | G16: GRATUITO | I16: Training Specialist I (SG11) | J16: Blk 5 Lot 1 Orchid Extension, Capitol Park Homes Ii, Brgy 179 Zone 16, Caloocan City. | K16: 09177037934 | P16: =CONCATENATE(E16," ",F16," ",G16) -> LUZARA JEAN GRATUITO | Q16: =IFERROR(VLOOKUP(P16,[1]Disposition!$AB$9:$AC$495,2,0),"NO RECORD YET") -> Blk 5 Lot 1 Orchid Extension, Capitol Park Homes II, Brgy 179 Zone 16, Caloocan City.
A17: 8 | B17: ODDA | C17: Male | D17: PCOL | E17: TAGAO | F17: RONALD | G17: MIGUEL | I17: Deputy Director for Admin.
A18: 9 | B18: ODDA/ PRO13 | C18: Male | D18: PLTCOL | E18: TARUN | F18: CHRISTIAN | G18: BELTRAN | I18: BACSEC/ IT Project Officer | J18: 110B. Harrison Street, Vermont Park, Mayamot, Antipolo City, Rizal | K18: 09178359985 | P18: =CONCATENATE(E18," ",F18," ",G18) -> TARUN CHRISTIAN BELTRAN | Q18: =IFERROR(VLOOKUP(P18,[1]Disposition!$AB$9:$AC$495,2,0),"NO RECORD YET") -> 110B. Harrison Street, Vermont Park, Mayamot, Antipolo City, Rizal
A19: 10 | B19: ODDA | C19: Male | D19: PSSg | E19: CHAN | F19: HAROLD JAY | G19: AMAZONA | I19: Duty PNCO | P19: =CONCATENATE(E19," ",F19," ",G19) -> CHAN HAROLD JAY AMAZONA
A20: 11 | B20: ODDA | C20: Female | D20: NUP | E20: ERIBAL | F20: JOZEL JOY | G20: FALAGNE | I20: Administrative Assistant III (SG9) (DMD) | J20: 5A Diamond St., Jra Subd., Rosario, Pasug City | K20: 09617215961 | P20: =CONCATENATE(E20," ",F20," ",G20) -> ERIBAL JOZEL JOY FALAGNE | Q20: =IFERROR(VLOOKUP(P20,[1]Disposition!$AB$9:$AC$495,2,0),"NO RECORD YET") -> 5A Diamond St., JRA Subd., Rosario, Pasug City
A21: 12 | B21: ODDA | C21: Female | D21: NUP | E21: SEMILLA | F21: FLORITES | G21: SARIO | I21: Administrative Asst V (SG 11) | J21: 18 C Dungo St., Brgy, Isabelita, San Juan City | K21: 09274390528 | P21: =CONCATENATE(E21," ",F21," ",G21) -> SEMILLA FLORITES SARIO
A22: 13 | B22: DD for IT Matters | C22: Female | D22: NUP | E22: MATILLANO | F22: MINA HAYDEE | G22: BECERA | I22: DD IT(SG25) | J22: B2 L17 Rose St., Venice Homes Subd., Cainta, Rizal | K22: 09266411836 | P22: =CONCATENATE(E22," ",F22," ",G22) -> MATILLANO MINA HAYDEE BECERA | Q22: =IFERROR(VLOOKUP(P22,[1]Disposition!$AB$9:$AC$495,2,0),"NO RECORD YET") -> B2 L17 Rose St., Venice Homes Subd., Cainta, Rizal
A23: 14 | B23: ODDIT | C23: Female | D23: NUP | E23: BAGO | F23: REBECCA | G23: LLANEZA | I23: Administrative Assistant VI (SG12) | J23: 196 Guyam Malaki, Indang, Cavite | K23: 09278398862 | P23: =CONCATENATE(E23," ",F23," ",G23) -> BAGO REBECCA LLANEZA | Q23: =IFERROR(VLOOKUP(P23,[1]Disposition!$AB$9:$AC$495,2,0),"NO RECORD YET") -> 196 Guyam Malaki, Indang, Cavite
A24: 15 | B24: ODDIT | C24: Female | D24: NUP | E24: CAADAN | F24: JENNYFER | G24: PISCO | I24: Administrative Aide VI (SG6) | J24: 65 Lower Molave St. Payatas B, QC | K24: 9294573659
A25: 16 | B25: OCS | C25: Male | D25: PCOL | E25: PATIÑO | F25: RANDI | G25: MANZANO | I25: Chief of Staff/Chief, PSMU | J25: Mddle Nivel Hills, Brgy Apas, Cebu City | K25: 09057369133 | P25: =CONCATENATE(E25," ",F25," ",G25) -> PATIÑO RANDI MANZANO | Q25: =IFERROR(VLOOKUP(P25,[1]Disposition!$AB$9:$AC$495,2,0),"NO RECORD YET") -> Mddle Nivel Hills, Brgy Apas, Cebu City
A26: 17 | B26: OCS | C26: Male | D26: PCPT | E26: KARIM | F26: BENSAR ALI | G26: ABDULGANI | I26: Secretary of the Chief of Staff | J26: 21-B Maguindanao St, Culiat, Quezon City | K26: 09267388655 | P26: =CONCATENATE(E26," ",F26," ",G26) -> KARIM BENSAR ALI ABDULGANI | Q26: =IFERROR(VLOOKUP(P26,[1]Disposition!$AB$9:$AC$495,2,0),"NO RECORD YET") -> 21-B Maguindanao St, Culiat, Quezon City
A27: 18 | B27: OCS | C27: Male | D27: PCpl | E27: AGGARAO | F27: ALBERTO | G27: CALLANGAN | I27: Action PNCO | J27: 215 D Guiho St., Cembo, Makati City | K27: 09434383476 | P27: =CONCATENATE(E27," ",F27," ",G27) -> AGGARAO ALBERTO CALLANGAN | Q27: =IFERROR(VLOOKUP(P27,[1]Disposition!$AB$9:$AC$495,2,0),"NO RECORD YET") -> 215 D Guiho St., Cembo, Makati City
A28: 19 | B28: OCS | C28: Female | D28: PCpl | E28: SANG-AN | F28: CATHERINE | G28: VALDESTAMON | I28: Secretary | J28: Zone 1 Purok Maligaya, Tagburos, Puerto Princesa City, Palawan | K28: 09279979400 | P28: =CONCATENATE(E28," ",F28," ",G28) -> SANG-AN CATHERINE VALDESTAMON | Q28: =IFERROR(VLOOKUP(P28,[1]Disposition!$AB$9:$AC$495,2,0),"NO RECORD YET") -> NO RECORD YET
A29: 20 | B29: OCS | C29: Female | D29: NUP | E29: ESTEVES | F29: MARICEL | G29: FRESNOZA | I29: Information Systems Researcher (SG10) | J29: 3310 Bataan St., Bacood, Sta.Mesa, Manila | K29: 09293473925 | P29: =CONCATENATE(E29," ",F29," ",G29) -> ESTEVES MARICEL FRESNOZA | Q29: =IFERROR(VLOOKUP(P29,[1]Disposition!$AB$9:$AC$495,2,0),"NO RECORD YET") -> 3310 Bataan St., Bacood, Sta.Mesa, Manila
A30: 21 | B30: PIO | C30: Male | D30: Pat | E30: PEÑON | F30: JAYSON | G30: CABRAL | I30: Duty PNCO/CSG (creation of AVP) | J30: 1901 Interior, Zamora Street, Manila, NCR | K30: 09608411365 | P30: =CONCATENATE(E30," ",F30," ",G30) -> PEÑON JAYSON CABRAL | Q30: =IFERROR(VLOOKUP(P30,[1]Disposition!$AB$9:$AC$495,2,0),"NO RECORD YET") -> NO RECORD YET
A31: 22 | B31: PIO | C31: Female | D31: NUP | E31: ALVAREZ | F31: PAMELA | G31: CEREZO | I31: PIO/PCR Staff (SG7) | J31: Pao, Manaoag, Pangasinan | K31: 09615765167 | P31: =CONCATENATE(E31," ",F31," ",G31) -> ALVAREZ PAMELA CEREZO | Q31: =IFERROR(VLOOKUP(P31,[1]Disposition!$AB$9:$AC$495,2,0),"NO RECORD YET") -> Pao, Manaoag, Pangasinan
A32: 23 | B32: PIO | C32: Male | D32: NUP | E32: RUIVIVAR | F32: JOSE SALVADOR | G32: DEL ROSARIO | I32: OIC, PIO/PCR Staff (SG14) | J32: 13 St. Joseph St., Milton Hills Subd, Diliman, Quezon City | K32: 09770330570 | P32: =CONCATENATE(E32," ",F32," ",G32) -> RUIVIVAR JOSE SALVADOR DEL ROSARIO | Q32: =IFERROR(VLOOKUP(P32,[1]Disposition!$AB$9:$AC$495,2,0),"NO RECORD YET") -> 13 St. Joseph St., Milton Hills Subd, Diliman, Quezon City
A33: 24 | B33: SLO/OCI | C33: Female | D33: PMAJ | E33: UNTALAN | F33: EDUARDO | G33: SANTOS | H33: II | I33: Servicing Legal Officer | J33: Purok 5, Santa Cruz, Bagabag, Nueva Vizcaya | K33: 09178334438 | P33: =CONCATENATE(E33," ",F33," ",G33) -> UNTALAN EDUARDO SANTOS
A34: 25 | B34: SLO/OCI/ARMD | C34: Male | D34: PMSg | E34: CANJA | F34: ROBERTO | G34: GINETA | H34: JR | I34: Duty PNCO/OIC, C, Clerk, ARMD | J34: Brgy. Mambabanga, Luna, Isabela | K34: 09350231418 | P34: =CONCATENATE(E34," ",F34," ",G34) -> CANJA ROBERTO GINETA | Q34: =IFERROR(VLOOKUP(P34,[1]Disposition!$AB$9:$AC$495,2,0),"NO RECORD YET") -> Brgy. Mambabanga, Luna, Isabela
A35: 26 | B35: SLO/OCI | C35: Female | D35: PCpl | E35: CUASAY | F35: ZAYRA JANE | G35: CEDENO | I35: Duty PNCO | J35: 29 P Dizon Circle, Hen. T. De Leon, Valenzuela City | K35: 09953744137 | P35: =CONCATENATE(E35," ",F35," ",G35) -> CUASAY ZAYRA JANE CEDENO | Q35: =IFERROR(VLOOKUP(P35,[1]Disposition!$AB$9:$AC$495,2,0),"NO RECORD YET") -> NO RECORD YET
A36: 27 | B36: SLO/OCI | C36: Female | D36: NUP | E36: COSTALES | F36: MARY GRACE | G36: RODRIGUEZ | I36: Computer Programmjer (SG11) | J36: 7C 2Nd Ave., Bagong Lipunan Ng Crame, Quezon City | K36: 09275492985 | P36: =CONCATENATE(E36," ",F36," ",G36) -> COSTALES MARY GRACE RODRIGUEZ | Q36: =IFERROR(VLOOKUP(P36,[1]Disposition!$AB$9:$AC$495,2,0),"NO RECORD YET") -> NO RECORD YET
A37: 28 | B37: SLO/OCI | C37: Female | D37: NUP | E37: VER | F37: MARIE LOUISE ROVIAN | G37: RAMOS | I37: Administrative Assistant I (SG7) | J37: Blk 43 Lot 16, Phase 7, Eastwood Residences, Brgy San Isidro, Montalban, Rizal | K37: 09158167417 | P37: =CONCATENATE(E37," ",F37," ",G37) -> VER MARIE LOUISE ROVIAN RAMOS | Q37: =IFERROR(VLOOKUP(P37,[1]Disposition!$AB$9:$AC$495,2,0),"NO RECORD YET") -> Blk 43 Lot 16, Phase 7, Eastwood Residences, Brgy San Isidro, Montalban, Rizal
A38: 29 | B38: PSMU | C38: Female | D38: Pat | E38: CELARIO | F38: RUBY ROSE | G38: BUEZA | I38: Staff, SMAS, PSMU | J38: 37 Tagumpay St. Marawi, Camiling, Tarlac | K38: 09514992446 | P38: =CONCATENATE(E38," ",F38," ",G38) -> CELARIO RUBY ROSE BUEZA | Q38: =IFERROR(VLOOKUP(P38,[1]Disposition!$AB$9:$AC$495,2,0),"NO RECORD YET") -> NO RECORD YET
A39: 30 | B39: PSMU | C39: Female | D39: NUP | E39: DAGUPLO | F39: ROSETTE | G39: CASTILLO | I39: Administrative Aide VI (SG6) (DMD) | P39: =CONCATENATE(E39," ",F39," ",G39) -> DAGUPLO ROSETTE CASTILLO
A40: 31 | B40: PSMU | C40: Female | D40: NUP | E40: FRANDO | F40: DANICA | G40: DATO-ON | I40: Administrative Aide VI (SG6) (DMD) | P40: =CONCATENATE(E40," ",F40," ",G40) -> FRANDO DANICA DATO-ON
A41: 32 | B41: PSMU | C41: Female | D41: NUP | E41: NABONG | F41: WENDA GREEN LINDON | G41: TOMAS | I41: Staff, Change Mgmt and Best Practices, SRS (SG6) | P41: =CONCATENATE(E41," ",F41," ",G41) -> NABONG WENDA GREEN LINDON TOMAS
A42: 33 | B42: PSMU | C42: Female | D42: NUP | E42: QUIJANO | F42: SHEILA MARIE | G42: VELARDE | I42: Administrative Aide VI (SG6) (DMD) | P42: =CONCATENATE(E42," ",F42," ",G42) -> QUIJANO SHEILA MARIE VELARDE
A43: 34 | B43: ITPMD | C43: Female | D43: PLTCOL | E43: FABRO | F43: JHOANNA GRACIA | G43: MANLAPAZ | I43: Asst. Chief/OIC, PIO/Asst. Chief, PSMU | J43: Purok 5, Santa Cruz, Bagabag, Nueva Vizcaya | K43: 09178334438
A44: 35 | B44: ITPMD | C44: Male | D44: PMSg | E44: PEÑAVERDE | F44: PHILIP JAMES | G44: RODRIGUEZ | I44: Chief, EMS | J44: Blk 1 Lot 128 P1-F Sub-Urban Village, Saan Jose, Rodriguez, Rizal | K44: 09266167584 | P44: =CONCATENATE(E44," ",F44," ",G44) -> PEÑAVERDE PHILIP JAMES RODRIGUEZ | Q44: =IFERROR(VLOOKUP(P44,[1]Disposition!$AB$9:$AC$495,2,0),"NO RECORD YET") -> Blk 1 Lot 128 P1-F Sub-Urban Village, Saan Jose, Rodriguez, Rizal
A45: 36 | B45: ITPMD | C45: Female | D45: Pat | E45: PACIENCIA | F45: METALLICA LYH | G45: OCTAVIANO | I45: Duty PNCO | J45: Real St., San Jose, Brgy. 85, Tacloban City, Leyte | K45: 09973655525 | P45: =CONCATENATE(E45," ",F45," ",G45) -> PACIENCIA METALLICA LYH OCTAVIANO | Q45: =IFERROR(VLOOKUP(P45,[1]Disposition!$AB$9:$AC$495,2,0),"NO RECORD YET") -> NO RECORD YET
A46: 37 | B46: ITPMD | C46: Female | D46: NUP | E46: BERENGUEL | F46: LUCHIE | G46: RELOYA | I46: Administrative Assistant II (SG8) | J46: #2 Alley 15, P. Rosales St., Sta. Ana Kaliwa, Pateros | K46: 09662553586 | P46: =CONCATENATE(E592," ",F592," ",G592) -> RAMOS WENCESLAO AGUILAR | Q46: =IFERROR(VLOOKUP(P46,[1]Disposition!$AB$9:$AC$495,2,0),"NO RECORD YET") -> 5-A St.Paul St., Remerville Subd. Baesa, Quezon City
A47: 38 | B47: ITPMD | C47: Male | D47: NUP | E47: DAGTA | F47: MARY ANN | G47: Yap | I47: Admin Assistant (SG9) | J47: Blk 3, Lot 20, Amber St., Summit Viwe Subd., Brgy. San Rafael, Rodriguez, Rizal | K47: 09568629227 | P47: =CONCATENATE(E47," ",F47," ",G47) -> DAGTA MARY ANN Yap | Q47: =IFERROR(VLOOKUP(P47,[1]Disposition!$AB$9:$AC$495,2,0),"NO RECORD YET") -> Blk 3, Lot 20, Amber St., Summit Viwe Subd., Brgy. San Rafael, Rodriguez, Rizal
A48: 39 | B48: ITPMD/ DICTM | C48: Female | D48: NUP | E48: GONZALES | F48: NECILDA | G48: JAVINIAR | I48: Administrative Assistant (SG9) (ARMD) | J48: 641 Blk 22 Kabisig Floodway, San Andres, Cainta, Rizal | K48: 09187708759 | P48: =CONCATENATE(E337," ",F337," ",G337) -> BATICADOS IVY ELEGARLE | Q48: =IFERROR(VLOOKUP(P48,[1]Disposition!$AB$9:$AC$495,2,0),"NO RECORD YET") -> EL Dorado Dulo, Brgy. Don Bosco, Better Living Subd., Parañaque City
A49: 40 | B49: ITPMIS, ITPMD | C49: Female | D49: PCPT | E49: QUINTOS | F49: ANGELICA | G49: AGOR | I49: Chief, ITPMIS/OIC, SCS | J49: B1 L128 Phase 1F, Sub Urban Village, San Jose, Montalban, Rizal | K49: 09458154169 | P49: =CONCATENATE(E49," ",F49," ",G49) -> QUINTOS ANGELICA AGOR | Q49: =IFERROR(VLOOKUP(P432,[1]Disposition!$AB$9:$AC$495,2,0),"NO RECORD YET") -> NO RECORD YET
A50: 41 | B50: ITPMIS, ITPMD | C50: Male | D50: Pat | E50: MANAOG | F50: RODNIE | G50: CASTILLO | I50: Duty PNCO | J50: Sitio Pongol., Brgy. Burabod, San Antonio, Northern Samar | K50: 09452066435 | N50: 3 | P50: =CONCATENATE(E50," ",F50," ",G50) -> MANAOG RODNIE CASTILLO | Q50: =IFERROR(VLOOKUP(P49,[1]Disposition!$AB$9:$AC$495,2,0),"NO RECORD YET") -> B1 L128 Phase 1F, Sub Urban Village, San Jose, Montalban, Rizal
A51: 42 | B51: ITPMIS, ITPMD | C51: Male | D51: Pat | E51: MORTEL | F51: ALWYN | G51: ALBUFERA | I51: Duty PNCO | J51: 330 Ilaya, Butong, Taal, Batangas | K51: 09652107608 | N51: 4 | P51: =CONCATENATE(E51," ",F51," ",G51) -> MORTEL ALWYN ALBUFERA | Q51: =IFERROR(VLOOKUP(P50,[1]Disposition!$AB$9:$AC$495,2,0),"NO RECORD YET") -> NO RECORD YET
A52: 43 | B52: EMS, ITPMD | C52: Female | D52: PEMS | E52: GASCON | F52: MARIA LUZ | G52: BUMAGAT | I52: Chief, EMS | J52: 3065 Abucay St., Manuguit Subd., Tondo, Manila | K52: 09059797471 | P52: =CONCATENATE(E52," ",F52," ",G52) -> GASCON MARIA LUZ BUMAGAT | Q52: =IFERROR(VLOOKUP(P51,[1]Disposition!$AB$9:$AC$495,2,0),"NO RECORD YET") -> NO RECORD YET
A53: 44 | B53: EMS, ITPMD | C53: Female | D53: NUP | E53: IRASUSTA | F53: JOANA MARIE | G53: NATIVIDAD | I53: Action NUP (SG7) | P53: =CONCATENATE(E53," ",F53," ",G53) -> IRASUSTA JOANA MARIE NATIVIDAD
A54: 45 | B54: ITPMD (OCPNP) | C54: Male | D54: PCPT | E54: SOSA | F54: GIBSON JOHN | G54: ARAOS | I54: IT Project Officer | J54: #10 Singapore, Bastulde, Fil-Inves, Cainta, Rizal | K54: 09176229285 | P54: =CONCATENATE(E54," ",F54," ",G54) -> SOSA GIBSON JOHN ARAOS | Q54: =IFERROR(VLOOKUP(P53,[1]Disposition!$AB$9:$AC$495,2,0),"NO RECORD YET") -> NO RECORD YET
A55: 46 | B55: ITPMD (OCPNP) | C55: Male | D55: PMAJ | E55: TAN | F55: ACHILES | G55: YABUT | I55: IT Project Officer | J55: Blk 1 Lot 33, Maunlad Homes Subd., Caingin, Malolos, Bulacan | K55: 09985974254 | P55: =CONCATENATE(E55," ",F55," ",G55) -> TAN ACHILES YABUT | Q55: =IFERROR(VLOOKUP(P54,[1]Disposition!$AB$9:$AC$495,2,0),"NO RECORD YET") -> #10 Singapore, Bastulde, Fil-Inves, Cainta, Rizal
A56: 47 | B56: ITPMD (OCPNP) | C56: Female | D56: PCpl | E56: CLAOR | F56: MICHELLE | G56: DUGAM | I56: IT Project PNCO | J56: Toon, La Paz, Abra | K56: 09556384560 | P56: =CONCATENATE(E56," ",F56," ",G56) -> CLAOR MICHELLE DUGAM | Q56: =IFERROR(VLOOKUP(P55,[1]Disposition!$AB$9:$AC$495,2,0),"NO RECORD YET") -> Blk 1 Lot 33, Maunlad Homes Subd., Caingin, Malolos, Bulacan
A57: 48 | B57: ITPMD (PPDC) | C57: Male | D57: NUP | E57: AGUILAR | F57: BERNARDINO | G57: SANTOS | I57: IT NUP (SG7) | J57: 194 Capt. I. Abella St., Poblacion 4-C, Imus City, Cavite | K57: 09175032721 | P57: =CONCATENATE(E57," ",F57," ",G57) -> AGUILAR BERNARDINO SANTOS | Q57: =IFERROR(VLOOKUP(P56,[1]Disposition!$AB$9:$AC$495,2,0),"NO RECORD YET") -> Toon, La Paz, Abra
A58: 49 | B58: ITPMD (PIO) | C58: Male | D58: PCPT | E58: ALIMAMBO | F58: JICK | G58: BONUAN | I58: IT Project Officer | J58: 72 Pucay Village, Purok I, Bakakeng Norte, Baguio City | K58: 09774274007 | P58: =CONCATENATE(E58," ",F58," ",G58) -> ALIMAMBO JICK BONUAN | Q58: =IFERROR(VLOOKUP(P127,[1]Disposition!$AB$9:$AC$495,2,0),"NO RECORD YET") -> NO RECORD YET
A59: 50 | B59: ITPMD (CPSM) | C59: Male | D59: PCpl | E59: LUALHATI | F59: PAULO ANDREW | G59: PUNZALAN | I59: IT Project PNCO | J59: 33 Jw Diokno St., Poblacion 13, Taal, Batangas | K59: 09568569677 | P59: =CONCATENATE(E59," ",F59," ",G59) -> LUALHATI PAULO ANDREW PUNZALAN | Q59: =IFERROR(VLOOKUP(P58,[1]Disposition!$AB$9:$AC$495,2,0),"NO RECORD YET") -> 72 Pucay Village, Purok I, Bakakeng Norte, Baguio City
A60: 51 | B60: ITPMD (CPSM) | C60: Male | D60: Pat | E60: TUBELLEZA | F60: JOHN CARLO | G60: VILLARINO | I60: IT Project PNCO | J60: 33 Family Ville Subdivision, Bucal, Tanza, Cavite | K60: 09957230126 | P60: =CONCATENATE(E60," ",F60," ",G60) -> TUBELLEZA JOHN CARLO VILLARINO | Q60: =IFERROR(VLOOKUP(P59,[1]Disposition!$AB$9:$AC$495,2,0),"NO RECORD YET") -> 33 JW Diokno St., Poblacion 13, Taal, Batangas
A61: 52 | B61: ITPMD (IAS) | C61: Female | D61: PCPT | E61: ESTRADA | F61: MICAELLA ALLYSSA | G61: MONTES | I61: IT Project Officer | J61: 15 Jonathan St., Brgy. 55, Tondo, Manila | K61: 09156803437 | P61: =CONCATENATE(E61," ",F61," ",G61) -> ESTRADA MICAELLA ALLYSSA MONTES | Q61: =IFERROR(VLOOKUP(P60,[1]Disposition!$AB$9:$AC$495,2,0),"NO RECORD YET") -> NO RECORD YET
A62: 53 | B62: ITPMD (IAS) | C62: Male | D62: PLT | E62: ECHANO | F62: KERWIN | G62: RUFON | I62: IT Project Officer | J62: Lot 37-38 Blk.5 Catanauan St., Vanessa Homes, Bucal, Calamba, Laguna | K62: 09760708892 | P62: =CONCATENATE(E62," ",F62," ",G62) -> ECHANO KERWIN RUFON | Q62: =IFERROR(VLOOKUP(P61,[1]Disposition!$AB$9:$AC$495,2,0),"NO RECORD YET") -> 15 Jonathan St., Brgy. 55, Tondo, Manila
A63: 54 | B63: ITPMD (HRAO) | C63: Female | D63: PCPT | E63: SALAS | F63: EUNILAINE | G63: SALVADOR | I63: IT Project Officer | J63: 131 Wwest Drive St., Narikina Heights, Marikina City | K63: 09175518988 | P63: =CONCATENATE(E63," ",F63," ",G63) -> SALAS EUNILAINE SALVADOR | Q63: =IFERROR(VLOOKUP(P62,[1]Disposition!$AB$9:$AC$495,2,0),"NO RECORD YET") -> Lot 37-38 BLK.5 Catanauan ST., Vanessa Homes, Bucal, Calamba, Laguna
A64: 55 | B64: ITPMD (OTDCA) | C64: Male | D64: PCPT | E64: MUÑOZ | F64: RANZ NIKKO | G64: BIEN | I64: IT Project Officer | J64: Blk. 15 Lot 22, Viola St., Camella Sorrento, P.F. Espiritu Iv, Bacoor, Cavite | K64: 09959045925 | P64: =CONCATENATE(E64," ",F64," ",G64) -> MUÑOZ RANZ NIKKO BIEN | Q64: =IFERROR(VLOOKUP(P63,[1]Disposition!$AB$9:$AC$495,2,0),"NO RECORD YET") -> 131 Wwest Drive St., Narikina Heights, Marikina City
A65: 56 | B65: ITPMD (OTDCA) | C65: Male | D65: Pat | E65: BACATAN | F65: FERDINAND | G65: JALOVA | H65: JR | I65: IT Project PNCO | J65: Blk 55b Lot 1 Sitio Panghulo, Floodway, San Juan, Taytay, Rizal | K65: 09465348401 | P65: =CONCATENATE(E65," ",F65," ",G65) -> BACATAN FERDINAND JALOVA | Q65: =IFERROR(VLOOKUP(P64,[1]Disposition!$AB$9:$AC$495,2,0),"NO RECORD YET") -> Blk. 15 Lot 22, Viola St., Camella Sorrento, P.F. Espiritu IV, Bacoor, Cavite
A66: 57 | B66: ITPMD (OTDCO) | C66: Male | D66: PCMS | E66: MARAÑON | F66: CHRIS JOHN | G66: CATALOGO | I66: IT Project PNCO | J66: B18 L1 P-J Francisco Homes, Sjdm, Bulacan | K66: 09217221646 | P66: =CONCATENATE(E66," ",F66," ",G66) -> MARAÑON CHRIS JOHN CATALOGO | Q66: =IFERROR(VLOOKUP(P65,[1]Disposition!$AB$9:$AC$495,2,0),"NO RECORD YET") -> NO RECORD YET
A67: 58 | B67: ITPMD (OTCDS) | C67: Male | D67: PMAJ | E67: AMIT | F67: ARIEL | G67: DE GUZMAN | I67: IT Project Officer | J67: Manila, Metro Manila | K67: 09205682939 | P67: =CONCATENATE(E67," ",F67," ",G67) -> AMIT ARIEL DE GUZMAN | Q67: =IFERROR(VLOOKUP(P66,[1]Disposition!$AB$9:$AC$495,2,0),"NO RECORD YET") -> B18 L1 P-J Francisco Homes, SJDM, Bulacan
A68: 59 | B68: ITPMD (OTCDS) | C68: Male | D68: PLT | E68: ILACAD | F68: DIONELL | G68: TUGADE | I68: IT Project Officer | J68: Cabaroan, Santa Maria, Ilocos Sur | K68: 09773306823 | P68: =CONCATENATE(E68," ",F68," ",G68) -> ILACAD DIONELL TUGADE
A69: 60 | B69: ITPMD (OTCDS) | C69: Male | D69: PMSg | E69: DULIN | F69: JOEY | G69: BINARAO | I69: IT Project PNCO | J69: 155 19Th Avenue, East Pembo, Makati City | K69: 09175073304 | P69: =CONCATENATE(E69," ",F69," ",G69) -> DULIN JOEY BINARAO | Q69: =IFERROR(VLOOKUP(P68,[1]Disposition!$AB$9:$AC$495,2,0),"NO RECORD YET") -> NO RECORD YET
A70: 61 | B70: ITPMD (OTCDS) | C70: Male | D70: PCpl | E70: DOCTOLERO | F70: JOHN NICK | G70: DE GUZMAN | I70: IT Project PNCO | J70: B25 L5 Ph. J, Brgy. Guijo, Francisco Homes, Sjdm, Bulacan | K70: 09063610614 | P70: =CONCATENATE(E70," ",F70," ",G70) -> DOCTOLERO JOHN NICK DE GUZMAN | Q70: =IFERROR(VLOOKUP(P69,[1]Disposition!$AB$9:$AC$495,2,0),"NO RECORD YET") -> 155 19th Avenue, East Pembo, Makati City
A71: 62 | B71: ITPMD (DICTM) | C71: Male | D71: NUP | E71: DIMACULANGAN | F71: JOHN VINCENT | G71: VENTURA | I71: Data Controller (SG7) | P71: =CONCATENATE(E596," ",F596," ",G596) -> BALUCANAG GRACE EBARSABAL | Q71: =IFERROR(VLOOKUP(P70,[1]Disposition!$AB$9:$AC$495,2,0),"NO RECORD YET") -> B25 L5 PH. J, Brgy. Guijo, Francisco Homes, SJDM, Bulacan
A72: 63 | B72: ITPMD (DICTM) | C72: Female | D72: NUP | E72: MEJIA | F72: GIRLIE | G72: CRUZ | I72: IT NUP (SG7) | J72: Main Ave., Cubao, Quezon City | K72: 09459925499 | P72: =CONCATENATE([2]Disposition!D387," ",[2]Disposition!E387," ",[2]Disposition!F387) -> NUP MEJIA GIRLIE | Q72: =IFERROR(VLOOKUP(P71,[1]Disposition!$AB$9:$AC$495,2,0),"NO RECORD YET") -> 2333 Mangga Extn., Velasco Ave., Napico, Manggahan, Pasig
A73: 64 | B73: ITPMD (DICTM) | C73: Female | D73: NUP | E73: PINEDA | F73: PRECIOUS PEARL | G73: PACTAO | I73: Database Administrator (SG7) | P73: =CONCATENATE(E585," ",F585," ",G585) -> HUERNO CLARISS ANN VALLESFINO | Q73: =IFERROR(VLOOKUP(P72,[1]Disposition!$AB$9:$AC$495,2,0),"NO RECORD YET") -> NO RECORD YET
A74: 65 | B74: ITPMD (DPRM) | C74: Male | D74: PMAJ | E74: DELA CRUZ | F74: ALVIN | G74: ORUA | I74: IT Project Officer | J74: #6087 Sto. Rosario St., Mapulang Lupa, Valenzuela City | K74: 09178710735 | P74: =CONCATENATE(E74," ",F74," ",G74) -> DELA CRUZ ALVIN ORUA | Q74: =IFERROR(VLOOKUP(P73,[1]Disposition!$AB$9:$AC$495,2,0),"NO RECORD YET") -> NO RECORD YET
A75: 66 | B75: ITPMD (DPRM) | C75: Male | D75: PMAJ | E75: DESEO | F75: REYNANTE | G75: NUYDA | I75: IT Project Officer | J75: Blk 4 L17 Arty In Subdivision, Karuhatan, Valenzueal City | K75: 09974766710 | P75: =CONCATENATE(E75," ",F75," ",G75) -> DESEO REYNANTE NUYDA | Q75: =IFERROR(VLOOKUP(P74,[1]Disposition!$AB$9:$AC$495,2,0),"NO RECORD YET") -> #6087 Sto. Rosario St., Mapulang Lupa, Valenzuela City
A76: 67 | B76: ITPMD (DPRM) | C76: Female | D76: PCpl | E76: CASTRO | F76: MARYJANE | G76: DIZON | I76: IT PNCO | J76: Phase 1, Purok 5, Taugtog, Botolan, Zambales | K76: 09501115804 | P76: =CONCATENATE(E76," ",F76," ",G76) -> CASTRO MARYJANE DIZON | Q76: =IFERROR(VLOOKUP(P75,[1]Disposition!$AB$9:$AC$495,2,0),"NO RECORD YET") -> Blk 4 L17 Arty in Subdivision, Karuhatan, Valenzueal City
A77: 68 | B77: ITPMD (DPRM) | C77: Female | D77: NUP | E77: LUMABI | F77: GINA | G77: TINGALA | I77: IT NUP (SG7) | J77: Mb 15 Rm 109, Diego Silang Village, Brgy Ususan, Taguig City | K77: 09471754148 | P77: =CONCATENATE(E77," ",F77," ",G77) -> LUMABI GINA TINGALA | Q77: =IFERROR(VLOOKUP(P76,[1]Disposition!$AB$9:$AC$495,2,0),"NO RECORD YET") -> Phase 1, Purok 5, Taugtog, Botolan, Zambales
A78: 69 | B78: ITPMD (DPRM) | C78: Female | D78: NUP | E78: UBANDO | F78: MARY ANN | G78: OBENA | I78: IT NUP (SG7) | J78: Blk 13 Lot 14 Phase M, Francisco Homes, Brgy. Guijo, Sjdm, Bulacan | K78: 09197265632 | P78: =CONCATENATE(E78," ",F78," ",G78) -> UBANDO MARY ANN OBENA | Q78: =IFERROR(VLOOKUP(P77,[1]Disposition!$AB$9:$AC$495,2,0),"NO RECORD YET") -> MB 15 RM 109, Diego Silang Village, Brgy Ususan, Taguig City
A79: 70 | B79: ITPMD (DRD) | C79: Male | D79: PMAJ | E79: LAXAMANA | F79: JOSE | G79: DELA CRUZ | H79: II | I79: IT Project Officer | J79: 191 Gen. Mascardo St., Bagong Barrio, Caloocan City | K79: 09983998333 | P79: =CONCATENATE(E79," ",F79," ",G79) -> LAXAMANA JOSE DELA CRUZ | Q79: =IFERROR(VLOOKUP(P78,[1]Disposition!$AB$9:$AC$495,2,0),"NO RECORD YET") -> Blk 13 Lot 14 Phase M, Francisco Homes, Brgy. Guijo, SJDM, Bulacan
A80: 71 | B80: ITPMD (DRD) | C80: Male | D80: NUP | E80: MANAHAN | F80: ALDRIN | G80: ENRIQUEZ | I80: IT NUP (SG6)
A81: 72 | B81: ITPMD (DIDM) | C81: Male | D81: PMAJ | E81: NOBRES | F81: ROY | G81: DANGSI | I81: IT Project Officer | J81: Lot 4-Lot 5 Metro Royale Homes Burgos, Montalban, Rizal | K81: 09178665305 | P81: =CONCATENATE(E81," ",F81," ",G81) -> NOBRES ROY DANGSI | Q81: =IFERROR(VLOOKUP(P80,[1]Disposition!$AB$9:$AC$495,2,0),"NO RECORD YET") -> NO RECORD YET
A82: 73 | B82: ITPMD (DIDM) | C82: Male | D82: PCPT | E82: ABO | F82: MARK JESSIE | G82: MELITANTE | I82: IT Project Officer | J82: Unit 909, Amaia Skies Cuibao, P. Tuazon Ave., Socorro, Quezon City | K82: 09566570420 | P82: =CONCATENATE(E82," ",F82," ",G82) -> ABO MARK JESSIE MELITANTE | Q82: =IFERROR(VLOOKUP(P81,[1]Disposition!$AB$9:$AC$495,2,0),"NO RECORD YET") -> Lot 4-Lot 5 Metro Royale Homes Burgos, Montalban, Rizal
A83: 74 | B83: ITPMD (DIDM) | C83: Male | D83: PLT | E83: GALAMGAM | F83: RAMON | G83: DIAZ | H83: JR | I83: IT Project Officer | J83: 8B Notre Dame, Silangan, Quezon City | K83: 09568570005 | P83: =CONCATENATE(E83," ",F83," ",G83) -> GALAMGAM RAMON DIAZ
A84: 75 | B84: ITPMD (DIDM) | C84: Female | D84: Pat | E84: ABRIAM | F84: ANNETH VALERIE | G84: MALNAT | I84: IT Project PNCO | J84: 13 P1 Villa Jose Ylanan, Maddela, Quirino | K84: 09686456470 | P84: =CONCATENATE(E84," ",F84," ",G84) -> ABRIAM ANNETH VALERIE MALNAT | Q84: =IFERROR(VLOOKUP(P83,[1]Disposition!$AB$9:$AC$495,2,0),"NO RECORD YET") -> 38 Agno, Tayug, Pangasinan
A85: 76 | B85: ITPMD (DIDM) | C85: Female | D85: Pat | E85: SAET | F85: MITZI ANNE | G85: BESA | I85: IT Project PNCO | J85: Lambingan, Sunrise Viu Village, San Guillermo, Morong, Rizal | K85: 09311126415 | P85: =CONCATENATE(E85," ",F85," ",G85) -> SAET MITZI ANNE BESA | Q85: =IFERROR(VLOOKUP(P84,[1]Disposition!$AB$9:$AC$495,2,0),"NO RECORD YET") -> NO RECORD YET
A86: 77 | B86: ITPMD (DIDM) | C86: Male | D86: Pat | E86: SALES | F86: JAFET | G86: ANINAO | I86: IT Project PNCO | J86: 164 J.P Rizal St., J.Rizal, Santa Maria, Laguna | K86: 09167919991 | P86: =CONCATENATE(E86," ",F86," ",G86) -> SALES JAFET ANINAO | Q86: =IFERROR(VLOOKUP(P85,[1]Disposition!$AB$9:$AC$495,2,0),"NO RECORD YET") -> NO RECORD YET
A87: 78 | B87: ITPMD (DIDM) | C87: Female | D87: NUP | E87: BUTLIG | F87: MARIE FE | G87: TUANDA | I87: IT NUP (SG6) | P87: =CONCATENATE(E87," ",F87," ",G87) -> BUTLIG MARIE FE TUANDA
A88: 79 | B88: ITPMD (DIDM-WCPC) | C88: Male | D88: PMAJ | E88: NICOLAS | F88: JAY-R | G88: TADEO | I88: IT Project Officer | J88: #143 Asin West., Malasigue, Pangasinan | K88: 09770935729 | P88: =CONCATENATE(E88," ",F88," ",G88) -> NICOLAS JAY-R TADEO | Q88: =IFERROR(VLOOKUP(P431,[1]Disposition!$AB$9:$AC$495,2,0),"NO RECORD YET") -> 2315 T2 Amaia Skies, Cubao, 5the Ave. cor P Tuazon Ave., Brgy. Socorro, Quezon City
A89: 80 | B89: ITPMD (DPL) | C89: Male | D89: PMAJ | E89: SY | F89: CHRISTIAN | G89: ONG | I89: IT Project Officer | J89: 4 | K89: 09176548452 | P89: =CONCATENATE(E89," ",F89," ",G89) -> SY CHRISTIAN ONG | Q89: =IFERROR(VLOOKUP(P88,[1]Disposition!$AB$9:$AC$495,2,0),"NO RECORD YET") -> #143 Asin West., Malasigue, Pangasinan
A90: 81 | B90: ITPMD (DPL) | C90: Male | D90: PLT | E90: GUIFAYA | F90: GILBERT | G90: ULIDAN | H90: JR | I90: IT Project Officer | P90: =CONCATENATE(E90," ",F90," ",G90) -> GUIFAYA GILBERT ULIDAN
A91: 82 | B91: ITPMD (DPL) | C91: Male | D91: Pat | E91: BILLOSO | F91: AL ANTHONY | G91: CONSOLACION | I91: IT Project PNCO | J91: B43 L11 Adrian St., Fairmoint Subd., North Fairview, Quezon City | K91: 09052721048 | P91: =CONCATENATE(E91," ",F91," ",G91) -> BILLOSO AL ANTHONY CONSOLACION | Q91: =IFERROR(VLOOKUP(P90,[1]Disposition!$AB$9:$AC$495,2,0),"NO RECORD YET") -> Purok 3, Mninallo, Naguilian, Isabela
A92: 83 | B92: ITPMD (DPL) | C92: Male | D92: Pat | E92: DIONEDA | F92: KARL JOHN | G92: QUIRANTE | I92: IT Project PNCO | J92: Blk. 5 Lot. 36, Masigasig St., Capitol Parkland Subd. Brgy. 177, Caloocan, NCR | K92: 09676218602 | P92: =CONCATENATE(E92," ",F92," ",G92) -> DIONEDA KARL JOHN QUIRANTE | Q92: =IFERROR(VLOOKUP(P91,[1]Disposition!$AB$9:$AC$495,2,0),"NO RECORD YET") -> NO RECORD YET
A93: 84 | B93: ITPMD (DPL) | C93: Male | D93: Pat | E93: OBOG | F93: JOHN MARLO | G93: MAGRAMO | I93: IT Project PNCO | J93: 0550 Sanggumay, Looc, Calamba, Laguna | K93: 09161978384 | P93: =CONCATENATE(E93," ",F93," ",G93) -> OBOG JOHN MARLO MAGRAMO | Q93: =IFERROR(VLOOKUP(P92,[1]Disposition!$AB$9:$AC$495,2,0),"NO RECORD YET") -> NO RECORD YET
A94: 85 | B94: ITPMD (DPL) | C94: Male | D94: NUP | E94: BUENSUCESO | F94: NEIL PAUL | G94: BAUTISTA | I94: IT NUP (SG7) | J94: 16B Buenmar, Santolan, Pasig City | K94: 09178380513 | P94: =CONCATENATE(E94," ",F94," ",G94) -> BUENSUCESO NEIL PAUL BAUTISTA
A95: 86 | B95: ITPMD (DL) | C95: Female | D95: PCPT | E95: DIMASANGKAY | F95: SORAIYA | G95: MUSAID | I95: IT Project Officer | J95: Silver Homes Subdivision, Sadaan, Midsayap, Cotabato | P95: =CONCATENATE(E95," ",F95," ",G95) -> DIMASANGKAY SORAIYA MUSAID | Q95: =IFERROR(VLOOKUP(P94,[1]Disposition!$AB$9:$AC$495,2,0),"NO RECORD YET") -> NO RECORD YET
A96: 87 | B96: ITPMD (DC) | C96: Male | D96: PCPT | E96: BALLENAS | F96: ROBERTO | G96: ALPAS | H96: JR | I96: IT Project Officer | J96: Purok Masipag, Buayan, M'Lang, Cotabato, North Cotabato | K96: 09664625855 | P96: =CONCATENATE(E96," ",F96," ",G96) -> BALLENAS ROBERTO ALPAS | Q96: =IFERROR(VLOOKUP(P276,[1]Disposition!$AB$9:$AC$495,2,0),"NO RECORD YET") -> Pacifico, San isidro, Surigao Del Norte
A97: 88 | B97: ITPMD (DPCR) | C97: Female | D97: PCPT | E97: BUHAIN | F97: DOROTHY | G97: VILLALOBOS | I97: IT Project Officer | J97: 301 Masagana Subd., Gumamela St., San Francisco, Bulacan | K97: 09567595065 | P97: =CONCATENATE(E97," ",F97," ",G97) -> BUHAIN DOROTHY VILLALOBOS | Q97: =IFERROR(VLOOKUP(P96,[1]Disposition!$AB$9:$AC$495,2,0),"NO RECORD YET") -> Purok Masipag, Buayan, M'lang, Cotabato, North Cotabato
A98: 89 | B98: ITPMD (DPCR) | C98: Male | D98: PSMS | E98: SIBAYAN | F98: REYGIE | G98: PIAGAN | I98: IT Project PNCO | J98: Giron St., Brgy No. 2, Santa Joaquina, Laoag City, Ilocos Norte | K98: 09082302544 | P98: =CONCATENATE(E98," ",F98," ",G98) -> SIBAYAN REYGIE PIAGAN | Q98: =IFERROR(VLOOKUP(P97,[1]Disposition!$AB$9:$AC$495,2,0),"NO RECORD YET") -> 301 Masagana Subd., Gumamela St., San Francisco, Bulacan
A99: 90 | B99: ITPMD (DPCR) | C99: Male | D99: Pat | E99: CORDERO | F99: EARLBON | G99: JIMENEZ | I99: IT Project PNCO | J99: 1362 R.A Reyes Street, Tondo, Manila | K99: 09066901087 | P99: =CONCATENATE(E99," ",F99," ",G99) -> CORDERO EARLBON JIMENEZ | Q99: =IFERROR(VLOOKUP(P98,[1]Disposition!$AB$9:$AC$495,2,0),"NO RECORD YET") -> Giron St., BRGY NO. 2, Santa Joaquina, Laoag City, Ilocos Norte
A100: 91 | B100: ITPMD (DPCR) | C100: Male | D100: Pat | E100: ORLANDA | F100: BERNABE | G100: MACADANGDANG | H100: JR | I100: IT Project PNCO | J100: Sitio Malubec Curva, Pamplona, Cagayan | K100: 09975442501 | P100: =CONCATENATE(E100," ",F100," ",G100) -> ORLANDA BERNABE MACADANGDANG | Q100: =IFERROR(VLOOKUP(P99,[1]Disposition!$AB$9:$AC$495,2,0),"NO RECORD YET") -> NO RECORD YET
A101: 92 | B101: ITPMD (DET) | C101: Female | D101: PCPT | E101: NAGESNES -SUAYA | F101: RAFFY JANE | G101: ALIDAO | I101: IT Project Officer | J101: #25 C Purok 1, Lower Liwanag, Liwanag-Loakan, Baguio City, Benguet | K101: 09126980797 | P101: =CONCATENATE(E101," ",F101," ",G101) -> NAGESNES -SUAYA RAFFY JANE ALIDAO | Q101: =IFERROR(VLOOKUP(P100,[1]Disposition!$AB$9:$AC$495,2,0),"NO RECORD YET") -> NO RECORD YET
A102: 93 | B102: ITPMD (DET) | C102: Male | D102: PLT | E102: BANTIYAN | F102: JEFTER | G102: PAKID | I102: IT Project Officer | P102: =CONCATENATE(E102," ",F102," ",G102) -> BANTIYAN JEFTER PAKID
...

Sheet Alpha List
A1: Republic of the Philippines
A2: NATIONAL POLICE COMMISSION
A3: PHILIPPINE NATIONAL POLICE
A4: INFORMATION TECHNOLOGY MANAGEMENT SERVICE
A6: ALPHA LIST
A7: (As of September 7, 2026)
A8: NO. | B8: RANK | C8: STATUS | D8: BADGE NO/SG | E8: LAST NAME | F8: FIRST NAME | G8: MIDDLE NAME | H8: QUAL. | I8: AGE TO DATE | J8: Birthdate | K8: AGE OF SERVICE TO DATE | L8: DES (UP) | M8: PNCO | N8: NUP | O8: OFFICE/DIVISION | P8: DESIGNATION
A9: 1 | B9: PCPT | C9: PERM | D9: O-36665 | E9: ABANILLA | F9: FREDDIE | G9: BAUTISTA | I9: =DATEDIF(J9,DATE(2026,4,30),"y")&" years, "&DATEDIF(J9,DATE(2026,4,30),"ym")&" month(s), "&DATEDIF(J9,DATE(2026,4,30),"md")&" day(s)" -> 34 years, 7 month(s), 19 day(s) | J9: 33492 | K9: =DATEDIF(L9,DATE(2026,4,30),"y")&" years, "&DATEDIF(L9,DATE(2026,4,30),"ym")&" month(s), "&DATEDIF(L9,DATE(2026,4,30),"md")&" day(s)" -> 4 years, 5 month(s), 26 day(s) | L9: 44504 | M9: 41619 | O9: ITPMD (SAF) | P9: IT Project Officer
A10: 2 | B10: PCpl | C10: PERM | D10: 311622 | E10: ABDUHARI | F10: AL-MITRA | G10: PUNGUTAN | I10: =DATEDIF(J10,DATE(2026,4,30),"y")&" years, "&DATEDIF(J10,DATE(2026,4,30),"ym")&" month(s), "&DATEDIF(J10,DATE(2026,4,30),"md")&" day(s)" -> 38 years, 6 month(s), 6 day(s) | J10: 32074 | K10: =DATEDIF(L10,DATE(2026,4,30),"y")&" years, "&DATEDIF(L10,DATE(2026,4,30),"ym")&" month(s), "&DATEDIF(L10,DATE(2026,4,30),"md")&" day(s)" -> 8 years, 7 month(s), 14 day(s) | L10: 42994 | O10: ITPMD (PRO9) | P10: IT Project PNCO
A11: 3 | B11: PCPT | C11: PERM | D11: O-37277 | E11: ABO | F11: MARK JESSIE | G11: MELITANTE | I11: =DATEDIF(J11,DATE(2026,4,30),"y")&" years, "&DATEDIF(J11,DATE(2026,4,30),"ym")&" month(s), "&DATEDIF(J11,DATE(2026,4,30),"md")&" day(s)" -> 31 years, 1 month(s), 27 day(s) | J11: 34761 | K11: =DATEDIF(L11,DATE(2026,4,30),"y")&" years, "&DATEDIF(L11,DATE(2026,4,30),"ym")&" month(s), "&DATEDIF(L11,DATE(2026,4,30),"md")&" day(s)" -> 6 years, 6 month(s), 9 day(s) | L11: 43759 | O11: ITPMD (DIDM) | P11: IT Project Officer
A12: 4 | B12: Pat | C12: PERM | D12: 376371 | E12: ABONG | F12: MARK CLENTON | G12: (NO MIDDLE NAME) | I12: =DATEDIF(J12,DATE(2026,4,30),"y")&" years, "&DATEDIF(J12,DATE(2026,4,30),"ym")&" month(s), "&DATEDIF(J12,DATE(2026,4,30),"md")&" day(s)" -> 28 years, 3 month(s), 28 day(s) | J12: 35797 | K12: =DATEDIF(L12,DATE(2026,4,30),"y")&" years, "&DATEDIF(L12,DATE(2026,4,30),"ym")&" month(s), "&DATEDIF(L12,DATE(2026,4,30),"md")&" day(s)" -> 3 years, 4 month(s), 3 day(s) | L12: 44922 | O12: ITPMD (NIR) | P12: IT Project PNCO
A13: 5 | B13: Pat | C13: PERM | D13: 375615 | E13: ABRIAM | F13: ANNETH VALERIE | G13: MALNAT | I13: =DATEDIF(J13,DATE(2026,4,30),"y")&" years, "&DATEDIF(J13,DATE(2026,4,30),"ym")&" month(s), "&DATEDIF(J13,DATE(2026,4,30),"md")&" day(s)" -> 28 years, 4 month(s), 4 day(s) | J13: 35790 | K13: =DATEDIF(L13,DATE(2026,4,30),"y")&" years, "&DATEDIF(L13,DATE(2026,4,30),"ym")&" month(s), "&DATEDIF(L13,DATE(2026,4,30),"md")&" day(s)" -> 3 years, 5 month(s), 16 day(s) | L13: 44879 | O13: ITPMD (DIDM) | P13: IT Project PNCO
A14: 6 | B14: PCPT | C14: PERM | D14: O-36426 | E14: ABUAN | F14: DICKSON | G14: CLEMENTE | I14: =DATEDIF(J14,DATE(2026,4,30),"y")&" years, "&DATEDIF(J14,DATE(2026,4,30),"ym")&" month(s), "&DATEDIF(J14,DATE(2026,4,30),"md")&" day(s)" -> 34 years, 1 month(s), 13 day(s) | J14: 33680 | K14: =DATEDIF(L14,DATE(2026,4,30),"y")&" years, "&DATEDIF(L14,DATE(2026,4,30),"ym")&" month(s), "&DATEDIF(L14,DATE(2026,4,30),"md")&" day(s)" -> 4 years, 7 month(s), 14 day(s) | L14: 44455 | M14: 42562 | O14: ITPMD (PSPG) | P14: IT Project Officer
A15: 7 | B15: NUP | C15: PERM | D15: 7 | E15: ACORDA | F15: ELPIDIO | G15: PALARCA | I15: =DATEDIF(J15,DATE(2026,4,30),"y")&" years, "&DATEDIF(J15,DATE(2026,4,30),"ym")&" month(s), "&DATEDIF(J15,DATE(2026,4,30),"md")&" day(s)" -> 63 years, 2 month(s), 12 day(s) | J15: 23060 | K15: =DATEDIF(L15,DATE(2026,4,30),"y")&" years, "&DATEDIF(L15,DATE(2026,4,30),"ym")&" month(s), "&DATEDIF(L15,DATE(2026,4,30),"md")&" day(s)" -> 43 years, 11 month(s), 29 day(s) | L15: 30072 | O15: ICRMS, ARMD | P15: Liaison Officer (SG7)
A16: 8 | B16: NUP | C16: PERM | D16: 17 | E16: ACUESTA | F16: ANA JUNE | G16: FORRO | I16: =DATEDIF(J16,DATE(2026,4,30),"y")&" years, "&DATEDIF(J16,DATE(2026,4,30),"ym")&" month(s), "&DATEDIF(J16,DATE(2026,4,30),"md")&" day(s)" -> 37 years, 10 month(s), 19 day(s) | J16: 32305 | K16: =DATEDIF(L16,DATE(2026,4,30),"y")&" years, "&DATEDIF(L16,DATE(2026,4,30),"ym")&" month(s), "&DATEDIF(L16,DATE(2026,4,30),"md")&" day(s)" -> 14 years, 6 month(s), 16 day(s) | L16: 40830 | O16: SPIS, SMD | P16: Info Systems Researcher (SG17)
A17: 9 | B17: NUP | C17: PERM | D17: 15 | E17: ADULTA | F17: ARREN LEE | G17: CHACON | I17: =DATEDIF(J17,DATE(2026,4,30),"y")&" years, "&DATEDIF(J17,DATE(2026,4,30),"ym")&" month(s), "&DATEDIF(J17,DATE(2026,4,30),"md")&" day(s)" -> 40 years, 11 month(s), 20 day(s) | J17: 31177 | K17: =DATEDIF(L17,DATE(2026,4,30),"y")&" years, "&DATEDIF(L17,DATE(2026,4,30),"ym")&" month(s), "&DATEDIF(L17,DATE(2026,4,30),"md")&" day(s)" -> 12 years, 5 month(s), 9 day(s) | L17: 41599 | O17: HMS, ITSD | P17: Comp. Maintenance Tech. II (SG15)
A18: 10 | B18: PCpl | C18: PERM | D18: 196791 | E18: AGGARAO | F18: ALBERTO | G18: CALLANGAN | I18: =DATEDIF(J18,DATE(2026,4,30),"y")&" years, "&DATEDIF(J18,DATE(2026,4,30),"ym")&" month(s), "&DATEDIF(J18,DATE(2026,4,30),"md")&" day(s)" -> 42 years, 10 month(s), 13 day(s) | J18: 30484 | K18: =DATEDIF(L18,DATE(2026,4,30),"y")&" years, "&DATEDIF(L18,DATE(2026,4,30),"ym")&" month(s), "&DATEDIF(L18,DATE(2026,4,30),"md")&" day(s)" -> 16 years, 9 month(s), 29 day(s) | L18: 39995 | O18: OCS | P18: Action PNCO
A19: 11 | B19: Pat | C19: PERM | D19: 382567 | E19: AGOS | F19: CELSO | G19: TAPONG | H19: JR | I19: =DATEDIF(J19,DATE(2026,4,30),"y")&" years, "&DATEDIF(J19,DATE(2026,4,30),"ym")&" month(s), "&DATEDIF(J19,DATE(2026,4,30),"md")&" day(s)" -> 32 years, 11 month(s), 29 day(s) | J19: 34090 | K19: =DATEDIF(L19,DATE(2026,4,30),"y")&" years, "&DATEDIF(L19,DATE(2026,4,30),"ym")&" month(s), "&DATEDIF(L19,DATE(2026,4,30),"md")&" day(s)" -> 1 years, 4 month(s), 15 day(s) | L19: 45641 | N19: 44935 | O19: DMD/DO | P19: Duty PNCO/IT PNCO
A20: 12 | B20: NUP | C20: PERM | D20: 6 | E20: AGRIPA | F20: PAUL KENNETH | G20: DE GUZMAN | I20: =DATEDIF(J20,DATE(2026,4,30),"y")&" years, "&DATEDIF(J20,DATE(2026,4,30),"ym")&" month(s), "&DATEDIF(J20,DATE(2026,4,30),"md")&" day(s)" -> 21 years, 10 month(s), 8 day(s) | J20: 38160 | K20: =DATEDIF(L20,DATE(2026,4,30),"y")&" years, "&DATEDIF(L20,DATE(2026,4,30),"ym")&" month(s), "&DATEDIF(L20,DATE(2026,4,30),"md")&" day(s)" -> 0 years, 1 month(s), 5 day(s) | L20: 46106 | O20: AISS, SMD | P20: Comp Programmer (SG6) (ISSD)
A21: 13 | B21: NUP | C21: PERM | D21: 18 | E21: AGUHO | F21: MARK ANTHONY | G21: CAMBA | I21: =DATEDIF(J21,DATE(2026,4,30),"y")&" years, "&DATEDIF(J21,DATE(2026,4,30),"ym")&" month(s), "&DATEDIF(J21,DATE(2026,4,30),"md")&" day(s)" -> 34 years, 11 month(s), 8 day(s) | J21: 33380 | K21: =DATEDIF(L21,DATE(2026,4,30),"y")&" years, "&DATEDIF(L21,DATE(2026,4,30),"ym")&" month(s), "&DATEDIF(L21,DATE(2026,4,30),"md")&" day(s)" -> 13 years, 0 month(s), 5 day(s) | L21: 41389 | O21: QAS, SMD | P21: OIC, OISS (SG18)
A22: 14 | B22: Pat | C22: PERM | D22: 376372 | E22: AGUILANDO | F22: ADAMSON | G22: BANDONG | I22: =DATEDIF(J22,DATE(2026,4,30),"y")&" years, "&DATEDIF(J22,DATE(2026,4,30),"ym")&" month(s), "&DATEDIF(J22,DATE(2026,4,30),"md")&" day(s)" -> 30 years, 10 month(s), 24 day(s) | J22: 34856 | K22: =DATEDIF(L22,DATE(2026,4,30),"y")&" years, "&DATEDIF(L22,DATE(2026,4,30),"ym")&" month(s), "&DATEDIF(L22,DATE(2026,4,30),"md")&" day(s)" -> 3 years, 4 month(s), 3 day(s) | L22: 44922 | O22: ITPMD (EOD/K9) | P22: IT Project PNCO
A23: 15 | B23: NUP | C23: PERM | D23: 7 | E23: AGUILAR | F23: BERNARDINO | G23: SANTOS | I23: =DATEDIF(J23,DATE(2026,4,30),"y")&" years, "&DATEDIF(J23,DATE(2026,4,30),"ym")&" month(s), "&DATEDIF(J23,DATE(2026,4,30),"md")&" day(s)" -> 57 years, 8 month(s), 16 day(s) | J23: 25064 | K23: =DATEDIF(L23,DATE(2026,4,30),"y")&" years, "&DATEDIF(L23,DATE(2026,4,30),"ym")&" month(s), "&DATEDIF(L23,DATE(2026,4,30),"md")&" day(s)" -> 96 years, 3 month(s), 14 day(s) | L23: 10974 | O23: ITPMD (PPDC) | P23: IT NUP (SG7)
A24: 16 | B24: PSSg | C24: PERM | D24: 260764 | E24: AGUILAR | F24: JAMES BENEDICT | G24: GALVEZ | I24: =DATEDIF(J24,DATE(2026,4,30),"y")&" years, "&DATEDIF(J24,DATE(2026,4,30),"ym")&" month(s), "&DATEDIF(J24,DATE(2026,4,30),"md")&" day(s)" -> 41 years, 8 month(s), 2 day(s) | J24: 30922 | K24: =DATEDIF(L24,DATE(2026,4,30),"y")&" years, "&DATEDIF(L24,DATE(2026,4,30),"ym")&" month(s), "&DATEDIF(L24,DATE(2026,4,30),"md")&" day(s)" -> 11 years, 4 month(s), 1 day(s) | L24: 42002 | O24: LS, ARMD | P24: RSPNCO
A25: 17 | B25: PLTCOL | C25: PERM | D25: O-22470 | E25: AGUS | F25: CARCIOLO | G25: CAJANDAB | H25: JR | I25: =DATEDIF(J25,DATE(2026,4,30),"y")&" years, "&DATEDIF(J25,DATE(2026,4,30),"ym")&" month(s), "&DATEDIF(J25,DATE(2026,4,30),"md")&" day(s)" -> 52 years, 2 month(s), 2 day(s) | J25: 27088 | K25: =DATEDIF(L25,DATE(2026,4,30),"y")&" years, "&DATEDIF(L25,DATE(2026,4,30),"ym")&" month(s), "&DATEDIF(L25,DATE(2026,4,30),"md")&" day(s)" -> 22 years, 11 month(s), 14 day(s) | L25: 37757 | O25: ITPMD (NCRPO/RICTMD NCRPO) | P25: IT Project Officer/ Asst Chief, RICTMD
A26: 18 | B26: PCPT | C26: PERM | D26: O-36666 | E26: AGUSTIN | F26: RIZELLE | G26: INALDO | I26: =DATEDIF(J26,DATE(2026,4,30),"y")&" years, "&DATEDIF(J26,DATE(2026,4,30),"ym")&" month(s), "&DATEDIF(J26,DATE(2026,4,30),"md")&" day(s)" -> 41 years, 10 month(s), 11 day(s) | J26: 30852 | K26: =DATEDIF(L26,DATE(2026,4,30),"y")&" years, "&DATEDIF(L26,DATE(2026,4,30),"ym")&" month(s), "&DATEDIF(L26,DATE(2026,4,30),"md")&" day(s)" -> 4 years, 5 month(s), 26 day(s) | L26: 44504 | M26: 38297 | O26: TSS, PTD | P26: Chief, TSS/Planning Officer
A27: 19 | B27: Pat | C27: PERM | D27: 339461 | E27: ALABA | F27: NIEL | G27: CAGAMPANG | I27: =DATEDIF(J27,DATE(2026,4,30),"y")&" years, "&DATEDIF(J27,DATE(2026,4,30),"ym")&" month(s), "&DATEDIF(J27,DATE(2026,4,30),"md")&" day(s)" -> 29 years, 6 month(s), 16 day(s) | J27: 35352 | K27: =DATEDIF(L27,DATE(2026,4,30),"y")&" years, "&DATEDIF(L27,DATE(2026,4,30),"ym")&" month(s), "&DATEDIF(L27,DATE(2026,4,30),"md")&" day(s)" -> 6 years, 6 month(s), 9 day(s) | L27: 43759 | O27: ITPMD (PRO13) | P27: IT Project PNCO
A28: 20 | B28: Pat | C28: PERM | D28: 339462 | E28: ALAWI | F28: NABIL | G28: HAJINULLA | I28: =DATEDIF(J28,DATE(2026,4,30),"y")&" years, "&DATEDIF(J28,DATE(2026,4,30),"ym")&" month(s), "&DATEDIF(J28,DATE(2026,4,30),"md")&" day(s)" -> 30 years, 7 month(s), 11 day(s) | J28: 34961 | K28: =DATEDIF(L28,DATE(2026,4,30),"y")&" years, "&DATEDIF(L28,DATE(2026,4,30),"ym")&" month(s), "&DATEDIF(L28,DATE(2026,4,30),"md")&" day(s)" -> 6 years, 6 month(s), 9 day(s) | L28: 43759 | O28: ITPMD (PRO9) | P28: IT Project PNCO
A29: 21 | B29: NUP | C29: PERM | D29: 7 | E29: ALCANTARA | F29: JHINNA-LOU | G29: SAN ESTEBAN | I29: =DATEDIF(J29,DATE(2026,4,30),"y")&" years, "&DATEDIF(J29,DATE(2026,4,30),"ym")&" month(s), "&DATEDIF(J29,DATE(2026,4,30),"md")&" day(s)" -> 28 years, 8 month(s), 21 day(s) | J29: 35651 | K29: =DATEDIF(L29,DATE(2026,4,30),"y")&" years, "&DATEDIF(L29,DATE(2026,4,30),"ym")&" month(s), "&DATEDIF(L29,DATE(2026,4,30),"md")&" day(s)" -> 3 years, 2 month(s), 16 day(s) | L29: 44971 | O29: BFS, ARMD | P29: Action NUP (SG6)
A30: 22 | B30: NUP | C30: PERM | D30: 6 | E30: ALDE | F30: MILA | G30: BERNADAS | I30: =DATEDIF(J30,DATE(2026,4,30),"y")&" years, "&DATEDIF(J30,DATE(2026,4,30),"ym")&" month(s), "&DATEDIF(J30,DATE(2026,4,30),"md")&" day(s)" -> 41 years, 7 month(s), 14 day(s) | J30: 30941 | K30: =DATEDIF(L30,DATE(2026,4,30),"y")&" years, "&DATEDIF(L30,DATE(2026,4,30),"ym")&" month(s), "&DATEDIF(L30,DATE(2026,4,30),"md")&" day(s)" -> 1 years, 1 month(s), 13 day(s) | L30: 45733 | O30: ITSD | P30: Administrative Aide VI (SG6)
A31: 23 | B31: NUP | C31: PERM | D31: 7 | E31: ALEGRE | F31: JAYBEE | G31: BALASE | I31: =DATEDIF(J31,DATE(2026,4,30),"y")&" years, "&DATEDIF(J31,DATE(2026,4,30),"ym")&" month(s), "&DATEDIF(J31,DATE(2026,4,30),"md")&" day(s)" -> 32 years, 3 month(s), 15 day(s) | J31: 34349 | K31: =DATEDIF(L31,DATE(2026,4,30),"y")&" years, "&DATEDIF(L31,DATE(2026,4,30),"ym")&" month(s), "&DATEDIF(L31,DATE(2026,4,30),"md")&" day(s)" -> 3 years, 3 month(s), 21 day(s) | L31: 44935 | O31: ITSD/IAS | P31: Administrative Asst I/ Technical Assistance (SG7)
A32: 24 | B32: PCPT | C32: PERM | D32: O-36719 | E32: ALEGRE | F32: DINA | G32: FERMANTEZ | I32: =DATEDIF(J32,DATE(2026,4,30),"y")&" years, "&DATEDIF(J32,DATE(2026,4,30),"ym")&" month(s), "&DATEDIF(J32,DATE(2026,4,30),"md")&" day(s)" -> 34 years, 4 month(s), 15 day(s) | J32: 33587 | K32: =DATEDIF(L32,DATE(2026,4,30),"y")&" years, "&DATEDIF(L32,DATE(2026,4,30),"ym")&" month(s), "&DATEDIF(L32,DATE(2026,4,30),"md")&" day(s)" -> 4 years, 5 month(s), 26 day(s) | L32: 44504 | M32: 43759 | O32: PHAS(DICTM) | P32: IT Officer
A33: 25 | B33: NUP | C33: PERM | D33: 7 | E33: ALFABETO | F33: LOUIE VAN | G33: ANASTACIO | I33: =DATEDIF(J33,DATE(2026,4,30),"y")&" years, "&DATEDIF(J33,DATE(2026,4,30),"ym")&" month(s), "&DATEDIF(J33,DATE(2026,4,30),"md")&" day(s)" -> 36 years, 11 month(s), 9 day(s) | J33: 32649 | K33: =DATEDIF(L33,DATE(2026,4,30),"y")&" years, "&DATEDIF(L33,DATE(2026,4,30),"ym")&" month(s), "&DATEDIF(L33,DATE(2026,4,30),"md")&" day(s)" -> 9 years, 11 month(s), 20 day(s) | L33: 42500 | O33: ISCS, ISSD | P33: Administrative Assistant I (SG7)
A34: 26 | B34: NUP | C34: PERM | D34: 9 | E34: ALFONSO | F34: IRANIE | G34: EMPENO | I34: =DATEDIF(J34,DATE(2026,4,30),"y")&" years, "&DATEDIF(J34,DATE(2026,4,30),"ym")&" month(s), "&DATEDIF(J34,DATE(2026,4,30),"md")&" day(s)" -> 59 years, 2 month(s), 15 day(s) | J34: 24518 | K34: =DATEDIF(L34,DATE(2026,4,30),"y")&" years, "&DATEDIF(L34,DATE(2026,4,30),"ym")&" month(s), "&DATEDIF(L34,DATE(2026,4,30),"md")&" day(s)" -> 34 years, 3 month(s), 29 day(s) | L34: 33604 | O34: ITSD/ DICTM | P34: Administrative Assistant III (SG9) (ITSD)
A35: 27 | B35: PCOL | C35: PERM | D35: O-12566 | E35: ALI | F35: AMIR HASSAN | G35: RAMOS | I35: =DATEDIF(J35,DATE(2026,4,30),"y")&" years, "&DATEDIF(J35,DATE(2026,4,30),"ym")&" month(s), "&DATEDIF(J35,DATE(2026,4,30),"md")&" day(s)" -> 46 years, 7 month(s), 2 day(s) | J35: 29126 | K35: =DATEDIF(L35,DATE(2026,4,30),"y")&" years, "&DATEDIF(L35,DATE(2026,4,30),"ym")&" month(s), "&DATEDIF(L35,DATE(2026,4,30),"md")&" day(s)" -> 25 years, 5 month(s), 3 day(s) | L35: 36857 | O35: DMD | P35: Chief, DMD
A36: 28 | B36: NUP | C36: PERM | D36: 19 | E36: ALI | F36: HUSSEIN | G36: RAMOS | I36: =DATEDIF(J36,DATE(2026,4,30),"y")&" years, "&DATEDIF(J36,DATE(2026,4,30),"ym")&" month(s), "&DATEDIF(J36,DATE(2026,4,30),"md")&" day(s)" -> 43 years, 6 month(s), 19 day(s) | J36: 30235 | K36: =DATEDIF(L36,DATE(2026,4,30),"y")&" years, "&DATEDIF(L36,DATE(2026,4,30),"ym")&" month(s), "&DATEDIF(L36,DATE(2026,4,30),"md")&" day(s)" -> 15 years, 1 month(s), 6 day(s) | L36: 40626 | O36: HMS, ITSD | P36: Chief, HMS/ITO I (SG19)
A37: 29 | B37: PCOL | C37: PERM | D37: O-13539 | E37: ALI | F37: SHIRLEY MAE | G37: SALVADOR | I37: =DATEDIF(J37,DATE(2026,4,30),"y")&" years, "&DATEDIF(J37,DATE(2026,4,30),"ym")&" month(s), "&DATEDIF(J37,DATE(2026,4,30),"md")&" day(s)" -> 47 years, 7 month(s), 11 day(s) | J37: 28752 | K37: =DATEDIF(L37,DATE(2026,4,30),"y")&" years, "&DATEDIF(L37,DATE(2026,4,30),"ym")&" month(s), "&DATEDIF(L37,DATE(2026,4,30),"md")&" day(s)" -> 24 years, 5 month(s), 24 day(s) | L37: 37201 | O37: PTD | P37: Chief, PTD
A38: 30 | B38: PCPT | C38: PERM | D38: O-36427 | E38: ALIMAMBO | F38: JICK | G38: BONUAN | I38: =DATEDIF(J38,DATE(2026,4,30),"y")&" years, "&DATEDIF(J38,DATE(2026,4,30),"ym")&" month(s), "&DATEDIF(J38,DATE(2026,4,30),"md")&" day(s)" -> 34 years, 7 month(s), 17 day(s) | J38: 33494 | K38: =DATEDIF(L38,DATE(2026,4,30),"y")&" years, "&DATEDIF(L38,DATE(2026,4,30),"ym")&" month(s), "&DATEDIF(L38,DATE(2026,4,30),"md")&" day(s)" -> 4 years, 7 month(s), 15 day(s) | L38: 44454 | M38: 42562 | O38: ITPMD (PIO) | P38: IT Project Officer
A39: 31 | B39: NUP | C39: PERM | D39: 12 | E39: ALMACHAR | F39: ARLENE | G39: ACIERTO | I39: =DATEDIF(J39,DATE(2026,4,30),"y")&" years, "&DATEDIF(J39,DATE(2026,4,30),"ym")&" month(s), "&DATEDIF(J39,DATE(2026,4,30),"md")&" day(s)" -> 53 years, 7 month(s), 3 day(s) | J39: 26569 | K39: =DATEDIF(L39,DATE(2026,4,30),"y")&" years, "&DATEDIF(L39,DATE(2026,4,30),"ym")&" month(s), "&DATEDIF(L39,DATE(2026,4,30),"md")&" day(s)" -> 28 years, 1 month(s), 14 day(s) | L39: 35870 | O39: AISS, SMD | P39: ISA/ISR (SG12)
A40: 32 | B40: NUP | C40: PERM | D40: 7 | E40: ALMADEN | F40: GILBERT | G40: CABACANG | I40: =DATEDIF(J40,DATE(2026,4,30),"y")&" years, "&DATEDIF(J40,DATE(2026,4,30),"ym")&" month(s), "&DATEDIF(J40,DATE(2026,4,30),"md")&" day(s)" -> 53 years, 8 month(s), 6 day(s) | J40: 26535 | K40: =DATEDIF(L40,DATE(2026,4,30),"y")&" years, "&DATEDIF(L40,DATE(2026,4,30),"ym")&" month(s), "&DATEDIF(L40,DATE(2026,4,30),"md")&" day(s)" -> 9 years, 6 month(s), 23 day(s) | L40: 42650 | O40: DPS, DMD | P40: Verifier/Encoder (SG7)
A41: 33 | B41: NUP | C41: PERM | D41: 7 | E41: ALVAREZ | F41: PAMELA | G41: CEREZO | I41: =DATEDIF(J41,DATE(2026,4,30),"y")&" years, "&DATEDIF(J41,DATE(2026,4,30),"ym")&" month(s), "&DATEDIF(J41,DATE(2026,4,30),"md")&" day(s)" -> 52 years, 3 month(s), 3 day(s) | J41: 27056 | K41: =DATEDIF(L41,DATE(2026,4,30),"y")&" years, "&DATEDIF(L41,DATE(2026,4,30),"ym")&" month(s), "&DATEDIF(L41,DATE(2026,4,30),"md")&" day(s)" -> 14 years, 5 month(s), 1 day(s) | L41: 40876 | O41: PIO | P41: PIO/PCR Staff (SG7)
A42: 34 | B42: PMAJ | C42: PERM | D42: O-29043 | E42: AMIT | F42: ARIEL | G42: DE GUZMAN | I42: =DATEDIF(J42,DATE(2026,4,30),"y")&" years, "&DATEDIF(J42,DATE(2026,4,30),"ym")&" month(s), "&DATEDIF(J42,DATE(2026,4,30),"md")&" day(s)" -> 51 years, 1 month(s), 19 day(s) | J42: 27464 | K42: =DATEDIF(L42,DATE(2026,4,30),"y")&" years, "&DATEDIF(L42,DATE(2026,4,30),"ym")&" month(s), "&DATEDIF(L42,DATE(2026,4,30),"md")&" day(s)" -> 8 years, 2 month(s), 14 day(s) | L42: 43147 | N42: 38604 | O42: ITPMD (OTCDS) | P42: IT Project Officer
A43: 35 | B43: PLTCOL | C43: PERM | D43: O-16853 | E43: AN | F43: SANTI RAYMUND | G43: NEVADO | I43: =DATEDIF(J43,DATE(2026,4,30),"y")&" years, "&DATEDIF(J43,DATE(2026,4,30),"ym")&" month(s), "&DATEDIF(J43,DATE(2026,4,30),"md")&" day(s)" -> 47 years, 9 month(s), 20 day(s) | J43: 28681 | K43: =DATEDIF(L43,DATE(2026,4,30),"y")&" years, "&DATEDIF(L43,DATE(2026,4,30),"ym")&" month(s), "&DATEDIF(L43,DATE(2026,4,30),"md")&" day(s)" -> 21 years, 7 month(s), 24 day(s) | L43: 38236 | O43: ITPMD (PRO4B) | P43: IT Project Officer
A44: 36 | B44: Pat | C44: PERM | D44: 376373 | E44: ANABON | F44: LEVI | G44: ABAGGUE | I44: =DATEDIF(J44,DATE(2026,4,30),"y")&" years, "&DATEDIF(J44,DATE(2026,4,30),"ym")&" month(s), "&DATEDIF(J44,DATE(2026,4,30),"md")&" day(s)" -> 28 years, 8 month(s), 6 day(s) | J44: 35666 | K44: =DATEDIF(L44,DATE(2026,4,30),"y")&" years, "&DATEDIF(L44,DATE(2026,4,30),"ym")&" month(s), "&DATEDIF(L44,DATE(2026,4,30),"md")&" day(s)" -> 3 years, 4 month(s), 3 day(s) | L44: 44922 | O44: ITPMD (PNP RSS) | P44: IT Project PNCO
A45: 37 | B45: NUP | C45: PERM | D45: 11 | E45: ANARNA | F45: DARIA | G45: CALAMAYA | I45: =DATEDIF(J45,DATE(2026,4,30),"y")&" years, "&DATEDIF(J45,DATE(2026,4,30),"ym")&" month(s), "&DATEDIF(J45,DATE(2026,4,30),"md")&" day(s)" -> 49 years, 6 month(s), 5 day(s) | J45: 28058 | K45: =DATEDIF(L45,DATE(2026,4,30),"y")&" years, "&DATEDIF(L45,DATE(2026,4,30),"ym")&" month(s), "&DATEDIF(L45,DATE(2026,4,30),"md")&" day(s)" -> 14 years, 2 month(s), 7 day(s) | L45: 40962 | O45: PS, ARMD | P45: Personnel Staff/PAIS Encoder
A46: 38 | B46: Pat | C46: PERM | D46: 376374 | E46: ANCHOVAS | F46: ESHIER | G46: QUIÑONES | I46: =DATEDIF(J46,DATE(2026,4,30),"y")&" years, "&DATEDIF(J46,DATE(2026,4,30),"ym")&" month(s), "&DATEDIF(J46,DATE(2026,4,30),"md")&" day(s)" -> 28 years, 2 month(s), 10 day(s) | J46: 35846 | K46: =DATEDIF(L46,DATE(2026,4,30),"y")&" years, "&DATEDIF(L46,DATE(2026,4,30),"ym")&" month(s), "&DATEDIF(L46,DATE(2026,4,30),"md")&" day(s)" -> 3 years, 4 month(s), 3 day(s) | L46: 44922 | O46: ITPMD (PRO8) | P46: IT Project PNCO
A47: 39 | B47: PMAJ | C47: PERM | D47: O-29033 | E47: ANDANAR | F47: JON JASON | G47: GORGOLON | I47: =DATEDIF(J47,DATE(2026,4,30),"y")&" years, "&DATEDIF(J47,DATE(2026,4,30),"ym")&" month(s), "&DATEDIF(J47,DATE(2026,4,30),"md")&" day(s)" -> 45 years, 6 month(s), 1 day(s) | J47: 29523 | K47: =DATEDIF(L47,DATE(2026,4,30),"y")&" years, "&DATEDIF(L47,DATE(2026,4,30),"ym")&" month(s), "&DATEDIF(L47,DATE(2026,4,30),"md")&" day(s)" -> 8 years, 2 month(s), 14 day(s) | L47: 43147 | M47: 37830 | O47: ITPMD (HS)/SMD | P47: IT Project Officer/Action PCO
A48: 40 | B48: PLTCOL | C48: PERM | D48: O-16848 | E48: ANDRES | F48: JOSE WILSON | G48: HACIÑAS | I48: =DATEDIF(J48,DATE(2026,4,30),"y")&" years, "&DATEDIF(J48,DATE(2026,4,30),"ym")&" month(s), "&DATEDIF(J48,DATE(2026,4,30),"md")&" day(s)" -> 48 years, 0 month(s), 30 day(s) | J48: 28580 | K48: =DATEDIF(L48,DATE(2026,4,30),"y")&" years, "&DATEDIF(L48,DATE(2026,4,30),"ym")&" month(s), "&DATEDIF(L48,DATE(2026,4,30),"md")&" day(s)" -> 21 years, 7 month(s), 24 day(s) | L48: 38236 | M48: 37757 | O48: PCC-SR, ITSD/PRO9 | P48: Supervising Officer/IT Project Officer
A49: 41 | B49: PCpl | C49: PERM | D49: 311625 | E49: ANGELES | F49: MARK DANIEL | G49: MAMITAG | I49: =DATEDIF(J49,DATE(2026,4,30),"y")&" years, "&DATEDIF(J49,DATE(2026,4,30),"ym")&" month(s), "&DATEDIF(J49,DATE(2026,4,30),"md")&" day(s)" -> 33 years, 6 month(s), 24 day(s) | J49: 33883 | K49: =DATEDIF(L49,DATE(2026,4,30),"y")&" years, "&DATEDIF(L49,DATE(2026,4,30),"ym")&" month(s), "&DATEDIF(L49,DATE(2026,4,30),"md")&" day(s)" -> 8 years, 7 month(s), 14 day(s) | L49: 42994 | O49: ITPMD (PRO11) | P49: IT Project PNCO
A50: 42 | B50: Pat | C50: PERM | D50: 376375 | E50: ANGLIGEN | F50: MARLON | G50: PINANGI | I50: =DATEDIF(J50,DATE(2026,4,30),"y")&" years, "&DATEDIF(J50,DATE(2026,4,30),"ym")&" month(s), "&DATEDIF(J50,DATE(2026,4,30),"md")&" day(s)" -> 29 years, 8 month(s), 15 day(s) | J50: 35292 | K50: =DATEDIF(L50,DATE(2026,4,30),"y")&" years, "&DATEDIF(L50,DATE(2026,4,30),"ym")&" month(s), "&DATEDIF(L50,DATE(2026,4,30),"md")&" day(s)" -> 3 years, 4 month(s), 3 day(s) | L50: 44922 | O50: PHAS (PNPA) | P50: IT PNCO
A51: 43 | B51: PCPT | C51: PERM | D51: O-36667 | E51: ANISCO | F51: ARCHIE | G51: STO.DOMINGO | I51: =DATEDIF(J51,DATE(2026,4,30),"y")&" years, "&DATEDIF(J51,DATE(2026,4,30),"ym")&" month(s), "&DATEDIF(J51,DATE(2026,4,30),"md")&" day(s)" -> 46 years, 10 month(s), 4 day(s) | J51: 29032 | K51: =DATEDIF(L51,DATE(2026,4,30),"y")&" years, "&DATEDIF(L51,DATE(2026,4,30),"ym")&" month(s), "&DATEDIF(L51,DATE(2026,4,30),"md")&" day(s)" -> 4 years, 5 month(s), 26 day(s) | L51: 44504 | M51: 39995 | O51: ITPMD (MG) | P51: IT Project Officer
A52: 44 | B52: PLTCOL | C52: PERM | D52: O-20596 | E52: ANUNCIO | F52: ALEJANDER | G52: TALAMPAS | I52: =DATEDIF(J52,DATE(2026,4,30),"y")&" years, "&DATEDIF(J52,DATE(2026,4,30),"ym")&" month(s), "&DATEDIF(J52,DATE(2026,4,30),"md")&" day(s)" -> 51 years, 11 month(s), 15 day(s) | J52: 27164 | K52: =DATEDIF(L52,DATE(2026,4,30),"y")&" years, "&DATEDIF(L52,DATE(2026,4,30),"ym")&" month(s), "&DATEDIF(L52,DATE(2026,4,30),"md")&" day(s)" -> 17 years, 7 month(s), 29 day(s) | L52: 39692 | N52: 38913 | O52: PHAS, ARMD | P52: Schooling (PSOSEC)
A53: 45 | B53: PCPT | C53: PERM | D53: O-31679 | E53: ANURAN | F53: ADRIAN | G53: MIRASOL | I53: =DATEDIF(J53,DATE(2026,4,30),"y")&" years, "&DATEDIF(J53,DATE(2026,4,30),"ym")&" month(s), "&DATEDIF(J53,DATE(2026,4,30),"md")&" day(s)" -> 40 years, 3 month(s), 6 day(s) | J53: 31436 | K53: =DATEDIF(L53,DATE(2026,4,30),"y")&" years, "&DATEDIF(L53,DATE(2026,4,30),"ym")&" month(s), "&DATEDIF(L53,DATE(2026,4,30),"md")&" day(s)" -> 7 years, 1 month(s), 12 day(s) | L53: 43542 | M53: 39995 | O53: PHAS (CICC) | P53: IT Project Officer
A54: 46 | B54: Pat | C54: PERM | D54: 376376 | E54: APACIBLE | F54: KIM SANDELL | G54: CAMO | I54: =DATEDIF(J54,DATE(2026,4,30),"y")&" years, "&DATEDIF(J54,DATE(2026,4,30),"ym")&" month(s), "&DATEDIF(J54,DATE(2026,4,30),"md")&" day(s)" -> 28 years, 0 month(s), 21 day(s) | J54: 35894 | K54: =DATEDIF(L54,DATE(2026,4,30),"y")&" years, "&DATEDIF(L54,DATE(2026,4,30),"ym")&" month(s), "&DATEDIF(L54,DATE(2026,4,30),"md")&" day(s)" -> 3 years, 4 month(s), 3 day(s) | L54: 44922 | O54: PHAS (PNPA) | P54: IT PNCO
A55: 47 | B55: Pat | C55: PERM | D55: 376377 | E55: APALLA | F55: RUEL | G55: AMPIS | I55: =DATEDIF(J55,DATE(2026,4,30),"y")&" years, "&DATEDIF(J55,DATE(2026,4,30),"ym")&" month(s), "&DATEDIF(J55,DATE(2026,4,30),"md")&" day(s)" -> 28 years, 9 month(s), 16 day(s) | J55: 35625 | K55: =DATEDIF(L55,DATE(2026,4,30),"y")&" years, "&DATEDIF(L55,DATE(2026,4,30),"ym")&" month(s), "&DATEDIF(L55,DATE(2026,4,30),"md")&" day(s)" -> 3 years, 4 month(s), 3 day(s) | L55: 44922 | O55: PS, ARMD | P55: Action PNCO/PAIS Encoder/Focal Person/OJT Coordinator/Alternate Secretary
A56: 48 | B56: PLTCOL | C56: PERM | D56: O-16857 | E56: AQUINO | F56: JOHANNES GOLD | G56: LUCERO | I56: =DATEDIF(J56,DATE(2026,4,30),"y")&" years, "&DATEDIF(J56,DATE(2026,4,30),"ym")&" month(s), "&DATEDIF(J56,DATE(2026,4,30),"md")&" day(s)" -> 46 years, 3 month(s), 25 day(s) | J56: 29225 | K56: =DATEDIF(L56,DATE(2026,4,30),"y")&" years, "&DATEDIF(L56,DATE(2026,4,30),"ym")&" month(s), "&DATEDIF(L56,DATE(2026,4,30),"md")&" day(s)" -> 21 years, 7 month(s), 14 day(s) | L56: 38246 | O56: LS/IHSS/PRO12 | P56: C, LS/C,IHSS/Asst. C, BFS/ITPO
A57: 49 | B57: NUP | C57: PERM | D57: 4 | E57: AQUINO | F57: ROGELIO | G57: PATIÑO | I57: =DATEDIF(J57,DATE(2026,4,30),"y")&" years, "&DATEDIF(J57,DATE(2026,4,30),"ym")&" month(s), "&DATEDIF(J57,DATE(2026,4,30),"md")&" day(s)" -> 55 years, 5 month(s), 3 day(s) | J57: 25899 | K57: =DATEDIF(L57,DATE(2026,4,30),"y")&" years, "&DATEDIF(L57,DATE(2026,4,30),"ym")&" month(s), "&DATEDIF(L57,DATE(2026,4,30),"md")&" day(s)" -> 15 years, 1 month(s), 6 day(s) | L57: 40626 | O57: IHSS, ARMD | P57: Reproduction Machine Operator (SG4)
A58: 50 | B58: PCpl | C58: PERM | D58: 311626 | E58: ARCANGEL | F58: OLIVER | G58: GARCIA | I58: =DATEDIF(J58,DATE(2026,4,30),"y")&" years, "&DATEDIF(J58,DATE(2026,4,30),"ym")&" month(s), "&DATEDIF(J58,DATE(2026,4,30),"md")&" day(s)" -> 39 years, 3 month(s), 10 day(s) | J58: 31797 | K58: =DATEDIF(L58,DATE(2026,4,30),"y")&" years, "&DATEDIF(L58,DATE(2026,4,30),"ym")&" month(s), "&DATEDIF(L58,DATE(2026,4,30),"md")&" day(s)" -> 8 years, 7 month(s), 14 day(s) | L58: 42994 | O58: LS, ARMD | P58: Action PNCO
A59: 51 | B59: NUP | C59: PERM | D59: 15 | E59: ARCE | F59: MARIE FRANCISSE THERESE | G59: ARMAMENTO | I59: =DATEDIF(J59,DATE(2026,4,30),"y")&" years, "&DATEDIF(J59,DATE(2026,4,30),"ym")&" month(s), "&DATEDIF(J59,DATE(2026,4,30),"md")&" day(s)" -> 44 years, 10 month(s), 5 day(s) | J59: 29762 | K59: =DATEDIF(L59,DATE(2026,4,30),"y")&" years, "&DATEDIF(L59,DATE(2026,4,30),"ym")&" month(s), "&DATEDIF(L59,DATE(2026,4,30),"md")&" day(s)" -> 10 years, 1 month(s), 20 day(s) | L59: 42439 | O59: SPIS, SMD | P59: Comp. Programmer (SG11)
A60: 52 | B60: Pat | C60: PERM | D60: 375616 | E60: AREOLA | F60: MARJORIE | G60: BALZA | I60: =DATEDIF(J60,DATE(2026,4,30),"y")&" years, "&DATEDIF(J60,DATE(2026,4,30),"ym")&" month(s), "&DATEDIF(J60,DATE(2026,4,30),"md")&" day(s)" -> 33 years, 9 month(s), 27 day(s) | J60: 33788 | K60: =DATEDIF(L60,DATE(2026,4,30),"y")&" years, "&DATEDIF(L60,DATE(2026,4,30),"ym")&" month(s), "&DATEDIF(L60,DATE(2026,4,30),"md")&" day(s)" -> 3 years, 5 month(s), 16 day(s) | L60: 44879 | O60: ITPMD (PRO1) | P60: IT Project PNCO
A61: 53 | B61: PCPT | C61: PERM | D61: O-37278 | E61: AREVALO | F61: RALPH LYNDON | G61: RESUELLO | I61: =DATEDIF(J61,DATE(2026,4,30),"y")&" years, "&DATEDIF(J61,DATE(2026,4,30),"ym")&" month(s), "&DATEDIF(J61,DATE(2026,4,30),"md")&" day(s)" -> 35 years, 8 month(s), 7 day(s) | J61: 33108 | K61: =DATEDIF(L61,DATE(2026,4,30),"y")&" years, "&DATEDIF(L61,DATE(2026,4,30),"ym")&" month(s), "&DATEDIF(L61,DATE(2026,4,30),"md")&" day(s)" -> 10 years, 8 month(s), 2 day(s) | L61: 42244 | O61: ITSD | P61: Duty PCO
A62: 54 | B62: Pat | C62: PERM | D62: 376378 | E62: ARGAWANON | F62: JUNREY | G62: BOOC | I62: =DATEDIF(J62,DATE(2026,4,30),"y")&" years, "&DATEDIF(J62,DATE(2026,4,30),"ym")&" month(s), "&DATEDIF(J62,DATE(2026,4,30),"md")&" day(s)" -> 30 years, 2 month(s), 19 day(s) | J62: 35106 | K62: =DATEDIF(L62,DATE(2026,4,30),"y")&" years, "&DATEDIF(L62,DATE(2026,4,30),"ym")&" month(s), "&DATEDIF(L62,DATE(2026,4,30),"md")&" day(s)" -> 3 years, 4 month(s), 3 day(s) | L62: 44922 | O62: ITPMD (DO) | P62: IT Project PNCO
A63: 55 | B63: NUP | C63: PERM | D63: 11 | E63: ARGETE | F63: GRACIANO | G63: ROSILLO | I63: =DATEDIF(J63,DATE(2026,4,30),"y")&" years, "&DATEDIF(J63,DATE(2026,4,30),"ym")&" month(s), "&DATEDIF(J63,DATE(2026,4,30),"md")&" day(s)" -> 38 years, 7 month(s), 29 day(s) | J63: 32021 | K63: =DATEDIF(L63,DATE(2026,4,30),"y")&" years, "&DATEDIF(L63,DATE(2026,4,30),"ym")&" month(s), "&DATEDIF(L63,DATE(2026,4,30),"md")&" day(s)" -> 15 years, 1 month(s), 6 day(s) | L63: 40626 | O63: PRS, PTD | P63: Planning Officer (SG10)
A64: 56 | B64: PLT | C64: PERM | D64: O-37877 | E64: ARIAS | F64: AUDEN | G64: GOZUM | I64: =DATEDIF(J64,DATE(2026,4,30),"y")&" years, "&DATEDIF(J64,DATE(2026,4,30),"ym")&" month(s), "&DATEDIF(J64,DATE(2026,4,30),"md")&" day(s)" -> 37 years, 1 month(s), 15 day(s) | J64: 32582 | K64: =DATEDIF(L64,DATE(2026,4,30),"y")&" years, "&DATEDIF(L64,DATE(2026,4,30),"ym")&" month(s), "&DATEDIF(L64,DATE(2026,4,30),"md")&" day(s)" -> 8 years, 7 month(s), 14 day(s) | L64: 42994 | O64: TS, PTD | P64: OIC, Training Section/Training Officer
A65: 57 | B65: Pat | C65: PERM | D65: 375629 | E65: ARLES | F65: VINZELL | G65: ROMANO | I65: =DATEDIF(J65,DATE(2026,4,30),"y")&" years, "&DATEDIF(J65,DATE(2026,4,30),"ym")&" month(s), "&DATEDIF(J65,DATE(2026,4,30),"md")&" day(s)" -> 29 years, 2 month(s), 6 day(s) | J65: 35485 | K65: =DATEDIF(L65,DATE(2026,4,30),"y")&" years, "&DATEDIF(L65,DATE(2026,4,30),"ym")&" month(s), "&DATEDIF(L65,DATE(2026,4,30),"md")&" day(s)" -> 3 years, 5 month(s), 16 day(s) | L65: 44879 | O65: ITPMD (PRO11) | P65: IT Project PNCO
A66: 58 | B66: NUP | C66: PERM | D66: 7 | E66: ARROYO | F66: CHRISTIAN | G66: REMOLADO | I66: =DATEDIF(J66,DATE(2026,4,30),"y")&" years, "&DATEDIF(J66,DATE(2026,4,30),"ym")&" month(s), "&DATEDIF(J66,DATE(2026,4,30),"md")&" day(s)" -> 40 years, 11 month(s), 27 day(s) | J66: 31170 | K66: =DATEDIF(L66,DATE(2026,4,30),"y")&" years, "&DATEDIF(L66,DATE(2026,4,30),"ym")&" month(s), "&DATEDIF(L66,DATE(2026,4,30),"md")&" day(s)" -> 3 years, 3 month(s), 21 day(s) | L66: 44935 | O66: TS, PTD | P66: Administrative Asst I/Training Staff (SG7)
A67: 59 | B67: Pat | C67: PERM | D67: 376379 | E67: ARROYO | F67: REYNALDO | G67: PASCO | H67: JR | I67: =DATEDIF(J67,DATE(2026,4,30),"y")&" years, "&DATEDIF(J67,DATE(2026,4,30),"ym")&" month(s), "&DATEDIF(J67,DATE(2026,4,30),"md")&" day(s)" -> 30 years, 0 month(s), 0 day(s) | J67: 35185 | K67: =DATEDIF(L67,DATE(2026,4,30),"y")&" years, "&DATEDIF(L67,DATE(2026,4,30),"ym")&" month(s), "&DATEDIF(L67,DATE(2026,4,30),"md")&" day(s)" -> 3 years, 4 month(s), 3 day(s) | L67: 44922 | O67: ITPMD (PRO10) | P67: IT Project PNCO
A68: 60 | B68: Pat | C68: PERM | D68: 375617 | E68: ASIRI | F68: DELFAIZA | G68: SARAJAN | I68: =DATEDIF(J68,DATE(2026,4,30),"y")&" years, "&DATEDIF(J68,DATE(2026,4,30),"ym")&" month(s), "&DATEDIF(J68,DATE(2026,4,30),"md")&" day(s)" -> 28 years, 6 month(s), 19 day(s) | J68: 35714 | K68: =DATEDIF(L68,DATE(2026,4,30),"y")&" years, "&DATEDIF(L68,DATE(2026,4,30),"ym")&" month(s), "&DATEDIF(L68,DATE(2026,4,30),"md")&" day(s)" -> 3 years, 5 month(s), 16 day(s) | L68: 44879 | O68: ITPMD (PRO9) | P68: IT Project PNCO
A69: 61 | B69: NUP | C69: PERM | D69: 14 | E69: AVENDAÑO | F69: MA. FRELIE JOY | G69: (no middle name) | I69: =DATEDIF(J69,DATE(2026,4,30),"y")&" years, "&DATEDIF(J69,DATE(2026,4,30),"ym")&" month(s), "&DATEDIF(J69,DATE(2026,4,30),"md")&" day(s)" -> 28 years, 7 month(s), 22 day(s) | J69: 35681 | K69: =DATEDIF(L69,DATE(2026,4,30),"y")&" years, "&DATEDIF(L69,DATE(2026,4,30),"ym")&" month(s), "&DATEDIF(L69,DATE(2026,4,30),"md")&" day(s)" -> 7 years, 4 month(s), 26 day(s) | L69: 43438 | O69: OD | P69: ISR II (SG14)
A70: 62 | B70: PSMS | C70: PERM | D70: 203704 | E70: AVILA | F70: CHRISTOPHER | G70: BALEÑA | I70: =DATEDIF(J70,DATE(2026,4,30),"y")&" years, "&DATEDIF(J70,DATE(2026,4,30),"ym")&" month(s), "&DATEDIF(J70,DATE(2026,4,30),"md")&" day(s)" -> 41 years, 9 month(s), 13 day(s) | J70: 30880 | K70: =DATEDIF(L70,DATE(2026,4,30),"y")&" years, "&DATEDIF(L70,DATE(2026,4,30),"ym")&" month(s), "&DATEDIF(L70,DATE(2026,4,30),"md")&" day(s)" -> 16 years, 2 month(s), 29 day(s) | L70: 40210 | O70: ITPMD (PRO8) | P70: IT Project PNCO
A71: 63 | B71: Pat | C71: PERM | D71: 376380 | E71: AYUPAN | F71: LAURENCE | G71: NOBLEZA | I71: =DATEDIF(J71,DATE(2026,4,30),"y")&" years, "&DATEDIF(J71,DATE(2026,4,30),"ym")&" month(s), "&DATEDIF(J71,DATE(2026,4,30),"md")&" day(s)" -> 28 years, 7 month(s), 17 day(s) | J71: 35686 | K71: =DATEDIF(L71,DATE(2026,4,30),"y")&" years, "&DATEDIF(L71,DATE(2026,4,30),"ym")&" month(s), "&DATEDIF(L71,DATE(2026,4,30),"md")&" day(s)" -> 3 years, 4 month(s), 3 day(s) | L71: 44922 | O71: DMD | P71: Duty PNCO
A72: 64 | B72: PCPT | C72: PERM | D72: O-36428 | E72: BABATE | F72: JAN NOEL | G72: ADUCA | I72: =DATEDIF(J72,DATE(2026,4,30),"y")&" years, "&DATEDIF(J72,DATE(2026,4,30),"ym")&" month(s), "&DATEDIF(J72,DATE(2026,4,30),"md")&" day(s)" -> 36 years, 3 month(s), 6 day(s) | J72: 32897 | K72: =DATEDIF(L72,DATE(2026,4,30),"y")&" years, "&DATEDIF(L72,DATE(2026,4,30),"ym")&" month(s), "&DATEDIF(L72,DATE(2026,4,30),"md")&" day(s)" -> 4 years, 7 month(s), 14 day(s) | L72: 44455 | M72: 42002 | O72: ITPMD (PRO2) | P72: IT Project Officer
A73: 65 | B73: Pat | C73: PERM | D73: 376381 | E73: BACATAN | F73: FERDINAND | G73: JALOVA | H73: JR | I73: =DATEDIF(J73,DATE(2026,4,30),"y")&" years, "&DATEDIF(J73,DATE(2026,4,30),"ym")&" month(s), "&DATEDIF(J73,DATE(2026,4,30),"md")&" day(s)" -> 29 years, 5 month(s), 19 day(s) | J73: 35380 | K73: =DATEDIF(L73,DATE(2026,4,30),"y")&" years, "&DATEDIF(L73,DATE(2026,4,30),"ym")&" month(s), "&DATEDIF(L73,DATE(2026,4,30),"md")&" day(s)" -> 3 years, 4 month(s), 3 day(s) | L73: 44922 | O73: ITPMD (OTDCA) | P73: IT Project PNCO
A74: 66 | B74: PLTCOL | C74: PERM | D74: O-20399 | E74: BACCAY | F74: PEDRO | G74: IQUIN | I74: =DATEDIF(J74,DATE(2026,4,30),"y")&" years, "&DATEDIF(J74,DATE(2026,4,30),"ym")&" month(s), "&DATEDIF(J74,DATE(2026,4,30),"md")&" day(s)" -> 52 years, 9 month(s), 0 day(s) | J74: 26875 | K74: =DATEDIF(L74,DATE(2026,4,30),"y")&" years, "&DATEDIF(L74,DATE(2026,4,30),"ym")&" month(s), "&DATEDIF(L74,DATE(2026,4,30),"md")&" day(s)" -> 17 years, 3 month(s), 25 day(s) | L74: 39818 | N74: 34335 | O74: ITPMD (PRO2) | P74: IT Project Officer
A75: 67 | B75: NUP | C75: PERM | D75: 8 | E75: BACLIG | F75: MICHAEL | G75: DELA CRUZ | I75: =DATEDIF(J75,DATE(2026,4,30),"y")&" years, "&DATEDIF(J75,DATE(2026,4,30),"ym")&" month(s), "&DATEDIF(J75,DATE(2026,4,30),"md")&" day(s)" -> 50 years, 11 month(s), 22 day(s) | J75: 27522 | K75: =DATEDIF(L75,DATE(2026,4,30),"y")&" years, "&DATEDIF(L75,DATE(2026,4,30),"ym")&" month(s), "&DATEDIF(L75,DATE(2026,4,30),"md")&" day(s)" -> 26 years, 0 month(s), 12 day(s) | L75: 36634 | O75: HMS, ITSD | P75: Administrative Assistant I(SG7)
A76: 68 | B76: NUP | C76: PERM | D76: 8 | E76: BACLIG | F76: NEILJANE | G76: ADONA | I76: =DATEDIF(J76,DATE(2026,4,30),"y")&" years, "&DATEDIF(J76,DATE(2026,4,30),"ym")&" month(s), "&DATEDIF(J76,DATE(2026,4,30),"md")&" day(s)" -> 44 years, 3 month(s), 29 day(s) | J76: 29952 | K76: =DATEDIF(L76,DATE(2026,4,30),"y")&" years, "&DATEDIF(L76,DATE(2026,4,30),"ym")&" month(s), "&DATEDIF(L76,DATE(2026,4,30),"md")&" day(s)" -> 14 years, 6 month(s), 16 day(s) | L76: 40830 | O76: ICRMS, ARMD | P76: ICRMIS Staff (SG8)
A77: 69 | B77: NUP | C77: PERM | D77: 12 | E77: BAGO | F77: REBECCA | G77: LLANEZA | I77: =DATEDIF(J77,DATE(2026,4,30),"y")&" years, "&DATEDIF(J77,DATE(2026,4,30),"ym")&" month(s), "&DATEDIF(J77,DATE(2026,4,30),"md")&" day(s)" -> 63 years, 10 month(s), 24 day(s) | J77: 22803 | K77: =DATEDIF(L77,DATE(2026,4,30),"y")&" years, "&DATEDIF(L77,DATE(2026,4,30),"ym")&" month(s), "&DATEDIF(L77,DATE(2026,4,30),"md")&" day(s)" -> 41 years, 3 month(s), 29 day(s) | L77: 31048 | O77: ODDIT | P77: Administrative Assistant VI (SG12)
A78: 70 | B78: NUP | C78: PERM | D78: 7 | E78: BAJAMONDE | F78: CHRISTIAN JOHN | G78: PLAZA | I78: =DATEDIF(J78,DATE(2026,4,30),"y")&" years, "&DATEDIF(J78,DATE(2026,4,30),"ym")&" month(s), "&DATEDIF(J78,DATE(2026,4,30),"md")&" day(s)" -> 32 years, 4 month(s), 8 day(s) | J78: 34325 | K78: =DATEDIF(L78,DATE(2026,4,30),"y")&" years, "&DATEDIF(L78,DATE(2026,4,30),"ym")&" month(s), "&DATEDIF(L78,DATE(2026,4,30),"md")&" day(s)" -> 1 years, 1 month(s), 13 day(s) | L78: 45733 | O78: QAS, SMD | P78: Computer Programmer(SG7)
A79: 71 | B79: PCpl | C79: PERM | D79: 311628 | E79: BALDERAMA | F79: HARLEY | G79: GALANG | I79: =DATEDIF(J79,DATE(2026,4,30),"y")&" years, "&DATEDIF(J79,DATE(2026,4,30),"ym")&" month(s), "&DATEDIF(J79,DATE(2026,4,30),"md")&" day(s)" -> 34 years, 2 month(s), 2 day(s) | J79: 33662 | K79: =DATEDIF(L79,DATE(2026,4,30),"y")&" years, "&DATEDIF(L79,DATE(2026,4,30),"ym")&" month(s), "&DATEDIF(L79,DATE(2026,4,30),"md")&" day(s)" -> 8 years, 7 month(s), 14 day(s) | L79: 42994 | O79: ITPMD (PRO4B) | P79: IT Project PNCO
A80: 72 | B80: Pat | C80: PERM | D80: 375973 | E80: BALDOS | F80: MARK ANTHONY | G80: BUNGAG | I80: =DATEDIF(J80,DATE(2026,4,30),"y")&" years, "&DATEDIF(J80,DATE(2026,4,30),"ym")&" month(s), "&DATEDIF(J80,DATE(2026,4,30),"md")&" day(s)" -> 29 years, 3 month(s), 2 day(s) | J80: 35458 | K80: =DATEDIF(L80,DATE(2026,4,30),"y")&" years, "&DATEDIF(L80,DATE(2026,4,30),"ym")&" month(s), "&DATEDIF(L80,DATE(2026,4,30),"md")&" day(s)" -> 3 years, 4 month(s), 25 day(s) | L80: 44900 | O80: ITPMD (FS) | P80: IT Project PNCO
A81: 73 | B81: PCPT | C81: PERM | D81: O-36668 | E81: BALICAG | F81: JOSE | G81: DAKETAN | I81: =DATEDIF(J81,DATE(2026,4,30),"y")&" years, "&DATEDIF(J81,DATE(2026,4,30),"ym")&" month(s), "&DATEDIF(J81,DATE(2026,4,30),"md")&" day(s)" -> 36 years, 11 month(s), 7 day(s) | J81: 32651 | K81: =DATEDIF(L81,DATE(2026,4,30),"y")&" years, "&DATEDIF(L81,DATE(2026,4,30),"ym")&" month(s), "&DATEDIF(L81,DATE(2026,4,30),"md")&" day(s)" -> 4 years, 5 month(s), 26 day(s) | L81: 44504 | M81: 42278 | O81: ITPMD (CSG-FEO) | P81: IT Project Officer
A82: 74 | B82: PMSg | C82: PERM | D82: 207837 | E82: BALINGIT | F82: JOSE JEFFERSON | G82: LACSAM | H82: II | I82: =DATEDIF(J82,DATE(2026,4,30),"y")&" years, "&DATEDIF(J82,DATE(2026,4,30),"ym")&" month(s), "&DATEDIF(J82,DATE(2026,4,30),"md")&" day(s)" -> 43 years, 4 month(s), 20 day(s) | J82: 30295 | K82: =DATEDIF(L82,DATE(2026,4,30),"y")&" years, "&DATEDIF(L82,DATE(2026,4,30),"ym")&" month(s), "&DATEDIF(L82,DATE(2026,4,30),"md")&" day(s)" -> 15 years, 4 month(s), 29 day(s) | L82: 40513 | O82: ITPMD (FS) | P82: IT Project PNCO
A83: 75 | B83: PCPT | C83: PERM | D83: O-36429 | E83: BALLENAS | F83: ROBERTO | G83: ALPAS | H83: JR | I83: =DATEDIF(J83,DATE(2026,4,30),"y")&" years, "&DATEDIF(J83,DATE(2026,4,30),"ym")&" month(s), "&DATEDIF(J83,DATE(2026,4,30),"md")&" day(s)" -> 33 years, 6 month(s), 2 day(s) | J83: 33905 | K83: =DATEDIF(L83,DATE(2026,4,30),"y")&" years, "&DATEDIF(L83,DATE(2026,4,30),"ym")&" month(s), "&DATEDIF(L83,DATE(2026,4,30),"md")&" day(s)" -> 4 years, 7 month(s), 14 day(s) | L83: 44455 | M83: 43759 | O83: ITPMD (DC) | P83: IT Project Officer
A84: 76 | B84: PCPT | C84: PERM | D84: O-36430 | E84: BALLESTEROS | F84: MHARK | G84: VISTA | I84: =DATEDIF(J84,DATE(2026,4,30),"y")&" years, "&DATEDIF(J84,DATE(2026,4,30),"ym")&" month(s), "&DATEDIF(J84,DATE(2026,4,30),"md")&" day(s)" -> 32 years, 11 month(s), 8 day(s) | J84: 34111 | K84: =DATEDIF(L84,DATE(2026,4,30),"y")&" years, "&DATEDIF(L84,DATE(2026,4,30),"ym")&" month(s), "&DATEDIF(L84,DATE(2026,4,30),"md")&" day(s)" -> 4 years, 7 month(s), 14 day(s) | L84: 44455 | M84: 42690 | O84: ITPMD (PNPTI/PNPTS) | P84: IT Project Officer
A85: 77 | B85: PLTCOL | C85: PERM | D85: O-16840 | E85: BALMACEDA | F85: ROMMEL | G85: BANGUILAN | I85: =DATEDIF(J85,DATE(2026,4,30),"y")&" years, "&DATEDIF(J85,DATE(2026,4,30),"ym")&" month(s), "&DATEDIF(J85,DATE(2026,4,30),"md")&" day(s)" -> 52 years, 7 month(s), 18 day(s) | J85: 26919 | K85: =DATEDIF(L85,DATE(2026,4,30),"y")&" years, "&DATEDIF(L85,DATE(2026,4,30),"ym")&" month(s), "&DATEDIF(L85,DATE(2026,4,30),"md")&" day(s)" -> 21 years, 7 month(s), 24 day(s) | L85: 38236 | O85: BFS, ARMD | P85: C, Budget and Fiscal Section
A86: 78 | B86: PCPT | C86: PERM | D86: O-36729 | E86: BALON | F86: PHIL JUERGEN | G86: ILAN | I86: =DATEDIF(J86,DATE(2026,4,30),"y")&" years, "&DATEDIF(J86,DATE(2026,4,30),"ym")&" month(s), "&DATEDIF(J86,DATE(2026,4,30),"md")&" day(s)" -> 36 years, 8 month(s), 1 day(s) | J86: 32749 | K86: =DATEDIF(L86,DATE(2026,4,30),"y")&" years, "&DATEDIF(L86,DATE(2026,4,30),"ym")&" month(s), "&DATEDIF(L86,DATE(2026,4,30),"md")&" day(s)" -> 4 years, 5 month(s), 26 day(s) | L86: 44504 | M86: 43759 | O86: ITPMD (IMEG) | P86: IT Project Officer
A87: 79 | B87: NUP | C87: PERM | D87: 22 | E87: BALONGOY | F87: RONALYN | G87: SOLDEVILLA | I87: =DATEDIF(J87,DATE(2026,4,30),"y")&" years, "&DATEDIF(J87,DATE(2026,4,30),"ym")&" month(s), "&DATEDIF(J87,DATE(2026,4,30),"md")&" day(s)" -> 48 years, 10 month(s), 29 day(s) | J87: 28277 | K87: =DATEDIF(L87,DATE(2026,4,30),"y")&" years, "&DATEDIF(L87,DATE(2026,4,30),"ym")&" month(s), "&DATEDIF(L87,DATE(2026,4,30),"md")&" day(s)" -> 21 years, 10 month(s), 16 day(s) | L87: 38152 | O87: PTD | P87: Asst. Chief, PTD (SG22)
A88: 80 | B88: NUP | C88: PERM | D88: 12 | E88: BALUCANAG | F88: GRACE | G88: EBARSABAL | I88: =DATEDIF(J88,DATE(2026,4,30),"y")&" years, "&DATEDIF(J88,DATE(2026,4,30),"ym")&" month(s), "&DATEDIF(J88,DATE(2026,4,30),"md")&" day(s)" -> 46 years, 1 month(s), 13 day(s) | J88: 29297 | K88: =DATEDIF(L88,DATE(2026,4,30),"y")&" years, "&DATEDIF(L88,DATE(2026,4,30),"ym")&" month(s), "&DATEDIF(L88,DATE(2026,4,30),"md")&" day(s)" -> 19 years, 2 month(s), 4 day(s) | L88: 39139 | O88: DWBIS, DMD | P88: Researcher (SG12)
A89: 81 | B89: PMAJ | C89: PERM | D89: O-29040 | E89: BANDULA | F89: MARIA GERLYINES | G89: CABRERA | I89: =DATEDIF(J89,DATE(2026,4,30),"y")&" years, "&DATEDIF(J89,DATE(2026,4,30),"ym")&" month(s), "&DATEDIF(J89,DATE(2026,4,30),"md")&" day(s)" -> 46 years, 10 month(s), 10 day(s) | J89: 29026 | K89: =DATEDIF(L89,DATE(2026,4,30),"y")&" years, "&DATEDIF(L89,DATE(2026,4,30),"ym")&" month(s), "&DATEDIF(L89,DATE(2026,4,30),"md")&" day(s)" -> 8 years, 2 month(s), 14 day(s) | L89: 43147 | M89: 37989 | O89: ITPMD (PRO3) | P89: IT Project Officer
A90: 82 | B90: PCPT | C90: PERM | D90: O-31677 | E90: BANTIC | F90: JUVENAL | G90: PULINNEK | I90: =DATEDIF(J90,DATE(2026,4,30),"y")&" years, "&DATEDIF(J90,DATE(2026,4,30),"ym")&" month(s), "&DATEDIF(J90,DATE(2026,4,30),"md")&" day(s)" -> 48 years, 10 month(s), 17 day(s) | J90: 28289 | K90: =DATEDIF(L90,DATE(2026,4,30),"y")&" years, "&DATEDIF(L90,DATE(2026,4,30),"ym")&" month(s), "&DATEDIF(L90,DATE(2026,4,30),"md")&" day(s)" -> 7 years, 1 month(s), 12 day(s) | L90: 43542 | M90: 39600 | O90: ITPMD (PRO1) | P90: IT Project Officer
A91: 83 | B91: PLT | C91: PERM | D91: O-37885 | E91: BANTIYAN | F91: JEFTER | G91: PAKID | I91: =DATEDIF(J91,DATE(2026,4,30),"y")&" years, "&DATEDIF(J91,DATE(2026,4,30),"ym")&" month(s), "&DATEDIF(J91,DATE(2026,4,30),"md")&" day(s)" -> 33 years, 9 month(s), 24 day(s) | J91: 33791 | K91: =DATEDIF(L91,DATE(2026,4,30),"y")&" years, "&DATEDIF(L91,DATE(2026,4,30),"ym")&" month(s), "&DATEDIF(L91,DATE(2026,4,30),"md")&" day(s)" -> 6 years, 6 month(s), 9 day(s) | L91: 43759 | O91: ITPMD (DET) | P91: IT Project Officer
A92: 84 | B92: Pat | C92: PERM | D92: 376383 | E92: BARQUIN | F92: CHRISTIAN PAUL | G92: SAN VICENTE | I92: =DATEDIF(J92,DATE(2026,4,30),"y")&" years, "&DATEDIF(J92,DATE(2026,4,30),"ym")&" month(s), "&DATEDIF(J92,DATE(2026,4,30),"md")&" day(s)" -> 30 years, 2 month(s), 11 day(s) | J92: 35114 | K92: =DATEDIF(L92,DATE(2026,4,30),"y")&" years, "&DATEDIF(L92,DATE(2026,4,30),"ym")&" month(s), "&DATEDIF(L92,DATE(2026,4,30),"md")&" day(s)" -> 3 years, 4 month(s), 3 day(s) | L92: 44922 | O92: LS, ARMD | P92: Action PNCO
A93: 85 | B93: PCPT | C93: PERM | D93: O-31678 | E93: BATALLER | F93: SHERWIN SOLOMON | G93: BELLEN | H93: III | I93: =DATEDIF(J93,DATE(2026,4,30),"y")&" years, "&DATEDIF(J93,DATE(2026,4,30),"ym")&" month(s), "&DATEDIF(J93,DATE(2026,4,30),"md")&" day(s)" -> 44 years, 7 month(s), 6 day(s) | J93: 29853 | K93: =DATEDIF(L93,DATE(2026,4,30),"y")&" years, "&DATEDIF(L93,DATE(2026,4,30),"ym")&" month(s), "&DATEDIF(L93,DATE(2026,4,30),"md")&" day(s)" -> 7 years, 1 month(s), 12 day(s) | L93: 43542 | M93: 37830 | O93: PHAS (DITCM) | P93: IT Officer
A94: 86 | B94: PCPT | C94: PERM | D94: O-36716 | E94: BATBAT | F94: MATT KYNNPEARL | G94: CABURATAN | I94: =DATEDIF(J94,DATE(2026,4,30),"y")&" years, "&DATEDIF(J94,DATE(2026,4,30),"ym")&" month(s), "&DATEDIF(J94,DATE(2026,4,30),"md")&" day(s)" -> 30 years, 10 month(s), 6 day(s) | J94: 34874 | K94: =DATEDIF(L94,DATE(2026,4,30),"y")&" years, "&DATEDIF(L94,DATE(2026,4,30),"ym")&" month(s), "&DATEDIF(L94,DATE(2026,4,30),"md")&" day(s)" -> 4 years, 5 month(s), 26 day(s) | L94: 44504 | M94: 43395 | O94: ITPMD (PRO10) | P94: IT Project Officer
A95: 87 | B95: NUP | C95: PERM | D95: 7 | E95: BATICADOS | F95: IVY | G95: ELEGARLE | I95: =DATEDIF(J95,DATE(2026,4,30),"y")&" years, "&DATEDIF(J95,DATE(2026,4,30),"ym")&" month(s), "&DATEDIF(J95,DATE(2026,4,30),"md")&" day(s)" -> 27 years, 10 month(s), 13 day(s) | J95: 35963 | K95: =DATEDIF(L95,DATE(2026,4,30),"y")&" years, "&DATEDIF(L95,DATE(2026,4,30),"ym")&" month(s), "&DATEDIF(L95,DATE(2026,4,30),"md")&" day(s)" -> 6 years, 4 month(s), 14 day(s) | L95: 43815 | O95: LS, ARMD | P95: Action NUP (SG7)
A96: 88 | B96: PLTCOL | C96: PERM | D96: O-22469 | E96: BAUSA | F96: RIQUE | G96: ARCOS | I96: =DATEDIF(J96,DATE(2026,4,30),"y")&" years, "&DATEDIF(J96,DATE(2026,4,30),"ym")&" month(s), "&DATEDIF(J96,DATE(2026,4,30),"md")&" day(s)" -> 48 years, 9 month(s), 8 day(s) | J96: 28328 | K96: =DATEDIF(L96,DATE(2026,4,30),"y")&" years, "&DATEDIF(L96,DATE(2026,4,30),"ym")&" month(s), "&DATEDIF(L96,DATE(2026,4,30),"md")&" day(s)" -> 16 years, 7 month(s), 14 day(s) | L96: 40072 | O96: PHAS (RICTMD PRO5) | P96: Asst Chief, RICTMD
A97: 89 | B97: PSMS | C97: PERM | D97: 207819 | E97: BAUTISTA | F97: CESAR | G97: ESCARZA | I97: =DATEDIF(J97,DATE(2026,4,30),"y")&" years, "&DATEDIF(J97,DATE(2026,4,30),"ym")&" month(s), "&DATEDIF(J97,DATE(2026,4,30),"md")&" day(s)" -> 37 years, 8 month(s), 29 day(s) | J97: 32356 | K97: =DATEDIF(L97,DATE(2026,4,30),"y")&" years, "&DATEDIF(L97,DATE(2026,4,30),"ym")&" month(s), "&DATEDIF(L97,DATE(2026,4,30),"md")&" day(s)" -> 15 years, 9 month(s), 29 day(s) | L97: 40360 | O97: ITPMD (PRO10) | P97: IT Project PNCO
A98: 90 | B98: NUP | C98: PERM | D98: 6 | E98: BAUZON | F98: KIETHEL | G98: CALAQUIAN | I98: =DATEDIF(J98,DATE(2026,4,30),"y")&" years, "&DATEDIF(J98,DATE(2026,4,30),"ym")&" month(s), "&DATEDIF(J98,DATE(2026,4,30),"md")&" day(s)" -> 28 years, 7 month(s), 17 day(s) | J98: 35686 | K98: =DATEDIF(L98,TODAY(),"y")&" years, "&DATEDIF(L98,TODAY(),"ym")&" month(s), "&DATEDIF(L98,TODAY(),"md")&" day(s)" -> 0 years, 1 month(s), 10 day(s) | L98: 46232 | O98: DMD | P98: Administrative Aide VI (SG6)
A99: 91 | B99: PCPT | C99: PERM | D99: O-31681 | E99: BAYAUA | F99: ANGELO | G99: ZALUN | I99: =DATEDIF(J99,DATE(2026,4,30),"y")&" years, "&DATEDIF(J99,DATE(2026,4,30),"ym")&" month(s), "&DATEDIF(J99,DATE(2026,4,30),"md")&" day(s)" -> 40 years, 2 month(s), 19 day(s) | J99: 31454 | K99: =DATEDIF(L99,DATE(2026,4,30),"y")&" years, "&DATEDIF(L99,DATE(2026,4,30),"ym")&" month(s), "&DATEDIF(L99,DATE(2026,4,30),"md")&" day(s)" -> 7 years, 1 month(s), 12 day(s) | L99: 43542 | M99: 40513 | O99: ITSD | P99: Duty PCO
A100: 92 | B100: Pat | C100: PERM | D100: 376384 | E100: BEJARIN | F100: GERALD | G100: DADIRO | I100: =DATEDIF(J100,DATE(2026,4,30),"y")&" years, "&DATEDIF(J100,DATE(2026,4,30),"ym")&" month(s), "&DATEDIF(J100,DATE(2026,4,30),"md")&" day(s)" -> 32 years, 11 month(s), 8 day(s) | J100: 34111 | K100: =DATEDIF(L100,DATE(2026,4,30),"y")&" years, "&DATEDIF(L100,DATE(2026,4,30),"ym")&" month(s), "&DATEDIF(L100,DATE(2026,4,30),"md")&" day(s)" -> 3 years, 4 month(s), 3 day(s) | L100: 44922 | O100: OD | P100: Duty PNCO
A101: 93 | B101: PMAJ | C101: PERM | D101: O-29035 | E101: BELLY | F101: JOCELYN | G101: DEL BARRIO | I101: =DATEDIF(J101,DATE(2026,4,30),"y")&" years, "&DATEDIF(J101,DATE(2026,4,30),"ym")&" month(s), "&DATEDIF(J101,DATE(2026,4,30),"md")&" day(s)" -> 49 years, 4 month(s), 21 day(s) | J101: 28103 | K101: =DATEDIF(L101,DATE(2026,4,30),"y")&" years, "&DATEDIF(L101,DATE(2026,4,30),"ym")&" month(s), "&DATEDIF(L101,DATE(2026,4,30),"md")&" day(s)" -> 8 years, 2 month(s), 14 day(s) | L101: 43147 | M101: 38299 | O101: PHAS(DICTM) | P101: IT Officer
...

Sheet 15 YRS LENGTH OF SERVICE
A2: NO. | B2: RANK | C2: STATUS | D2: BADGE NO/SG | E2: LAST NAME | F2: FIRST NAME | G2: MIDDLE NAME | H2: QUAL. | I2: AGE TO DATE | J2: Birthdate | K2: LENGTH OF SERVICE TO DATE | L2: DES (UP) | M2: REMARKS
A3: 1 | B3: NUP | C3: PERM | D3: 7 | E3: ACORDA | F3: ELPIDIO | G3: PALARCA | I3: 62 years, 10 month(s), 13 day(s) | J3: 23060 | K3: =DATEDIF(L3,DATE(2025,9,30),"y")&" years, "&DATEDIF(L3,DATE(2025,9,30),"ym")&" month(s), "&DATEDIF(L3,DATE(2025,9,30),"md")&" day(s)" -> 43 years, 4 month(s), 29 day(s) | L3: 30072 | N3: ICRMS, ARMD | O3: Admin Asst/Liaison (SG7)
A4: 2 | B4: PCpl | C4: PERM | D4: 196791 | E4: AGGARAO | F4: ALBERTO | G4: CALLANGAN | I4: 42 years, 6 month(s), 14 day(s) | J4: 30484 | K4: =DATEDIF(L4,DATE(2025,9,30),"y")&" years, "&DATEDIF(L4,DATE(2025,9,30),"ym")&" month(s), "&DATEDIF(L4,DATE(2025,9,30),"md")&" day(s)" -> 16 years, 2 month(s), 29 day(s) | L4: 39995 | N4: OCS | O4: Action PNCO
A5: 3 | B5: PLTCOL | C5: PERM | D5: O-22470 | E5: AGUS | F5: CARCIOLO | G5: CAJANDAB | H5: JR | I5: 51 years, 10 month(s), 3 day(s) | J5: 27088 | K5: =DATEDIF(L5,DATE(2025,9,30),"y")&" years, "&DATEDIF(L5,DATE(2025,9,30),"ym")&" month(s), "&DATEDIF(L5,DATE(2025,9,30),"md")&" day(s)" -> 22 years, 4 month(s), 14 day(s) | L5: 37757 | N5: ITPMD (NCRPO) | O5: IT Project Officer
A6: 4 | B6: PLTCOL | C6: PERM | D6: O-22471 | E6: ALABADO | F6: AURELIO | G6: PERITO | I6: 48 years, 0 month(s), 12 day(s) | J6: 28478 | K6: =DATEDIF(L6,DATE(2025,9,30),"y")&" years, "&DATEDIF(L6,DATE(2025,9,30),"ym")&" month(s), "&DATEDIF(L6,DATE(2025,9,30),"md")&" day(s)" -> 22 years, 2 month(s), 2 day(s) | L6: 37830 | N6: ITPMD (PRO8) | O6: IT Project Officer
A7: 5 | B7: NUP | C7: PERM | D7: 9 | E7: ALFONSO | F7: IRANIE | G7: EMPENO | I7: 58 years, 10 month(s), 16 day(s) | J7: 24518 | K7: =DATEDIF(L7,DATE(2025,9,30),"y")&" years, "&DATEDIF(L7,DATE(2025,9,30),"ym")&" month(s), "&DATEDIF(L7,DATE(2025,9,30),"md")&" day(s)" -> 33 years, 8 month(s), 29 day(s) | L7: 33604 | N7: PHAS(DICTM) | O7: Administrative Assistant III (SG9)
A8: 6 | B8: PCOL | C8: PERM | D8: O-12566 | E8: ALI | F8: AMIR HASSAN | G8: RAMOS | I8: 46 years, 3 month(s), 3 day(s) | J8: 29126 | K8: =DATEDIF(L8,DATE(2025,9,30),"y")&" years, "&DATEDIF(L8,DATE(2025,9,30),"ym")&" month(s), "&DATEDIF(L8,DATE(2025,9,30),"md")&" day(s)" -> 24 years, 10 month(s), 3 day(s) | L8: 36857 | N8: PHAS (PNPA) | O8: Chief, ICTMD, PNPA
A9: 7 | B9: PCOL | C9: PERM | D9: O-13539 | E9: ALI | F9: SHIRLEY MAE | G9: SALVADOR | I9: 47 years, 3 month(s), 12 day(s) | J9: 28752 | K9: =DATEDIF(L9,DATE(2025,9,30),"y")&" years, "&DATEDIF(L9,DATE(2025,9,30),"ym")&" month(s), "&DATEDIF(L9,DATE(2025,9,30),"md")&" day(s)" -> 23 years, 10 month(s), 24 day(s) | L9: 37201 | N9: PTD | O9: Chief, PTD
A10: 8 | B10: NUP | C10: PERM | D10: 12 | E10: ALMACHAR | F10: ARLENE | G10: ACIERTO | I10: 53 years, 3 month(s), 4 day(s) | J10: 26569 | K10: =DATEDIF(L10,DATE(2025,9,30),"y")&" years, "&DATEDIF(L10,DATE(2025,9,30),"ym")&" month(s), "&DATEDIF(L10,DATE(2025,9,30),"md")&" day(s)" -> 27 years, 6 month(s), 14 day(s) | L10: 35870 | M10: from DPRM | N10: AISS, SMD | O10: ISA/ISR (SG12)
A11: 9 | B11: PLTCOL | C11: PERM | D11: O-16853 | E11: AN | F11: SANTI RAYMUND | G11: NEVADO | I11: 47 years, 5 month(s), 21 day(s) | J11: 28681 | K11: =DATEDIF(L11,DATE(2025,9,30),"y")&" years, "&DATEDIF(L11,DATE(2025,9,30),"ym")&" month(s), "&DATEDIF(L11,DATE(2025,9,30),"md")&" day(s)" -> 21 years, 0 month(s), 24 day(s) | L11: 38236 | N11: ITPMD (PRO4B) | O11: IT Project Officer
A12: 10 | B12: PLTCOL | C12: PERM | D12: O-16848 | E12: ANDRES | F12: JOSE WILSON | G12: HACIÑAS | I12: 47 years, 9 month(s), 0 day(s) | J12: 28580 | K12: =DATEDIF(L12,DATE(2025,9,30),"y")&" years, "&DATEDIF(L12,DATE(2025,9,30),"ym")&" month(s), "&DATEDIF(L12,DATE(2025,9,30),"md")&" day(s)" -> 21 years, 0 month(s), 24 day(s) | L12: 38236 | N12: ITPMD (PRO3) | O12: IT Project Officer
A13: 11 | B13: PLTCOL | C13: PERM | D13: O-20596 | E13: ANUNCIO | F13: ALEJANDER | G13: TALAMPAS | I13: 51 years, 7 month(s), 16 day(s) | J13: 27164 | K13: =DATEDIF(L13,DATE(2025,9,30),"y")&" years, "&DATEDIF(L13,DATE(2025,9,30),"ym")&" month(s), "&DATEDIF(L13,DATE(2025,9,30),"md")&" day(s)" -> 17 years, 0 month(s), 29 day(s) | L13: 39692 | N13: PHAS (RICTMD NCRPO) | O13: Asst Chief, RICTMD
A14: 12 | B14: PLTCOL | C14: PERM | D14: O-16857 | E14: AQUINO | F14: JOHANNES GOLD | G14: LUCERO | I14: 45 years, 11 month(s), 26 day(s) | J14: 29225 | K14: =DATEDIF(L14,DATE(2025,9,30),"y")&" years, "&DATEDIF(L14,DATE(2025,9,30),"ym")&" month(s), "&DATEDIF(L14,DATE(2025,9,30),"md")&" day(s)" -> 21 years, 0 month(s), 14 day(s) | L14: 38246 | N14: LS/IHSSPRO12 | O14: C, Logistics/C,IHSS /IT Project Officer
A15: 13 | B15: PSMS | C15: PERM | D15: 203704 | E15: AVILA | F15: CHRISTOPHER | G15: BALEÑA | I15: 41 years, 5 month(s), 14 day(s) | J15: 30880 | K15: =DATEDIF(L15,DATE(2025,9,30),"y")&" years, "&DATEDIF(L15,DATE(2025,9,30),"ym")&" month(s), "&DATEDIF(L15,DATE(2025,9,30),"md")&" day(s)" -> 15 years, 7 month(s), 29 day(s) | L15: 40210 | N15: ITPMD (PRO8) | O15: IT Project PNCO
A16: 14 | B16: PLTCOL | C16: PERM | D16: O-20399 | E16: BACCAY | F16: PEDRO | G16: IQUIN | I16: 52 years, 5 month(s), 1 day(s) | J16: 26875 | K16: =DATEDIF(L16,DATE(2025,9,30),"y")&" years, "&DATEDIF(L16,DATE(2025,9,30),"ym")&" month(s), "&DATEDIF(L16,DATE(2025,9,30),"md")&" day(s)" -> 16 years, 8 month(s), 25 day(s) | L16: 39818 | N16: ITPMD (PRO2) | O16: IT Project Officer
A17: 15 | B17: NUP | C17: PERM | D17: 7 | E17: BACLIG | F17: MICHAEL | G17: DELA CRUZ | I17: 50 years, 7 month(s), 23 day(s) | J17: 27522 | K17: =DATEDIF(L17,DATE(2025,9,30),"y")&" years, "&DATEDIF(L17,DATE(2025,9,30),"ym")&" month(s), "&DATEDIF(L17,DATE(2025,9,30),"md")&" day(s)" -> 24 years, 9 month(s), 13 day(s) | L17: 36877 | N17: HMS, ITSD | O17: Administrative Assistant I(SG7)
A18: 16 | B18: NUP | C18: PERM | D18: 12 | E18: BAGO | F18: REBECCA | G18: LLANEZA | I18: 63 years, 6 month(s), 25 day(s) | J18: 22803 | K18: =DATEDIF(L18,DATE(2025,9,30),"y")&" years, "&DATEDIF(L18,DATE(2025,9,30),"ym")&" month(s), "&DATEDIF(L18,DATE(2025,9,30),"md")&" day(s)" -> 40 years, 8 month(s), 29 day(s) | L18: 31048 | N18: ODDIT | O18: Administrative Assistant VI (SG12)
A19: 17 | B19: PLTCOL | C19: PERM | D19: O-16840 | E19: BALMACEDA | F19: ROMMEL | G19: BANGUILAN | I19: 52 years, 3 month(s), 19 day(s) | J19: 26919 | K19: =DATEDIF(L19,DATE(2025,9,30),"y")&" years, "&DATEDIF(L19,DATE(2025,9,30),"ym")&" month(s), "&DATEDIF(L19,DATE(2025,9,30),"md")&" day(s)" -> 21 years, 0 month(s), 24 day(s) | L19: 38236 | N19: BFS, ARMD | O19: C, Budget and Fiscal Section
A20: 18 | B20: NUP | C20: PERM | D20: 22 | E20: BALONGOY | F20: RONALYN | G20: SOLDEVILLA | I20: 48 years, 6 month(s), 30 day(s) | J20: 28277 | K20: =DATEDIF(L20,DATE(2025,9,30),"y")&" years, "&DATEDIF(L20,DATE(2025,9,30),"ym")&" month(s), "&DATEDIF(L20,DATE(2025,9,30),"md")&" day(s)" -> 21 years, 3 month(s), 16 day(s) | L20: 38152 | N20: PTD | O20: Asst. Chief, PTD (SG22)
A21: 19 | B21: NUP | C21: PERM | D21: 12 | E21: BALUCANAG | F21: GRACE | G21: EBARSABAL | I21: 45 years, 9 month(s), 14 day(s) | J21: 29297 | K21: =DATEDIF(L21,DATE(2025,9,30),"y")&" years, "&DATEDIF(L21,DATE(2025,9,30),"ym")&" month(s), "&DATEDIF(L21,DATE(2025,9,30),"md")&" day(s)" -> 18 years, 7 month(s), 4 day(s) | L21: 39139 | M21: from DO | N21: DWBIS, DMD | O21: Researcher (SG12)
A22: 20 | B22: PLTCOL | C22: PERM | D22: O-22469 | E22: BAUSA | F22: RIQUE | G22: ARCOS | I22: 48 years, 5 month(s), 9 day(s) | J22: 28328 | K22: =DATEDIF(L22,DATE(2025,9,30),"y")&" years, "&DATEDIF(L22,DATE(2025,9,30),"ym")&" month(s), "&DATEDIF(L22,DATE(2025,9,30),"md")&" day(s)" -> 16 years, 0 month(s), 14 day(s) | L22: 40072 | N22: PHAS (RICTMD PRO5) | O22: Asst Chief, RICTMD
